Workbook

Sheet 1°K
F1: Centro de Investigación Educativa Colegio San Diego | S1: ACEPTADOS POR CORPORATIVO
F2: Punta el Campanario #183 Col. Bahia de San Martín CP 96536 | S2: PAGOS DE HIJOS DE MAESTROS
F3: PREESCOLAR 30PJN1037Z PRIMARIA 30PPR3773B SECUNDARIA 30PES0033G | S3: MES PAGADO
D4: FACTURA | F4: CICLO ESCOLAR 2024-2025 | S4: ALUMNO DADO DE BAJA
S5: IRRIGULARIDADES
B7: N° | C7: MATRICULA | D7: NOMBRE DEL ALUMNO | E7: PROMOCION | F7: INSCRIPCION | G7: FOLIO | H7: FECHA | I7: MATERIAL | J7: FECHA | K7: FOLIO | L7: ARANCEL | M7: FECHA | N7: FOLIO | O7: LIBROS | P7: FECHA | Q7: FOLIO | R7: UNIFORMES | S7: FECHA | T7: FOLIO | U7: PLAN PAGO | V7: BECA | W7: COLEG | X7: 10 meses
A8: 921 173 2609 | B8: FALTA DE FIRMAR | C8: NUEVO INGRESO | D8: ADRIAN GABRIEL CASTELLANOS VARGAS | E8: ENERO-FEBRERO | F8: GRATIS | G8: GRATIS | H8: 45728 | I8: 2990 | J8: 45728 | K8: 30065 | L8: 2390 | M8: 45728 | N8: 030065 | O8: 3900 | P8: 45798 | Q8: 023933 | U8: 10 MESES | V8: 0.3 | W8: 2394
A9: 921 291 0428 | B9: FIRMO DOCUMENTOS | C9: NUEVO INGRESO | D9: ELIAS DANIEL CRUZ LOPEZ | E9: MARZO-JUNIO | F9: GRATIS | G9: GRATIS | H9: 45825 | I9: 2093 | J9: 45825 | K9: 63415250 | L9: 1673 | M9: 45825 | N9: 63415250 | O9: 1980 | P9: 45903 | Q9: 3012346
A10: 921 280 1194 | C10: NUEVO INGRESO | D10: HELENA POBLETE PEÑA | E10: MARZO-JUNIO | F10: GRATIS | G10: GRATIS | H10: 45895 | I10: 1195 | J10: 45895 | K10: 692208 | L10: 1245 | M10: 45895 | N10: 692208 | U10: 12 MESES | V10: 0.3 | W10: 1852
Z13: 7213
B19: COLEGIATURA
B20: N° | C20: MATRICULA | D20: NOMBRE DEL ALUMNO | E20: AGOSTO | H20: SEPTIEMBRE | K20: OCTUBRE | N20: NOVIEMBRE | Q20: DICIEMBRE | T20: ENERO | W20: JULIO | Z20: FEBRERO | AC20: MARZO | AF20: ABRIL | AI20: MAYO | AL20: JUNIO
E21: MONTO | F21: FECHA | G21: FOLIO | H21: MONTO | I21: FECHA | J21: FOLIO | K21: MONTO | L21: FECHA | M21: FOLIO | N21: MONTO | O21: FECHA | P21: FOLIO | Q21: MONTO | R21: FECHA | S21: FOLIO | T21: MONTO | U21: FECHA | V21: FOLIO | W21: MONTO | X21: FECHA | Y21: FOLIO | Z21: MONTO | AA21: FECHA | AB21: FOLIO | AC21: MONTO | AD21: FECHA | AE21: FOLIO | AF21: MONTO | AG21: FECHA | AH21: FOLIO | AI21: MONTO | AJ21: FECHA | AK21: FOLIO | AL21: MONTO | AM21: FECHA | AN21: FOLIO
D22: =D8 -> ADRIAN GABRIEL CASTELLANOS VARGAS | H22: 2394 | I22: 45903 | J22: 662152 | K22: 2394 | L22: 45933 | M22: 351478 | N22: 2394 | O22: 45965 | P22: 680625 | Q22: 2394 | R22: 45995 | S22: 587592 | T22: 2394 | U22: 46027 | V22: SF | Z22: 2394 | AA22: 46057 | AB22: 829169 | AC22: 2394 | AD22: 46086 | AE22: SF | AF22: 2394 | AG22: 46117 | AH22: 54896123 | AI22: 2394 | AJ22: 46140 | AK22: 427092 TD | AL22: 2394 | AM22: 46174 | AN22: 82731 TD | AO22: fac ok
D23: =D9 -> ELIAS DANIEL CRUZ LOPEZ | H23: 2394 | I23: 45901 | J23: 3900479 | K23: 2394 | L23: 45935 | M23: 3900458 | N23: 2394 | O23: 45966 | P23: 68654212 | Q23: 2394 | R23: 45996 | S23: 91731157 | T23: 2394 | U23: 46387 | V23: 74572516 | Z23: 2394 | AA23: 46056 | AB23: 43068784 | AC23: 2394 | AD23: 46084 | AE23: 23256555 | AF23: 2394 | AG23: 46116 | AH23: 22936963 | AI23: 2394 | AJ23: 46146 | AK23: 40105282 | AL23: 2394 | AM23: 46179 | AN23: 20930613 | AO23: fac ok
D24: =D10 -> HELENA POBLETE PEÑA | H24: 1995 | I24: 45895 | J24: 692208 | K24: 1852 | L24: 45698 | M24: 89983 | N24: 1852 | O24: 45966 | P24: 552233 | Q24: 1852 | R24: 45996 | S24: 24151418 | T24: 1852 | U24: 46027 | V24: SF | Z24: 1852 | AA24: 46058 | AB24: 953212 | AC24: 1852 | AD24: 46086 | AE24: SF | AF24: 1852 | AG24: 46118 | AH24: 28873685 | AI24: 1852 | AJ24: 46148 | AK24: 289 (tarjeta cred) | AL24: 1852 | AM24: 46178 | AN24: 158878 TC | AO24: fac ok

Sheet 2°K
F1: Centro de Investigación Educativa Colegio San Diego | S1: ACEPTADOS POR CORPORATIVO
F2: Punta el Campanario #183 Col. Bahia de San Martín CP 96536 | S2: PAGOS DE HIJOS DE MAESTROS
F3: PREESCOLAR 30PJN1037Z PRIMARIA 30PPR3773B SECUNDARIA 30PES0033G | S3: MES PAGADO
D4: FACTURA | F4: CICLO ESCOLAR 2024-2025 | S4: ALUMNO DADO DE BAJA
S5: IRRIGULARIDADES
B7: N° | C7: MATRICULA | D7: NOMBRE DEL ALUMNO | E7: PROMOCION | F7: INSCRIPCION | G7: FOLIO | H7: FECHA | I7: MATERIAL | J7: FECHA | K7: FOLIO | L7: ARANCEL | M7: FECHA | N7: FOLIO | O7: LIBROS | P7: FECHA | Q7: FOLIO | R7: UNIFORMES | S7: FECHA | T7: FOLIO | U7: PLAN PAGO | V7: BECA | W7: COLEG | X7: 10 meses | Z7: 2700 | AA7: 0.3 | AB7: =Z7*AA7 -> 810 | AC7: =Z7-AB7 -> 1890
A8: 921 266 6224 | C8: NUEVO INGRESO | D8: DANAE GARCÍA JIMÉNEZ | E8: NOVIEMBRE-DICIEMBRE | F8: 1450 | G8: 85906482800336200´ | H8: 45653 | I8: 2990 | J8: 45653 | K8: 85906482800336200´ | L8: 2390 | M8: 45653 | N8: 85906482800336200´ | O8: 3900 | P8: 45803 | Q8: 8.5902325e+16 | R8: 3085 | S8: 45887 | T8: 784769 | U8: 12 meses | V8: 0.25 | W8: 1995 | Z8: 3108.8 | AA8: 0.3 | AB8: =Z8*AA8 -> 932.64 | AC8: =Z8-AB8 -> 2176.16
A9: 556 932 1515 | C9: NUEVO INGRESO | D9: SARA ANALI CRUZ PORTILLA | E9: MARZO-JUNIO | F9: 1450 | G9: 5020242 | H9: 45853 | I9: 2990 | J9: 45853 | K9: 5020242 | L9: 2390 | M9: 45853 | N9: 5020242 | O9: 4400 | U9: 12 meses | V9: 0.25 | W9: 1995
A10: 922 220 8188 | C10: NUEVO INGRESO | D10: JOHANA CRUZ MURGIA | E10: MARZO-JUNIO | F10: 1450 | G10: 102LL1 | H10: 45847 | I10: 2990 | J10: 45847 | K10: 102LL1 | L10: 2390 | M10: 45847 | N10: 102LL1 | O10: 4400 | P10: 45847 | Q10: 102LL1 | R10: 3085 | S10: 45847 | T10: 102LL1 | U10: 10 meses | V10: 0.35 | W10: 2223
A11: 923 108 1626 | C11: NUEVO INGRESO | D11: GAEL SANDOVAL GARCIA | E11: MARZO-JUNIO
A12: 229 465 3459 | C12: NUEVO INGRESO | D12: AITANA REBECA FERNÁNDEZ CRUZ | E12: MARZO-JUNIO | F12: GRATIS | G12: GRATIS | H12: 45897 | I12: 500 | J12: 45897 | K12: 2808250 | L12: GRATIS | M12: 45897 | N12: GRATIS | O12: 2200 | P12: 45905 | Q12: 1375802219 | U12: 12 meses | V12: 0.3 | W12: 1995
B19: COLEGIATURA
B20: N° | C20: MATRICULA | D20: NOMBRE DEL ALUMNO | E20: AGOSTO | H20: SEPTIEMBRE | K20: OCTUBRE | N20: NOVIEMBRE | Q20: DICIEMBRE | T20: ENERO | W20: JULIO | Z20: FEBRERO | AC20: MARZO | AF20: ABRIL | AI20: MAYO | AL20: JUNIO
E21: MONTO | F21: FECHA | G21: FOLIO | H21: MONTO | I21: FECHA | J21: FOLIO | K21: MONTO | L21: FECHA | M21: FOLIO | N21: MONTO | O21: FECHA | P21: FOLIO | Q21: MONTO | R21: FECHA | S21: FOLIO | T21: MONTO | U21: FECHA | V21: FOLIO | W21: MONTO | X21: FECHA | Y21: FOLIO | Z21: MONTO | AA21: FECHA | AB21: FOLIO | AC21: MONTO | AD21: FECHA | AE21: FOLIO | AF21: MONTO | AG21: FECHA | AH21: FOLIO | AI21: MONTO | AJ21: FECHA | AK21: FOLIO | AL21: MONTO | AM21: FECHA | AN21: FOLIO
D22: =D8 -> DANAE GARCÍA JIMÉNEZ | H22: 1995 | I22: 45904 | J22: TC | K22: 1995 | L22: 45933 | M22: 8.5907785e+16 | N22: 1995 | O22: 45966 | P22: 8.5901977e+16 | Q22: 1995 | R22: 45996 | S22: 95876545 | T22: 1995 | U22: 46027 | V22: 8.5907935e+16 | W22: 1995 | X22: 45993 | Y22: 8.5902321e+16 | Z22: 1995 | AA22: 46057 | AB22: 8.5907053e+16 | AC22: 1995 | AD22: 46066 | AE22: 8.5903656e+16 | AF22: 1995 | AG22: 46099 | AH22: 8.5906685e+16 | AI22: 1995 | AJ22: 46146 | AK22: 960913 | AL22: 1995 | AM22: 46176 | AN22: 560315466 | AO22: fact ok
D23: =D9 -> SARA ANALI CRUZ PORTILLA | H23: 1995 | I23: 45903 | J23: 85909084190324600´ | K23: 1995 | L23: 45935 | M23: KLAR OP | N23: 1995 | O23: 45966 | P23: 8.5902277e+16 | Q23: 1995 | R23: 45996 | S23: 8.5909043e+16 | T23: 1995 | U23: 46083 | V23: 8948427 | Z23: 1995 | AA23: 46098 | AB23: 8.5906251e+16 | AC23: 1995 | AD23: 46098 | AE23: 8.5906251e+16 | AF23: 1995 | AG23: 46116 | AH23: 8.5900882e+16 | AI23: 1995 | AJ23: 46116 | AK23: 8.5900882e+16 | AL23: 2395 | AM23: 46182 | AN23: 70466355 | AO23: fact ok
D24: =D10 -> JOHANA CRUZ MURGIA | H24: 2223 | I24: 45905 | J24: SF | K24: 2223 | L24: 45935 | M24: SF | N24: 2223 | O24: 45966 | P24: 644668 | Q24: 2223 | R24: 45995 | S24: 37195
D25: =D12 -> AITANA REBECA FERNÁNDEZ CRUZ | H25: 1995 | I25: 45905 | J25: 1375789930 | K25: 1995 | L25: 45934 | M25: 1470769624 | N25: 1995 | O25: 45964 | P25: 1595590764 | Q25: 1995 | R25: 45997 | S25: 61225 | T25: 1995 | U25: 46026 | V25: 1401261 | Z25: 1995 | AA25: 46056 | AB25: 302262 | AC25: 1995 | AD25: 46105 | AE25: 2403260 | AF25: 1995 | AG25: 46124 | AH25: 55332306 | AI25: 1995 | AJ25: 46154 | AK25: 120526 | AL25: 1995 | AM25: 46174 | AN25: 253194906 | AO25: no fact

Sheet 3°K
F1: Centro de Investigación Educativa Colegio San Diego | S1: ACEPTADOS POR CORPORATIVO
F2: Punta el Campanario #183 Col. Bahia de San Martín CP 96536 | S2: PAGOS DE HIJOS DE MAESTROS
F3: PREESCOLAR 30PJN1037Z PRIMARIA 30PPR3773B SECUNDARIA 30PES0033G | S3: MES PAGADO
D4: FACTURA | F4: CICLO ESCOLAR 2024-2025 | S4: ALUMNO DADO DE BAJA
B7: N° | C7: MATRICULA | D7: NOMBRE DEL ALUMNO | E7: PROMOCION | F7: INSCRIPCION | G7: FOLIO | H7: FECHA | I7: MATERIAL | J7: FECHA | K7: FOLIO | L7: ARANCEL | M7: FECHA | N7: FOLIO | O7: LIBROS | P7: FECHA | Q7: FOLIO | R7: UNIFORMES | S7: FECHA | T7: FOLIO | U7: PLAN PAGO | V7: BECA | W7: COLEG | X7: TOTAL | Y7: 10 meses
A8: 921 272 1703 | C8: REINSCRIPCIÓN | D8: CARLA SOFÍA JIMÉNEZ CRUZ | E8: NOVIEMBRE-DICIEMBRE | F8: 1450 | G8: 4667997 | H8: 45677 | Y8: =+X8/12 -> 0
A9: 921 280 7541 | C9: NUEVO INGRESO | D9: ELISA ABIGAIL ALONSO ZAMORA | E9: ENERO FEBRERO | F9: 1450 | G9: 8439639819 | H9: 45701 | I9: 2990 | J9: 45701 | K9: 8439639819 | L9: 2390 | M9: 45701 | N9: 8439639819 | O9: 3900 | P9: 45797 | Q9: 7218123 | R9: 3085 | S9: 45894 | T9: 3520740 | U9: 10 MESES | V9: 0.3 | W9: 2990 | X9: 2394
C10: REINSCRIPCIÓN | D10: NAYAN MARIN MARTINEZ | E10: ENERO FEBRERO | F10: 1450 | G10: HSBC522914 | H10: 45723 | I10: 2990 | J10: 45723 | K10: HSBC522914 | L10: 2390 | M10: 45723 | N10: HSBC522914 | O10: 3900 | P10: 45796 | Q10: 4076892 | U10: 10 MESES | V10: 0.25 | W10: 3420 | X10: 2565
A11: 921 229 2822 | C11: REINSCRIPCIÓN | D11: KAI DE MARIA HERNADEZ ROMÁN | E11: ENERO FEBRERO | F11: 1450 | G11: 12561756 | H11: 45877 | I11: 1212 | J11: 45964 | K11: 1592829844 | U11: 10 MESES | V11: 0.3 | W11: 2990 | X11: 2394
K12: x
B19: COLEGIATURA
B20: N° | C20: MATRICULA | D20: NOMBRE DEL ALUMNO | E20: AGOSTO | H20: SEPTIEMBRE | K20: OCTUBRE | N20: NOVIEMBRE | Q20: DICIEMBRE | T20: ENERO | W20: JULIO | Z20: FEBRERO | AC20: MARZO | AF20: ABRIL | AI20: MAYO | AL20: JUNIO
E21: MONTO | F21: FECHA | G21: FOLIO | H21: MONTO | I21: FECHA | J21: FOLIO | K21: MONTO | L21: FECHA | M21: FOLIO | N21: MONTO | O21: FECHA | P21: FOLIO | Q21: MONTO | R21: FECHA | S21: FOLIO | T21: MONTO | U21: FECHA | V21: FOLIO | W21: MONTO | X21: FECHA | Y21: FOLIO | Z21: MONTO | AA21: FECHA | AB21: FOLIO | AC21: MONTO | AD21: FECHA | AE21: FOLIO | AF21: MONTO | AG21: FECHA | AH21: FOLIO | AI21: MONTO | AJ21: FECHA | AK21: FOLIO | AL21: MONTO | AM21: FECHA | AN21: FOLIO
C22: PASO PAPA | D22: =D8 -> CARLA SOFÍA JIMÉNEZ CRUZ | H22: 2052 | I22: 45936 | J22: 1768637 | K22: 2052 | L22: 45936 | M22: 89705632 | N22: 2052 | O22: 46067 | P22: 5478962135 | Q22: 2052 | R22: 46067 | S22: 5478962135 | T22: 2052 | U22: 46067 | V22: 5478962135 | Z22: 2052 | AA22: 46067 | AB22: 5478962135 | AC22: 2052 | AD22: 46149 | AE22: 64046 TD | AI22: 2452 | AJ22: 46155 | AK22: 7098753
D23: =D9 -> ELISA ABIGAIL ALONSO ZAMORA | H23: 2394 | I23: 45904 | J23: 92025 | K23: 2394 | L23: 45932 | M23: 370251314 | N23: 2394 | O23: 45966 | P23: 1097424 | Q23: 2394 | R23: 45994 | S23: 8847032 | T23: 2394 | U23: 46034 | V23: 2989580 | W23: 2394 | X23: 46000 | Y23: 5611616 | Z23: 2394 | AA23: 46057 | AB23: 6014650 | AC23: 2394 | AD23: 46083 | AE23: 7016241 | AF23: 2394 | AG23: 46113 | AH23: 48302093 | AI23: 2394 | AJ23: 46148 | AK23: 6567541 | AL23: 2394 | AM23: 46175 | AN23: 99599832 | AO23: fact ok
D24: =D10 -> NAYAN MARIN MARTINEZ | H24: 2565 | I24: 45866 | J24: 9359986 | K24: 2565 | L24: 45866 | M24: 9359986 | N24: 2565 | O24: 45949 | P24: 5345598 | Q24: 2565 | R24: 45996 | S24: 4301107 | T24: 2565 | U24: 46028 | V24: 590013 | Z24: 2565 | AA24: 46081 | AB24: 6760150 | AC24: 2565 | AD24: 46096 | AE24: 6656463 | AF24: 2565 | AG24: 46108 | AH24: 9111778 | AI24: 2565 | AJ24: 46140 | AK24: 9959550 | AL24: 2565 | AM24: 46158 | AN24: 1341080 | AO24: fact ok
D25: KAI DE MARIA HERNANDEZ ROMAN | H25: 2794 | I25: 45905 | J25: 1592829844 | K25: 2794 | L25: 45936 | M25: 1592829844 | N25: 2794 | O25: 45964 | P25: 1592829844 | Q25: 2794 | R25: 45964 | S25: 1592829844 | T25: 3194 | U25: 46057 | V25: 4589763122 | Z25: 3174 | AA25: 46100 | AB25: 83057999 | AC25: 3190 | AD25: 46147 | AE25: 54733770 | AF25: 3190 | AG25: 46147 | AH25: 54733770 | AO25: 6380

Sheet 1°P
F1: Centro de Investigación Educativa Colegio San Diego | S1: ACEPTADOS POR CORPORATIVO
F2: Punta el Campanario #183 Col. Bahia de San Martín CP 96536 | S2: PAGOS DE HIJOS DE MAESTROS
F3: PREESCOLAR 30PJN1037Z PRIMARIA 30PPR3773B SECUNDARIA 30PES0033G | S3: MES PAGADO
D4: FACTURA | F4: CICLO ESCOLAR 2024-2025 | S4: ALUMNO DADO DE BAJA
B7: N° | C7: MATRICULA | D7: NOMBRE DEL ALUMNO | E7: PROMOCION | F7: INSCRIPCION | G7: FOLIO | H7: FECHA | I7: MATERIAL | J7: FECHA | K7: FOLIO | L7: ARANCEL | M7: FECHA | N7: FOLIO | O7: LIBROS | P7: FECHA | Q7: FOLIO | R7: UNIFORMES | S7: FECHA | T7: FOLIO | U7: PLAN PAGO | V7: BECA | W7: COLEG | X7: TOTAL
A8: 921 129 3915 | B8: REINSCRIPCIÓN | D8: GUTIERREZ VEGA JAZMIN ALEJANDRA | E8: NOVIEMBRE-DICIEMBRE | F8: GRATIS | G8: GRATIS | H8: GRATIS | I8: 2690 | J8: 45656 | K8: 8.5902114e+16 | L8: 2490 | M8: 45656 | N8: 8.5902114e+16 | O8: 5500 | P8: 45805 | Q8: 8.5903082e+16
A9: 921 266 3787 | B9: REINSCRIPCIÓN | D9: LIAM SAEL RAMIREZ PEREA | E9: NOVIEMBRE-DICIEMBRE | F9: GRATIS | G9: GRATIS | H9: GRATIS | I9: 2690 | J9: 45645 | K9: 8.590208e+16 | L9: 2490 | M9: 45645 | N9: 8.590208e+16 | O9: 5500 | P9: 45808 | Q9: 8.5900908e+16
A10: 921 178 7512 | B10: NUEVO INGRESO | D10: ISABELLA GALVEZ DÍAZ | E10: NOVIEMBRE-DICIEMBRE | F10: GRATIS | G10: GRATIS | H10: GRATIS | I10: 2690 | J10: 45675 | K10: 6192027242 | L10: 2490 | M10: 45675 | N10: 6192027242 | O10: 5500 | P10: 45797 | Q10: 6729893681 | R10: 3085 | S10: 45896 | T10: SF | U10: 10 MESES | V10: 0.25 | W10: 3838.8 | X10: 2879
A11: 921 151 7779 | B11: NUEVO INGRESO | D11: GEORGINA FERNÁNDEZ THEUREL | E11: NOVIEMBRE-DICIEMBRE | F11: GRATIS | G11: GRATIS | H11: 0 | I11: 2690 | J11: 45874 | K11: 8.5901285e+16 | L11: 2490 | M11: 45678 | N11: 8.5905809e+16 | O11: 5500 | P11: 45819 | Q11: 8.5902439e+16 | R11: 3085 | T11: SF | U11: 12 MESES | V11: 0.25 | W11: 3199 | X11: 2399
A12: 803 949 5281 | B12: REINSCRIPCIÓN | D12: YOSHIMI MADARA BURELO OLIVARES | E12: ENERO-FEBRERO | F12: GRATIS | G12: GRATIS | H12: 45719 | I12: 2690 | L12: 2490 | M12: 45719 | N12: 772948 | O12: 5500 | P12: 45798 | Q12: 30828 | U12: 12 MESES | V12: 0.25 | W12: 3199 | X12: 2399
A13: 921 265 1701 | B13: NUEVO INGRESO | D13: LILIAN RENATA CORTEZ FUENTES | E13: ENERO-FEBRERO | F13: GRATIS | G13: GRATIS | H13: 45719 | L13: 2490 | M13: 45719 | N13: 303251 | O13: 4000 | P13: 45904 | Q13: 89428950 | U13: 12 MESES | V13: 0.3 | W13: 3199 | X13: 2239
A14: 921 195 6663 | B14: NUEVO INGRESO | C14: ENVIAR COMPROBANTE DE PAGO EN PDF | D14: EITHAN GARDUZA SCOTT | E14: ENERO-FEBRERO | F14: GRATIS | G14: GRATIS | H14: 45723 | I14: 2690 | J14: 45723 | K14: 104452928362 | L14: 2490 | M14: 45723 | N14: 104452928632
A15: 921 121 3656 | B15: NUEVO INGRESO | D15: LIAM ZAMORANO HERNANDEZ | E15: MARZO-JUNIO | F15: GRATIS | G15: GRATIS | H15: GRATIS | I15: 2690 | J15: 45827 | K15: 24310 | L15: 2490 | M15: 45827 | N15: 24310 | U15: 12 MESES | V15: 0.2 | W15: 3199 | X15: 2559
A16: 921 150 2316 | B16: NUEVO INGRESO | D16: REGINA PEREYRA TOLEDO | E16: MARZO-JUNIO | F16: GRATIS | G16: GRATIS | H16: GRATIS | I16: 2690 | J16: 45838 | K16: 8.5903861e+16 | L16: 2490 | M16: 45838 | N16: 8.5903861e+16 | O16: 5900 | P16: 45859 | Q16: 8.5902092e+16 | U16: 12 MESES | V16: 0.18 | W16: 3199.9 | X16: 2623
A17: 921 144 6840 | B17: NUEVO INGRESO | D17: ABRAHAM DE JESUS MONTERO GARCIA | E17: NOVIEMBRE-DICIEMBRE | F17: GRATIS | G17: GRATIS | H17: GRATIS | I17: 1500 | J17: 45743 | K17: 2065526638 | L17: 1500 | M17: 45846 | N17: 18870727 | O17: 5900 | P17: 45877 | Q17: 93322540 | R17: 2000 | S17: 45884 | T17: 67780840 | U17: 12 MESES | W17: 3199 | X17: 1500
A18: 923 130 6307 | B18: NUEVO INGRESO | C18: SIMON BOLIVAR | D18: IVANNA GARCIA RUIZ | E18: MARZO-JUNIO | F18: GRATIS | G18: GRATIS | H18: GRATIS | L18: 1743 | M18: 45861 | N18: 59269061 | O18: 5900 | P18: 45888 | Q18: 12415877 | R18: 3085 | S18: 45888 | T18: 12415877 | U18: 10 MESES | X18: 2687
A19: 921 307 0216 | B19: REINSCRIPCIÓN | C19: PROMO 2X1 | D19: MATIAS SAUL RIVAS GRAJEDA | E19: MARZO-JUNIO | F19: GRATIS | G19: GRATIS | H19: 45872 | L19: 2499 | M19: 45885 | N19: 4358446906
A20: 921 196 0028 | B20: NUEVO INGRESO | C20: MAESTRA CSD | D20: AKANE MORALES ROMAN | E20: MARZO-JUNIO | F20: GRATIS | G20: GRATIS | H20: 45877 | I20: 1345 | J20: 45877 | K20: SF | L20: 1245 | M20: 45877 | N20: sf | O20: 3200 | P20: 45937 | Q20: 50995809 | R20: 3208.4 | S20: 45880 | T20: 927278 | U20: 12 MESES | V20: 0.5 | W20: 3199 | X20: 1559
A21: 921 261 1498 | B21: REINSCRIPCIÓN | D21: KHATERIN AMAIA MORALES DOMINGUEZ | E21: MARZO-JUNIO | F21: GRATIS | G21: GRATIS | H21: 45896 | I21: 2690 | J21: 45896 | K21: 5301872915 | L21: 2490 | M21: 45896 | N21: 5301872915
A22: 961 300 0674 | B22: REINSCRIPCIÓN | D22: YELENA ROSAS SANCHEZ | E22: . | F22: GRATIS | G22: GRATIS | H22: 3.875 | I22: 1345 | J22: 45900 | K22: SF | L22: 1245 | M22: 45900 | N22: SF | U22: 10 MESES | V22: 0.3 | X22: 2687
B27: COLEGIATURA
B28: N° | C28: MATRICULA | D28: NOMBRE DEL ALUMNO | E28: AGOSTO | H28: SEPTIEMBRE | K28: OCTUBRE | N28: NOVIEMBRE | Q28: DICIEMBRE | T28: ENERO | W28: JULIO | Z28: FEBRERO | AC28: MARZO | AF28: ABRIL | AI28: MAYO | AL28: JUNIO
E29: MONTO | F29: FECHA | G29: FOLIO | H29: MONTO | I29: FECHA | J29: FOLIO | K29: MONTO | L29: FECHA | M29: FOLIO | N29: MONTO | O29: FECHA | P29: FOLIO | Q29: MONTO | R29: FECHA | S29: FOLIO | T29: MONTO | U29: FECHA | V29: FOLIO | W29: MONTO | X29: FECHA | Y29: FOLIO | Z29: MONTO | AA29: FECHA | AB29: FOLIO | AC29: MONTO | AD29: FECHA | AE29: FOLIO | AF29: MONTO | AG29: FECHA | AH29: FOLIO | AI29: MONTO | AJ29: FECHA | AK29: FOLIO | AL29: MONTO | AM29: FECHA | AN29: FOLIO
D30: =D8 -> GUTIERREZ VEGA JAZMIN ALEJANDRA | H30: 2687 | I30: 45903 | J30: 43606205 | K30: 2687 | L30: 45932 | M30: 3820081 | N30: 2673 | O30: 45931 | P30: 3820081 | Q30: 2673 | R30: 45995 | S30: 36193672 | T30: 2673 | U30: 46027 | V30: 78923078 | Z30: 2673 | AA30: 46057 | AB30: 8822285 | AC30: 2673 | AD30: 46086 | AE30: 99922069 | AF30: 2677 | AG30: 46115 | AH30: 79836391 | AI30: 2673 | AJ30: 46147 | AK30: 52361928 | AL30: 2673 | AM30: 46174 | AN30: 51920061 | AO30: no fact
D31: =D9 -> LIAM SAEL RAMIREZ PEREA | E31: 2623 | F31: 45874 | G31: 8.5902155e+16 | H31: 2623 | I31: 45905 | J31: 8.5904182e+16 | K31: 2623 | L31: 45935 | M31: 853216 | N31: 2623 | O31: 45964 | P31: 8.5906925e+16 | Q31: 2623 | R31: 45993 | S31: 8.5901155e+16 | T31: 2623 | U31: 46025 | V31: 579069 | W31: 2623 | X31: 45999 | Y31: 8.5904697e+16 | Z31: 2623 | AA31: 46057 | AB31: 8.5906126e+16 | AC31: 2623 | AD31: 46085 | AE31: 2603954306300 | AF31: 2623 | AG31: 46115 | AH31: 8.5900297e+16 | AI31: 2624 | AJ31: 46146 | AK31: 312464 | AL31: 2623 | AM31: 46175 | AN31: 315361 | AO31: fact ok
C32: FACTURA | D32: =D10 -> ISABELLA GALVEZ DÍAZ | H32: 2879 | I32: 45675 | J32: 6192027242 | K32: 2879 | L32: 45931 | M32: 1144620 | N32: 2879 | O32: 45964 | P32: 44999439 | Q32: 2879 | R32: 45992 | S32: 86276026 | T32: 2879 | U32: 46027 | V32: 24191315 | Z32: 2879 | AA32: 46057 | AB32: 73490873 | AC32: 2879 | AD32: 46082 | AE32: 82745502 | AF32: 2879 | AG32: 46116 | AH32: 82180340 | AI32: 2879 | AJ32: 46147 | AK32: 86097863 | AL32: 2879 | AM32: 46175 | AN32: 5788308 | AO32: fact ok
D33: =D11 -> GEORGINA FERNÁNDEZ THEUREL | E33: 2399 | F33: 45874 | G33: 8.5901285e+16 | H33: 2399 | I33: 45903 | J33: 250370 | K33: 2399 | L33: 45936 | M33: 8.5902762e+16 | N33: 2399 | O33: 45966 | P33: 8.5907127e+16 | Q33: 2399 | R33: 45999 | S33: 8.5902882e+16 | T33: 2399 | U33: 46029 | V33: 8.5902268e+16 | Z33: 2399 | AA33: 46057 | AB33: 8.5907633e+16 | AC33: 2399 | AD33: 46105 | AE33: 1061928 | AF33: 2399 | AG33: 46105 | AH33: 1061928 | AI33: 2399 | AJ33: 46148 | AK33: 312665
B34: 10 MESES | C34: NO FACTURA | D34: =D12 -> YOSHIMI MADARA BURELO OLIVARES | H34: 2399 | I34: 45901 | J34: DEBIT CARD | K34: 2399 | L34: 45935 | M34: 656567 | N34: 2399 | O34: 45966 | P34: 24952 | Q34: 2399 | R34: 45996 | S34: 55487960 | T34: 2799 | U34: 46036 | V34: PAGOTDINT | Z34: 2399 | AA34: 46058 | AB34: 305688 | AC34: 2399 | AD34: 46086 | AE34: 87985645 | AF34: 2799 | AG34: 46124 | AH34: 548976213 | AI34: 2399 | AJ34: 46148 | AK34: 288 (tarjeta) | AL34: 2399 | AM34: 46175 | AN34: 872251 TD | AO34: no fact
D35: =D13 -> LILIAN RENATA CORTEZ FUENTES | H35: 2879 | I35: 45901 | J35: 16908756 | K35: 2239 | L35: 45905 | M35: 80059121 | N35: 2239 | O35: 45967 | P35: 38642635 | Q35: 2239 | R35: 45999 | S35: 38646235 | T35: 2239 | U35: 45999 | V35: deb0534 | W35: 2239 | X35: 46000 | Y35: deb0534 | Z35: 2239 | AA35: 46057 | AB35: 6604664 | AC35: 2239 | AD35: 46115 | AE35: 6604664 | AF35: 2239 | AG35: 46116 | AH35: 6604664 | AI35: 2239 | AJ35: 46147 | AK35: 6604664 | AL35: 1839 | AM35: 46181 | AN35: 906847 | AO35: no fact | AP35: comenta: Buenos días le comenté a la directora que no me a completaba para el pago de colegiatura
D36: =D14 -> EITHAN GARDUZA SCOTT
D37: =D15 -> LIAM ZAMORANO HERNANDEZ | E37: 2559 | F37: 45874 | G37: 84695 | H37: 2559 | I37: 45905 | J37: 93487 | K37: 2559 | L37: 45933 | M37: 332114 | N37: 2559 | O37: 45966 | P37: 10876 | Q37: 2239 | R37: 45999 | S37: 64705 | T37: 2559 | U37: 5 | V37: 9463952 | W37: 2239 | X37: 45999 | Y37: 64705 | Z37: 2639 | AA37: 46062 | AB37: 62670 | AC37: 2639 | AD37: 46086 | AE37: 879512 | AF37: 2639 | AG37: 46117 | AH37: 61069 | AI37: 2639 | AJ37: 46146 | AK37: 286 (tarjeta) | AL37: 2559 | AM37: 46181 | AN37: 84865 TC | AO37: no fact
D38: =D16 -> REGINA PEREYRA TOLEDO | E38: 2623 | F38: 45781 | G38: 348350 | H38: 2623 | I38: 45902 | J38: 8.5901635e+16 | K38: 2623 | L38: 45932 | M38: 8.5900823e+15 | N38: 2623 | O38: 45964 | P38: 8.5906491e+16 | Q38: 2623 | R38: 45992 | S38: 8.5905111e+16 | T38: 2623 | U38: 46027 | V38: 8.5904815e+16 | W38: 2623 | X38: 45992 | Y38: 8.5905111e+16 | Z38: 2623 | AA38: 46058 | AB38: 8.590141e+16 | AC38: 2623 | AD38: 46085 | AE38: 771274306369 | AF38: 2623 | AG38: 46126 | AH38: 140426 | AI38: 2623 | AJ38: 46156 | AK38: 414313463 | AL38: 2623 | AM38: 46174 | AN38: 315263 | AO38: fact ok
D39: =D17 -> ABRAHAM DE JESUS MONTERO GARCIA | E39: 1500 | F39: 45901 | G39: 43551496 | H39: 1500 | I39: 45905 | J39: 50897645 | K39: 1900 | L39: 45951 | M39: 59097254 | N39: 1500 | O39: 45952 | P39: 59097254 | Q39: 1500 | R39: 46005 | S39: 20189863 | T39: 1500 | U39: 46027 | V39: 46143963 | W39: 1500 | X39: 45999 | Y39: 536590 | Z39: 1500 | AA39: 46053 | AB39: 5434853 | AC39: 1500 | AD39: 46079 | AE39: 97852712 | AF39: 1500 | AG39: 46108 | AH39: 74182179 | AI39: 1500 | AJ39: 46141 | AK39: 32477095 | AL39: 1500 | AM39: 46174 | AN39: 42349957 | AO39: fact ok
D40: =D18 -> IVANNA GARCIA RUIZ | H40: 2687 | I40: 45905 | J40: SF | K40: 2687 | L40: 45935 | M40: 44449845 | N40: 2687 | O40: 45966 | P40: 37240654 | Q40: 2687 | R40: 45993 | S40: 25782987 | T40: 2687 | U40: 46027 | V40: 36804787 | Z40: 2687 | AA40: 46056 | AB40: 66317447 | AC40: 2687 | AD40: 46083 | AE40: 3915390 | AF40: 2687 | AG40: 46108 | AH40: 88341480 | AI40: 2687 | AJ40: 46139 | AK40: 84625200 | AL40: 2687 | AM40: 46168 | AN40: 49090922 | AO40: fact ok
D41: =D19 -> MATIAS SAUL RIVAS GRAJEDA | H41: 2686 | I41: 45877 | J41: 86337846 | K41: 2686 | L41: 45936 | M41: 67398754 | N41: 2686 | O41: 45967 | P41: 1410671778 | Q41: 2686 | R41: 45997 | S41: 48526973 | T41: 2686 | U41: 46028 | V41: 21536479 | Z41: 2686 | AA41: 46063 | AB41: 67398754 | AC41: 2686 | AD41: 46088 | AE41: 58936336 | AF41: 2687 | AG41: 46156 | AH41: 58639034 | AI41: 2686 | AJ41: 46147 | AK41: 67398754 | AL41: 2686 | AM41: 46177 | AN41: 91470328 | AO41: fact ok
D42: =D20 -> AKANE MORALES ROMAN | H42: 1599 | I42: 45905 | J42: 38846348 | K42: 1600 | L42: 45937 | M42: 50995809 | N42: 1599 | O42: 45962 | P42: 3415019 | Q42: 1599 | R42: 45996 | S42: TRANSFDE | T42: 1599 | U42: 46361 | V42: TRANSFDE | Z42: 1559 | AA42: 46058 | AB42: TRANSFDE | AC42: 1559 | AD42: 46086 | AE42: TRANSFDE | AF42: 1559 | AG42: 46118 | AH42: 26603543 | AI42: 1559 | AJ42: 46147 | AK42: 49458601 | AL42: 1599 | AM42: 46174 | AN42: 126527 TD | AO42: no fact
D43: KHATERIN AMAIA MORALES DOMINGUEZ | H43: 2879 | I43: 45905 | J43: 89966780 | K43: 3147 | L43: 45934 | M43: 24876531 | N43: 3147 | O43: 45967 | P43: 50679516 | Q43: 3147 | R43: 46361 | S43: 71292800 | T43: 3147 | U43: 46058 | V43: 83006103 | Z43: 3147 | AA43: 46177 | AB43: 44804264 | AC43: 3147 | AD43: 46086 | AE43: 465 | AF43: 3547 | AG43: 46181 | AH43: 86330335 | AI43: 3147 | AJ43: 46147 | AK43: 44604939 | AN43: convenio
D44: YELENA ROSAS SANCHEZ | H44: 2686 | I44: 45934 | J44: 48902654 | K44: 2686 | L44: 45944 | M44: YTMBOK | N44: 2686 | O44: 45966 | P44: 974643 | Q44: 2686 | R44: 45995 | S44: V8WF3G | T44: 2686 | U44: 46027 | V44: TC | Z44: 2239 | AA44: 46054 | AB44: CTA2493 | AC44: 2239 | AD44: 46086 | AE44: CTA2493 | AF44: 2839 | AG44: 46129 | AH44: 573084 | AI44: 2239 | AJ44: 46150 | AK44: 10333 TC | AL44: 2239 | AM44: 46188 | AN44: 0349 TD | AO44: no fact
C45: NO LOC NUMERO | D45: JARA DOMINGUEZ MARIA RENATA | T45: 2559 | U45: 46040 | V45: 54621387 | Z45: 2559 | AA45: 46058 | AB45: 39434 | AC45: 2559 | AD45: 46086 | AE45: 25489671 | AF45: 2559 | AG45: 46115 | AH45: HSB5682276 | AI45: =2559+400 -> 2959 | AJ45: 46153 | AK45: 110526 | AL45: 2959 | AM45: 46199 | AN45: 54758 | AO45: no fact
N52: 380
N53: 370
M54: 2490 | N54: =M54/2 -> 1245
M55: 2690 | N55: =M55/2 -> 1345
N56: 2559
N57: =SUMPRODUCT(N52:N56) -> 5899

Sheet 2°P
F1: Centro de Investigación Educativa Colegio San Diego | S1: ACEPTADOS POR CORPORATIVO
F2: Punta el Campanario #183 Col. Bahia de San Martín CP 96536 | S2: PAGOS DE HIJOS DE MAESTROS
F3: PREESCOLAR 30PJN1037Z PRIMARIA 30PPR3773B SECUNDARIA 30PES0033G | S3: MES PAGADO
D4: FACTURA | F4: CICLO ESCOLAR 2024-2025 | S4: ALUMNO DADO DE BAJA
B7: N° | C7: MATRICULA | D7: NOMBRE DEL ALUMNO | E7: PROMOCION | F7: INSCRIPCION | G7: FOLIO | H7: FECHA | I7: MATERIAL | J7: FECHA | K7: FOLIO | L7: ARANCEL | M7: FECHA | N7: FOLIO | O7: LIBROS | P7: FECHA | Q7: FOLIO | R7: UNIFORMES | S7: FECHA | T7: FOLIO | U7: PLAN PAGO | V7: BECA | W7: COLEG | X7: TOTAL
A8: 294 121 5790 | B8: REINSCRIPCIÓN | D8: OSWALDO LOPEZ FONSECA | E8: NOVIEMBRE-DICIEMBRE | F8: 1550 | G8: 1343589496 | H8: 45619 | I8: 2690 | J8: 45809 | K8: 7762010280 | L8: 1810 | M8: 45809 | N8: 7762010280 | O8: 5500 | P8: 45811 | Q8: 7762010280
A9: 33 1252 9236 | B9: REINSCRIPCIÓN | D9: CARLOS DANIEL TRUJILLO RODRIGUEZ | E9: NOVIEMBRE-DICIEMBRE | F9: 1550 | G9: 2813342240 | H9: 45636 | I9: 2690 | J9: 45636 | K9: 2813452941 | L9: 2490 | M9: 45636 | N9: 2813386375 | O9: 5500 | P9: 45797 | Q9: 6736479464
A10: 921 151 3220 | B10: REINSCRIPCIÓN | D10: CESAR BENHUR CASTAN OVANDO | E10: NOVIEMBRE-DICIEMBRE | F10: 1550 | G10: 85902131894335200´ | H10: 45643 | I10: 2690 | J10: 45810 | K10: 8.5905633e+16 | L10: 2490 | M10: 45810 | N10: 8.5905633e+16 | O10: 5500 | P10: 45792 | Q10: 8.5904168e+16 | U10: 10 MESES | V10: 0.25 | W10: 3838 | X10: 2879
A11: 921 207 3167 | B11: REINSCRIPCIÓN | D11: JONATHAN DE JESÚS SALINAS TOLEDO | E11: NOVIEMBRE-DICIEMBRE | F11: 1550 | G11: 287318 | H11: 45657 | I11: 2690 | J11: 45889 | K11: 164200 | O11: 5900 | P11: 45900 | Q11: 310825 | U11: 10 MESES | V11: 0.3 | W11: 3838 | X11: 2686
A12: 921 272 1703 | B12: REINSCRIPCIÓN | D12: NATHALIA ITZAÉ JIMÉNEZ CRUZ | E12: NOVIEMBRE-DICIEMBRE | F12: 1550 | G12: 8127769 | H12: 45677
A13: 921 103 2088 | B13: REINSCRIPCIÓN | C13: 20% DESCUENTO ARANCEL | D13: JEAN CARLOS RICARDEZ VEGA | E13: ENERO-FEBRERO | F13: 1550 | G13: 7328700925 | H13: 45688 | I13: 2690 | J13: 45905 | K13: 572893 | L13: 2490 | M13: 45905 | N13: 572893 | U13: 12 MESES | V13: 0.3 | W13: 3199 | X13: 2239
A14: 921 205 6342 | B14: REINSCRIPCIÓN | C14: 20% DESCUENTO ARANCEL | D14: DOMINIC GUSTAVO NIVON OROZCO | E14: ENERO-FEBRERO | F14: 1550 | G14: 8.5904684e+16 | H14: 45694 | I14: 2690 | J14: 45895 | K14: 332872 | L14: 2490 | M14: 45895 | N14: 332872 | U14: 12 MESES | V14: 0.2 | W14: 3199 | X14: 2559
A15: 921 122 6826 | B15: REINSCRIPCIÓN | D15: LUIS MARIO HERNANDEZ VARGAS | E15: ENERO-FEBRERO | F15: 1550 | G15: HSBC343677 | H15: 45716 | I15: 2690 | J15: 45866 | K15: 1538958 | L15: 1992 | M15: 45866 | N15: 4029199 | O15: 5900 | P15: 45869 | Q15: 281018
A16: 921 115 9794 | B16: REINSCRIPCIÓN | D16: ROMINA RODRIGUEZ PEREZ | E16: ENERO-FEBRERO | F16: 1550 | G16: 9741630351 | H16: 45716 | I16: 2690 | J16: 45895 | K16: 85906073290323800´ | L16: 2490 | M16: 45895 | N16: 85906073290323800´ | O16: 5900 | P16: 45895 | Q16: 85906073290323800´ | U16: 10 MESES | V16: 0.25 | W16: 3838.8 | X16: 2879
A17: 921 291 0428 | B17: REINSCRIPCIÓN | D17: JOSE MIGUEL CRUZ LOPEZ | E17: MARZO-ABRIL | F17: 1550 | G17: 2998534748 | H17: 45754 | I17: 1234 | J17: 45825 | K17: 63415250 | O17: 2655 | P17: 45903 | Q17: 3012346
A18: 921 105 3439 | B18: NUEVO INGRESO | D18: INGRID PATRICIA GUZMAN SANTIAGO | E18: MARZO-ABRIL | F18: PENDIENTE | G18: PENDIENTE | H18: PENDIENTE | I18: 2690 | J18: 45838 | K18: 48635063 | L18: 2490 | M18: 45793 | N18: 6378639052 | O18: 5900 | P18: 45861 | Q18: 14374475 | U18: 12 MESES | V18: 0.2 | W18: 3838.8 | X18: 2559
A19: 921 178 1586 | B19: SIMON BOLIVAR | C19: 30% DESC ARANCEL Y MATERIAL | D19: EMMA SOFIA DOMINGUEZ NIETO | E19: MARZO-JUNIO | F19: GRATIS | G19: GRATIS | H19: 45869 | I19: 1883 | J19: 45869 | K19: 27027325 | L19: 1743 | M19: 45869 | N19: 30996518 | O19: 5900 | P19: 45871 | Q19: 27816400 | R19: 3085 | S19: 45871 | T19: 19765211 | U19: 10 MESE | V19: 0.3 | W19: 3838 | X19: 2878
A20: 921 272 5928/9212286982 | B20: REINSCRIPCIÓN | C20: INSCRIPCIÓN GRATIS | D20: VALENTINA TOSCANO MOSQUEDA | E20: MARZO-JUNIO | F20: GRATIS | G20: GRATIS | H20: 45883 | I20: 2690 | J20: 45883 | K20: 743269432 | L20: 2490 | M20: 45883 | N20: 743269432 | O20: 3000 | P20: 45883 | Q20: 743269432 | U20: 10 MESES | V20: 0.25 | W20: 3838 | X20: 2878
A21: 921 118 1360 | B21: REINSCRIPCIÓN | D21: ANGEL DE JESUS ARRONIZ CALZADA | E21: MARZO-JUNIO | F21: 1860 | G21: 55270537 | H21: 45865 | I21: 2783 | J21: 45839 | K21: 2324992 | U21: 10 MESES | V21: 0.25 | W21: 3838 | X21: 2878
A22: 921 138 9951 | B22: REINSCRIPCIÓN | D22: ANDRES VEGA CAPORAL | E22: MARZO-JUNIO | F22: GRATIS | G22: GRATIS | H22: 45890 | I22: 2690 | J22: 45890 | K22: 91745108 | L22: 2490 | M22: 45901 | N22: 58428646 | O22: 3000 | P22: 45912 | Q22: 9120272 | U22: 10 MESES | V22: 0.18 | W22: 3838.8 | X22: 3147
A23: 922 140 6895 | B23: REINSCRIPCIÓN | C23: EL MARTES 26 HACE LOS PAGOS | D23: MATIAS ALEJANDRO PEREZ REYES | E23: MARZO-JUNIO | F23: GRATIS | G23: GRATIS | H23: 45898 | I23: 1345 | J23: 45898 | K23: 87801674 | L23: 1245 | M23: 45898 | N23: 87801674
A24: 921 125 2551 | B24: REINSCRIPCIÓN | D24: JARED ALEXANDER FUENTES TORRRES | E24: MARZO-JUNIO | F24: GRATIS | G24: GRATIS | H24: 45890 | I24: 1445 | J24: 45897 | K24: 681592 | L24: 1195 | M24: 45897 | N24: 681592 | O24: 3000 | P24: 45918 | Q24: 180925 | U24: 10 MESES | V24: 0.3 | W24: 3838 | X24: 2686
B25: NUEVO INGRESO | D25: VALENTINA MARTINEZ | E25: MARZO-JUNIO
A26: 55 1260 2277 | C26: NUEVO INGRESO | D26: DOMINIC ISAAR RUIZ GARZÓN | E26: ENERO-FEBRERO | F26: 1550 | G26: 46190675 | H26: 46056 | I26: 1445 | J26: 46056 | K26: 46190675 | L26: 1245 | M26: 46056 | N26: 46190675 | U26: 12 MESES | V26: 0.25 | W26: 3199 | X26: 2559
D27: MARIA RENATA | E27: ENERO-FEBRERO
B33: COLEGIATURA
B34: N° | C34: MATRICULA | D34: NOMBRE DEL ALUMNO | E34: AGOSTO | H34: SEPTIEMBRE | K34: OCTUBRE | N34: NOVIEMBRE | Q34: DICIEMBRE | T34: ENERO | W34: JULIO | Z34: FEBRERO | AC34: MARZO | AF34: ABRIL | AI34: MAYO | AL34: JUNIO
E35: MONTO | F35: FECHA | G35: FOLIO | H35: MONTO | I35: FECHA | J35: FOLIO | K35: MONTO | L35: FECHA | M35: FOLIO | N35: MONTO | O35: FECHA | P35: FOLIO | Q35: MONTO | R35: FECHA | S35: FOLIO | T35: MONTO | U35: FECHA | V35: FOLIO | W35: MONTO | X35: FECHA | Y35: FOLIO | Z35: MONTO | AA35: FECHA | AB35: FOLIO | AC35: MONTO | AD35: FECHA | AE35: FOLIO | AF35: MONTO | AG35: FECHA | AH35: FOLIO | AI35: MONTO | AJ35: FECHA | AK35: FOLIO | AL35: MONTO | AM35: FECHA | AN35: FOLIO
C36: 10 MESES | D36: =D8 -> OSWALDO LOPEZ FONSECA | H36: 2600 | I36: 45874 | J36: 95945829 | K36: 2600 | L36: 45874 | M36: 95945829 | N36: 2600 | O36: 45874 | P36: 95945829 | Q36: 2600 | R36: 45997 | S36: 4654 | T36: 2600 | U36: 45997 | V36: 4654 | Z36: 2600 | AA36: 46022 | AB36: SF | AC36: =500+1500+600 -> 2600 | AD36: 46125 | AE36: 7410 | AF36: 2600 | AG36: 46167 | AH36: SF | AI36: 800 | AJ36: 46167 | AK36: SF | AO36: =2600-800 -> 1800 | AP36: PEND SOL NVO PAGO
D37: =D9 -> CARLOS DANIEL TRUJILLO RODRIGUEZ | H37: 2686 | I37: 45782 | J37: 48922771 | K37: 2686 | L37: 45930 | M37: 62348679 | N37: 2686 | O37: 45960 | P37: 49834581 | Q37: 2686 | R37: 45993 | S37: 77361689 | T37: 2686 | U37: 45999 | V37: 89312066 | Z37: 2686 | AA37: 46056 | AB37: 57499353 | AC37: 2686 | AD37: 46086 | AE37: 50648220 | AF37: 2686 | AG37: 46115 | AH37: 26344497 | AI37: 2686 | AJ37: 46147 | AK37: 25992592 | AL37: 2686 | AM37: 46179 | AN37: 46351542 | AO37: FACT OK
D38: =D10 -> CESAR BENHUR CASTAN OVANDO | H38: 2686 | I38: 45904 | J38: 58497120 | K38: 2879 | L38: 45930 | M38: 8.5904615e+16 | N38: 2879 | O38: 45960 | P38: 84681 | Q38: 2879 | R38: 45979 | S38: 84681 | T38: 2879 | U38: 46006 | V38: 20612 | Z38: 2879 | AA38: 46058 | AB38: 89745631 | AC38: 2879 | AD38: 46086 | AE38: 78452163 | AF38: 2879 | AG38: 46126 | AH38: 85974631 | AI38: 2879 | AJ38: 45780 | AK38: 312361 | AL38: 2879 | AM38: 46174 | AN38: 85116 TD | AO38: FACT OK
D39: =D11 -> JONATHAN DE JESÚS SALINAS TOLEDO | H39: 2494.75 | I39: 45900 | J39: 300825 | K39: 2494.75 | L39: 45935 | M39: 61025 | N39: 2494.75 | O39: 45965 | P39: 1615258 | Q39: 2496 | R39: 46361 | S39: 191152 | T39: 2496 | U39: 46041 | V39: 28994436 | Z39: 2694.5 | AA39: 46084 | AB39: DEP BANC | AC39: 2694 | AD39: 46135 | AE39: 28677803 | AF39: 2694 | AG39: 46135 | AH39: 28677803 | AI39: 2694 | AJ39: 46147 | AK39: 88516315 | AL39: 2694 | AM39: 46178 | AN39: 59924705 | AO39: NO FACT
C40: PASO PAPA | D40: =D12 -> NATHALIA ITZAÉ JIMÉNEZ CRUZ | H40: 2302 | I40: 45906 | J40: 1768637 | K40: 2302 | L40: 45906 | M40: 89137465 | N40: 2302 | O40: 46055 | P40: TDC | Q40: 2302 | R40: 46055 | S40: TDC | T40: 2302 | U40: 46055 | V40: TDC | Z40: 2302 | AA40: 46055 | AB40: TDC | AC40: 2702 | AD40: 46169 | AE40: 64046 TD | AI40: 2702 | AJ40: 46155 | AK40: 7098753
D41: =D13 -> JEAN CARLOS RICARDEZ VEGA | E41: 2399 | F41: 45887 | G41: 6049483 | H41: 2399 | I41: 45905 | J41: 572893 | K41: 2399 | L41: 45938 | M41: 859827 | N41: 2399 | O41: 45967 | P41: 274544 | Q41: 2399 | R41: 45997 | S41: 436129 | T41: 2399 | U41: 46027 | V41: 77792 | W41: 2399 | X41: 06/112 | Y41: 436129 | Z41: 2399 | AA41: 46055 | AB41: 458714 | AC41: 2399 | AD41: 46087 | AE41: 565064 | AF41: 2399 | AG41: 46120 | AH41: 3380020 | AI41: $2,399 (cole normal) diferencia material siguiente año ($501) | AJ41: 46147 | AK41: 504750 | AL41: 2399 | AM41: 46181 | AN41: 43839199 | AO41: $2,399 (cole normal) diferencia material siguiente año ($501) | AP41: NO FACT
D42: =D14 -> DOMINIC GUSTAVO NIVON OROZCO | E42: 2559 | F42: 46207 | G42: 62272735 | H42: 2559 | I42: 45905 | J42: 8.5908018e+16 | K42: 2559 | L42: 45933 | M42: 8.5908454e+16 | N42: 2559 | O42: 45966 | P42: 8.5903362e+16 | Q42: 2559 | R42: 45997 | S42: 8.5901018e+16 | T42: 2559 | U42: 46027 | V42: 548976 | W42: 2559 | X42: 45997 | Y42: 8.5901018e+16 | Z42: 2559 | AA42: 46057 | AB42: 28918961 | AC42: 2559 | AD42: 46083 | AE42: 820633 | AF42: 2559 | AG42: 46116 | AH42: 63225954 | AI42: 2559 | AJ42: 46146 | AK42: 8.5902392e+16 | AL42: 2559 | AM42: 46174 | AN42: 315260 | AO42: FACT OK
D43: =D15 -> LUIS MARIO HERNANDEZ VARGAS | H43: 2239 | I43: 45912 | J43: 4215190 | K43: 2239.3 | L43: 45935 | M43: 281018 | N43: 2559 | O43: 45967 | P43: 40741 | Q43: 2239 | R43: 46386 | S43: 3332905 | T43: 2239 | U43: 46023 | V43: 3332905 | Z43: 2239 | AA43: 46067 | AB43: 2345294 | AC43: 2239 | AD43: 46129 | AE43: 5268183 | AF43: 2239 | AG43: 46129 | AH43: 9900530 | AI43: 2239.3 | AJ43: 46170 | AK43: 8365018 | AL43: 2239.3 | AM43: 46184 | AN43: 4124157
D44: =D16 -> ROMINA RODRIGUEZ PEREZ | H44: 2879 | I44: 45915 | J44: 71746458 | K44: 2879 | L44: 45945 | M44: 8843465 | N44: 2879 | O44: 45960 | P44: 12364113 | Q44: 2879 | R44: 46006 | S44: 27548151 | T44: 2879 | U44: 46027 | V44: 88740576 | Z44: 2879 | AA44: 46057 | AB44: 66470624 | AC44: 2879 | AD44: 46081 | AE44: 54003840 | AF44: 2879 | AG44: 46127 | AH44: 19864641 | AI44: 3279 | AJ44: 46155 | AK44: 54638119 | AL44: 3279 | AM44: 46179 | AN44: 7932841 | AO44: FACT OK
D45: =D17 -> JOSE MIGUEL CRUZ LOPEZ | H45: 2687.6 | I45: 45901 | J45: 18569766 | K45: 2687 | L45: 45938 | M45: 98547924 | N45: 2394 | O45: 45966 | P45: 68654212 | Q45: 2687.6 | R45: 45996 | S45: 16809912 | T45: 2687.6 | U45: 46022 | V45: 53321648 | Z45: 2687.6 | AA45: 46056 | AB45: 72596916 | AC45: 2687.6 | AD45: 46084 | AE45: 62176790 | AF45: 2687.6 | AG45: 46116 | AH45: 40066842 | AI45: 2687.6 | AJ45: 46146 | AK45: 39668816 | AL45: 2687.6 | AM45: 46177 | AN45: 14061067 | AO45: FACT OK
C46: 12 MESES | D46: =D18 -> INGRID PATRICIA GUZMAN SANTIAGO | H46: 2559 | I46: 45891 | J46: 570485 | K46: 2559 | L46: 45920 | M46: 734775 | N46: 2559 | O46: 45979 | P46: 63257132 | Q46: 2559 | R46: 45996 | S46: 548799 | T46: 2559 | U46: 46025 | V46: 80482146 | W46: 2560 | X46: 46003 | Y46: 887949 | Z46: 2559 | AA46: 46057 | AB46: 520333 | AC46: 2559 | AD46: 46086 | AE46: 87963547 | AF46: 2259 | AG46: 46116 | AH46: 32250109 | AI46: 2259 | AJ46: 46147 | AK46: 72960374 | AL46: 2559 | AM46: 46177 | AN46: 40970035 | AO46: pago $600, por la difrencia de las colegiaturas de abril y mayo | AP46: FACT OK
D47: =D19 -> EMMA SOFIA DOMINGUEZ NIETO | H47: 2878 | I47: 45903 | J47: 34580363 | K47: 2878 | L47: 45932 | M47: 21646416 | N47: 2878 | O47: 45965 | P47: 37680345 | Q47: 2878 | R47: 45993 | S47: 31484078 | T47: 2878 | U47: 46027 | V47: 47813707 | Z47: 2878 | AA47: 46056 | AB47: 98814826 | AC47: 2878 | AD47: 46086 | AE47: 37779636 | AF47: 2878 | AG47: 46119 | AH47: 26035745 | AI47: 2878 | AJ47: 46126 | AK47: 32504668 | AL47: 2878 | AM47: 46157 | AN47: 40620357 | AO47: FACT OK
D48: =D20 -> VALENTINA TOSCANO MOSQUEDA | H48: 2878 | I48: 45935 | J48: CTA0615 | K48: 2878 | L48: 45952 | M48: CTA0615 | N48: 3278 | O48: 46001 | P48: CTA0615 | Q48: 3278 | R48: 46001 | S48: CTA0615 | T48: 3278 | U48: 46045 | V48: 46976879 | Z48: 3278 | AA48: 46045 | AB48: 46976879 | AC48: 3278 | AD48: 46045 | AE48: 46976879 | AF48: 3278 | AG48: 46045 | AH48: 46976879 | AI48: 3278 | AJ48: 46045 | AK48: 46976879 | AL48: 3278 | AM48: 46045 | AN48: 46976879 | AO48: NO FACT
D49: =D21 -> ANGEL DE JESUS ARRONIZ CALZADA | E49: 2783 | F49: 45839 | G49: 2324992 | H49: 2983 | I49: 45934 | J49: 794564 | K49: 3198 | L49: 45939 | M49: 80420511 | N49: 3198 | O49: 45966 | P49: 74614286 | Q49: 3198 | R49: 45997 | S49: 54869723 | T49: 3198 | U49: 46028 | V49: 57102871 | Z49: 3198 | AA49: 46064 | AB49: 52382494 | AC49: 3198 | AD49: 46139 | AE49: 959095 | AF49: 3198 | AG49: 46160 | AH49: 36893 | AI49: 3278 | AJ49: 45817 | AK49: 62721846 | AN49: pend apenas pago mayo
D50: =D22 -> ANDRES VEGA CAPORAL | H50: 2687 | I50: 45934 | J50: 13152586 | K50: 2687 | L50: 45939 | M50: SF | N50: 2687 | O50: 45965 | P50: 85851424 | Q50: 2687 | R50: 46032 | S50: 425274 | T50: 2687 | U50: 46081 | V50: 66892 | Z50: 2687 | AA50: 46085 | AB50: 357852 | AC50: 2687 | AD50: 46124 | AE50: 88225280 | AF50: 3087 | AG50: 46168 | AH50: 188250 | AI50: 3087 | AJ50: 46168 | AK50: 188250 | AO50: NO FACT
D51: =D23 -> MATIAS ALEJANDRO PEREZ REYES | H51: 2687 | I51: 45919 | J51: 9224609 | K51: 2687 | L51: 45951 | M51: 590065667 | N51: 2687 | O51: 45966 | P51: 4877003 | Q51: 2687 | R51: 46010 | S51: 78056577 | T51: 2687 | U51: 46027 | V51: 58799632 | Z51: 2687 | AA51: 46062 | AB51: 16066028 | AC51: 2687 | AD51: 46084 | AE51: 82784126 | AF51: 2687 | AG51: 46136 | AH51: 75067131 | AI51: 2687 | AJ51: 46146 | AK51: 61751876 | AL51: 2687 | AM51: 46183 | AN51: 71456732 | AO51: FACT OK
D52: =D24 -> JARED ALEXANDER FUENTES TORRRES | H52: 2686 | I52: 45897 | J52: 250828 | K52: 3386 | L52: 45947 | M52: 251017 | N52: 2686 | O52: 45966 | P52: 251105 | Q52: 2686 | R52: 46361 | S52: 251205 | T52: 2686 | U52: 46027 | V52: 260105 | Z52: 2686 | AA52: 46058 | AB52: 260205 | AC52: 2686 | AD52: 46086 | AE52: 260305 | AF52: 2686 | AG52: 46117 | AH52: 260405 | AI52: 2686 | AJ52: 46127 | AK52: 260415 | AL52: 2686 | AM52: 46178 | AN52: 261285 | AO52: NO FACT
D53: VALENTINA MARTINEZ | N53: 2399 | O53: 45967 | P53: 21702454 | Q53: 2399 | R53: 46002 | S53: 98758190 | T53: 2399 | U53: 46027 | V53: 28269095 | Z53: 2399 | AA53: 46061 | AB53: 39269270 | AC53: 2399 | AD53: 46086 | AE53: 36124016 | AF53: 2399 | AG53: 46120 | AH53: 45151633 | AI53: 2399 | AJ53: 45785 | AK53: 91036564 | AL53: 2400 | AM53: AGREGAR
D54: DOMINIC ISAAR RUIZ GARZÓN | Z54: 2559 | AA54: 46055 | AB54: 115101153 | AC54: 2559 | AD54: 46092 | AE54: 19129566 | AF54: 2559 | AG54: 46128 | AH54: 38991139 | AI54: 2959 | AJ54: 46162 | AK54: 53344741 | AL54: 2559 | AM54: 46178 | AN54: 28926676 | AO54: no fact
D55: KARLA SUGEY OLAN MEJIA

Sheet 3° P
F1: Centro de Investigación Educativa Colegio San Diego | S1: ACEPTADOS POR CORPORATIVO
F2: Punta el Campanario #183 Col. Bahia de San Martín CP 96536 | S2: PAGOS DE HIJOS DE MAESTROS
F3: PREESCOLAR 30PJN1037Z PRIMARIA 30PPR3773B SECUNDARIA 30PES0033G | S3: MES PAGADO
D4: FACTURA | F4: CICLO ESCOLAR 2024-2025 | S4: ALUMNO DADO DE BAJA
B7: N° | C7: MATRICULA | D7: NOMBRE DEL ALUMNO | E7: PROMOCION | F7: INSCRIPCION | G7: FOLIO | H7: FECHA | I7: MATERIAL | J7: FECHA | K7: FOLIO | L7: ARANCEL | M7: FECHA | N7: FOLIO | O7: LIBROS | P7: FECHA | Q7: FOLIO | R7: UNIFORMES | S7: FECHA | T7: FOLIO | U7: PLAN PAGO | V7: BECA | W7: COLEG | X7: TOTAL
A8: 921 207 3167 | C8: REINSCRIPCIÓN | D8: ALICE YANELI SALINAS TOLEDO | E8: NOVIEMBRE-DICIEMBRE | F8: 1550 | G8: 287318 | H8: 45657 | I8: 2690 | J8: 45889 | K8: 164200 | O8: 5900 | P8: 45900 | Q8: 310825 | U8: 10 meses | V8: 0.3 | W8: 3838 | X8: 2686
A9: 921 123 1837 | C9: ARANCEL AL 20% DE DESCUENTO | D9: KAORU HIGASHI ALCANTARA | E9: ENERO-FEBRERO | F9: 1550 | G9: 3910305 | H9: 45694 | I9: 2690 | J9: 45694 | K9: HSBC013246 | L9: 1992 | M9: 45695 | N9: HSBC013246 | U9: 10 meses | V9: 0.25 | W9: 3838 | X9: 2686
A10: 921 110 3093 | B10: AGREGAR A CONTACTO | C10: NUEVO INGRESO | D10: AGNES DANIELLE JIMENEZ CALDERON | E10: MARZO-JUNIO | F10: GRATIS | G10: GRATIS | H10: 45877 | I10: 2690 | J10: 45803 | K10: 67848127 | L10: 2490 | M10: 45877 | N10: 90510FS00962067214 | O10: 5500 | P10: 45877 | Q10: 65669 | R10: 1755 | S10: 45888 | T10: 27388321 | U10: 10 meses | V10: 0.3 | W10: 3838 | X10: 2686
A11: 921 123 0949 | C11: REINSCRIPCIÓN | D11: CESAR MATEO CRUZ LANDA | E11: ENERO-FEBRERO | F11: 1550 | G11: 8776707083 | H11: 45705 | I11: 2690 | J11: 45931 | K11: 12640830 | L11: 2490 | M11: 45705 | N11: 8776707083 | O11: 5900 | P11: 45862 | Q11: 21849877 | U11: 12 meses | V11: 0.25 | W11: 3838 | X11: 2559
A12: 921 256 0669 | C12: NUEVO INGRESO | D12: THIAGO ALFONSO FUENTES | E12: ENERO-FEBRERO | F12: 1550 | G12: HSBC5537 | H12: 45712 | I12: 2690 | J12: 45712 | K12: HSBC5537 | L12: 2490 | M12: 45712 | N12: HSBC5537 | O12: 4000 | P12: 45810 | Q12: BANORTE5537 | U12: 12 meses | V12: 0.3 | W12: 3199 | X12: 2239.3
A13: 921 345 7203 | C13: NUEVO INGRESO | D13: ISABELLA FERNANDA PEREZ VELAZQUEZ | E13: ENERO-FEBRERO | F13: 1550 | G13: 174622771 | H13: 45721 | I13: 2690 | J13: 45721 | K13: 174622771 | L13: 2490 | M13: 45721 | N13: 174622771 | R13: 3085 | S13: 45897 | T13: 2808250 | U13: 10 meses | V13: 0.3 | W13: 3838 | X13: 2686
A14: 921 101 3834 | C14: REINSCRIPCIÓN | D14: ASIEL ROQUE FUENTES | E14: ENERO-FEBRERO | F14: 1550 | G14: 7584919327 | H14: 45807 | I14: 2690 | J14: 45807 | K14: 7584919327 | L14: 2490 | M14: 45807 | N14: 7584919327 | U14: 10 meses | V14: 0.2 | W14: 3838 | X14: 3071
A15: 921 147 1116 | C15: REINSCRIPCIÓN | D15: ALEXANDRO VIDAL APOLINAR VELAZQUEZ | E15: MARZO-JUNIO | F15: 1860 | G15: 3006250 | H15: 45838 | I15: 2690 | J15: 45838 | K15: 3006250 | L15: 2490 | M15: 45838 | N15: 3006250 | O15: 5900 | P15: 45868 | Q15: 85902586874321100´
A16: 921 112 7464 | C16: REINSCRIPCIÓN | D16: AZAEL BAILON CANCINO | E16: MARZO-JUNIO | F16: 1860 | G16: 94628 | H16: 45839 | I16: 2690 | J16: 45871 | K16: 8.5902004e+16 | L16: 2490 | M16: 45839 | N16: 94628 | O16: 5900 | P16: 45871 | Q16: 8.5902004e+16
A17: 556 932 1515 | C17: NUEVO INGRESO | D17: MATEO CRUZ PORTILLA | E17: MARZO-JUNIO | F17: 1860 | G17: 5020242 | H17: 45853 | I17: 2690 | J17: 45853 | K17: 5020242 | L17: 2490 | M17: 45853 | N17: 5020242 | O17: 5900 | P17: 45897 | Q17: 5022242
A18: 921 305 2090 | C18: NUEVO INGRESO | D18: DEREK ABDIEL PECH SANTIAGO | E18: MARZO-JUNIO | F18: 1860 | G18: 26500582 | H18: 45845 | L18: 2490 | M18: 45845 | N18: 40017281 | O18: 5900 | P18: 45860 | Q18: 11469359
A19: 921 154 9372 | C19: REINSCRIPCIÓN | D19: DIEGO LARA BARRERA | E19: MARZO-JUNIO | F19: 1860 | G19: HSB5544347 | H19: 45852 | I19: 2690 | J19: 46148 | K19: 57660 | L19: 2490 | M19: 46148 | N19: 57666 | O19: 5900 | P19: 45852 | Q19: HSB5544347
A20: 922 127 2139 | C20: REINSCRIPCIÓN | D20: SEBASTIAN CARRASCO RAMIREZ | E20: MARZO-JUNIO | F20: 2X1 | G20: 2X1 | H20: 45854 | I20: 2690 | J20: 45854 | K20: 250716 | L20: 2490 | M20: 45854 | N20: 250716 | O20: 5900 | P20: 45854 | Q20: 250716
A21: 229 124 7667 | C21: REINSCRIPCIÓN | D21: MARCELO IVAN CRUZ GARCIA | E21: MARZO-JUNIO | F21: 1860 | G21: 785296355 | H21: 45810 | I21: 2690 | J21: 45855 | K21: 785296355 | L21: 2490 | M21: 45810 | N21: 785296355 | O21: 5900 | P21: 45874 | Q21: 26341385
A22: 921 192 2612 | C22: NUEVO INGRESO | D22: JOSUE VALENCIA OCAMPO | E22: MARZO-JUNIO | F22: 1860 | G22: 21370334 | H22: 45856 | I22: 2690 | J22: 45856 | K22: 213703334 | O22: 5900 | P22: 45897 | Q22: 1748 | X22: 2686
A23: 993 397 1246 | C23: REINSCRIPCIÓN | D23: JUAN SEBASTIAN PEREZ SANTOS | E23: MARZO-JUNIO | F23: GRATIS | G23: GRATIS | H23: 45863 | L23: 2490 | M23: 45863 | N23: 56006 | O23: 4200 | P23: 46086
A24: 921 151 4694 | C24: NUEVO INGRESO | D24: GABRIEL ARRIAGA PEREZ | E24: MARZO-JUNIO | F24: 1743 | G24: 35678624 | H24: 45859 | I24: 1883 | J24: 45866 | K24: 75239048 | L24: 1743 | M24: 45859 | N24: 35678624 | O24: 5900 | P24: 45901 | Q24: 56010377´
A25: 921 136 9723 | C25: REINSCRIPCIÓN | D25: LUIS EDUARDO GUITARTH MARTINEZ | E25: MARZO-JUNIO | F25: GRATIS | G25: GRATIS | H25: 45877 | L25: 1550 | M25: 45877 | N25: 90510FS00962067214 | O25: 5500 | P25: 45877 | Q25: 65669 | U25: 10 MESES | V25: 0.25 | W25: 3838.8 | X25: 2879
A26: 921 252 7975 | C26: SIMON BOLIBAR | D26: CLAUDIA MARIA CASTRO CAMACHO | E26: MARZO-JUNIO | F26: GRATIS | G26: GRATIS | H26: 45883 | I26: 1883 | J26: 45915 | K26: 404260 | L26: 1550 | M26: 45915 | N26: 404260 | O26: 3000 | P26: 45915 | Q26: 404260
C27: REINSCRIPCIÓN | D27: LIAM HANIEL ROBLES LIMON | E27: MARZO-JUNIO | F27: 1860 | G27: 93996052 | H27: 45835 | I27: 2690 | J27: 45835 | K27: 93996052 | L27: 2490 | M27: 45835 | N27: 93996052 | O27: 5900 | P27: 45884 | Q27: 4514232 | U27: 10 MESES | V27: 0.25 | W27: 3838.8 | X27: 2879
A28: 938 180 0913 | C28: NUEVO INGRESO | D28: DIANA MARTINEZ MENDOZA | E28: MARZO-JUNIO | F28: GRATIS | G28: GRATIS | H28: 45889 | I28: 1345 | J28: 45889 | K28: 2008250 | L28: 1245 | M28: 45889 | N28: 2008250
A29: 921 257 2547 | C29: SIMON BOLIBAR | D29: CONTRERAS PALACIONS KEIDY ISABELLA | E29: MARZO-JUNIO | F29: GRATIS | G29: GRATIS | H29: 45894 | U29: 12 meses | V29: 0.3 | W29: 3838 | X29: 3239
A30: 921 221 5011 | C30: NUEVO INGRESO | D30: ATENEA ALESSANDRA USCANGA TOLEDO | E30: MARZO-JUNIO | F30: 1860 | G30: 36644385 | H30: 45862 | I30: 2690 | J30: 45862 | K30: 36644385 | L30: 2490 | M30: 45862 | N30: 36644385 | O30: 5900 | P30: 45870 | Q30: 57211632 | U30: 12 meses | V30: 0.2 | W30: 3838 | X30: 2623
A31: 921 240 2488 | C31: SIMON BOLIBAR | D31: KAREN ITZEL VÉLAZQUEZ JIMENEZ | E31: MARZO-JUNIO | F31: GRATIS | G31: GRATIS | H31: 45884 | I31: 1245 | J31: 45922 | K31: 15661754 | L31: 1345 | M31: 45922 | N31: 29462213 | O31: 5900 | P31: 45898 | Q31: 65092656 | R31: 2045 | S31: 45898 | T31: 65092656
B39: COLEGIATURA
B40: N° | C40: MATRICULA | D40: NOMBRE DEL ALUMNO | E40: AGOSTO | H40: SEPTIEMBRE | K40: OCTUBRE | N40: NOVIEMBRE | Q40: DICIEMBRE | T40: ENERO | W40: JULIO | Z40: FEBRERO | AC40: MARZO | AF40: ABRIL | AI40: MAYO | AL40: JUNIO
E41: MONTO | F41: FECHA | G41: FOLIO | H41: MONTO | I41: FECHA | J41: FOLIO | K41: MONTO | L41: FECHA | M41: FOLIO | N41: MONTO | O41: FECHA | P41: FOLIO | Q41: MONTO | R41: FECHA | S41: FOLIO | T41: MONTO | U41: FECHA | V41: FOLIO | W41: MONTO | X41: FECHA | Y41: FOLIO | Z41: MONTO | AA41: FECHA | AB41: FOLIO | AC41: MONTO | AD41: FECHA | AE41: FOLIO | AF41: MONTO | AG41: FECHA | AH41: FOLIO | AI41: MONTO | AJ41: FECHA | AK41: FOLIO | AL41: MONTO | AM41: FECHA | AN41: FOLIO
D42: =D8 -> ALICE YANELI SALINAS TOLEDO | H42: 2494.75 | I42: 45900 | J42: 300825 | K42: 2494.75 | L42: 45935 | M42: 61025 | N42: 2494.75 | O42: 45966 | P42: 1615258 | Q42: 2494.75 | R42: 45993 | S42: 101226 | T42: 2696 | U42: 46022 | V42: 10126 | Z42: 2696 | AA42: 46022 | AB42: 28994436 | AC42: 2696 | AD42: 46084 | AE42: 13205 | AF42: 3094 | AG42: 46144 | AH42: 31434955 | AI42: 2696 | AJ42: 46147 | AK42: 87435645 | AL42: 2696 | AM42: 46178 | AN42: 59924705 | AO42: no fact
C43: PAGO ANUAL | D43: =D9 -> KAORU HIGASHI ALCANTARA | H43: 2686 | I43: 45636 | J43: PAGO TARJETA | K43: 2686 | L43: 46001 | M43: PAGO TARJETA | N43: 2686 | O43: 45636 | P43: PAGO TARJETA | Q43: 2686 | R43: 46001 | S43: PAGO TARJETA | T43: 2686 | U43: 46001 | V43: PAGO TARJETA | Z43: 2686 | AA43: 46001 | AB43: PAGO TARJETA | AC43: 2686 | AD43: 46001 | AE43: PAGO TARJETA | AF43: 2686 | AG43: 46001 | AH43: PAGO TARJETA | AO43: fact ok
D44: =D10 -> AGNES DANIELLE JIMENEZ CALDERON | H44: 2686 | I44: 45904 | J44: 54232768 | K44: 2686 | L44: 45935 | M44: 68089812 | N44: 2686 | O44: 45964 | P44: 131756415619 | Q44: 3086 | R44: 46041 | S44: 1856412 | Z44: 2686 | AA44: 46056 | AB44: 1454302255001 | AC44: 2686 | AD44: 46074 | AE44: 1856412 | AH44: PENDIENTE | AI44: 2686 | AJ44: 46147 | AK44: 157863535380
D45: =D11 -> CESAR MATEO CRUZ LANDA | E45: 2559 | F45: 45750 | G45: 20968661 | H45: 2559 | I45: 45903 | J45: 522224278 | K45: 2559 | L45: 45931 | M45: 3272717 | N45: 2559 | O45: 45963 | P45: 12699903 | Q45: 2559 | R45: 45995 | S45: 72361207 | T45: 2559 | U45: 46027 | V45: 617550 | W45: 2559 | X45: 46013 | Y45: 31898027 | Z45: 2559 | AA45: 46057 | AB45: 12399279 | AC45: 2559 | AD45: 46083 | AE45: 32751424 | AF45: 2559 | AG45: 46116 | AH45: 42076800 | AI45: 2559 | AJ45: 46146 | AK45: 91511543 | AL45: 2559 | AM45: 46176 | AN45: 14047772 | AO45: fact ok
D46: =D12 -> THIAGO ALFONSO FUENTES | H46: 2239 | I46: 45903 | J46: 5537 | K46: 2239 | L46: 45934 | M46: 5537 | N46: 2239 | O46: 45967 | P46: CUENTA5539 | Q46: 2239 | R46: 45997 | S46: cuenta5537 | T46: 2559 | U46: 46037 | V46: HSBC088684 | Z46: 2559 | AA46: 46068 | AB46: CUENTA5537 | AC46: 2239 | AD46: 46082 | AE46: 5537 | AF46: 2239 | AG46: 46116 | AH46: cta5537 | AI46: 2239 | AJ46: 46144 | AK46: SF | AL46: 2239 | AM46: 07706/2026 | AN46: SF | AO46: fact ok
D47: =D13 -> ISABELLA FERNANDA PEREZ VELAZQUEZ | H47: 2559 | I47: 45901 | J47: 98502613 | K47: 2686 | L47: 45936 | M47: 910251 | N47: 2686 | O47: 45967 | P47: 47512693 | Q47: 2686 | R47: 45997 | S47: 9875463214 | T47: 2686 | U47: 46026 | V47: 1301260 | Z47: 2686 | AA47: 46082 | AB47: 73962594 | AC47: 2686 | AD47: 46124 | AE47: 90570999 | AF47: 2686 | AG47: 46133 | AH47: 2686 | AI47: 2728 | AJ47: 46148 | AK47: 11610122 | AL47: 2728 | AM47: 46177 | AN47: 45676335 | AO47: fact ok
D48: =D14 -> ASIEL ROQUE FUENTES | H48: 2686 | I48: 45901 | J48: 14157685 | K48: 3071 | L48: 45931 | M48: 6947927 | N48: 3071 | O48: 45964 | P48: 7507982 | Q48: 3071 | R48: 45994 | S48: 9025676 | T48: 3071 | U48: 46024 | V48: 54897621 | Z48: 3071 | AA48: 46055 | AB48: 4584316 | AC48: 3071 | AD48: 46086 | AE48: 77568016 | AF48: 3071 | AG48: 46113 | AH48: 6932914 | AI48: 3071 | AJ48: 46145 | AK48: 69346061 | AL48: 3071 | AM48: 46177 | AN48: 18480826 | AO48: fact ok
D49: =D15 -> ALEXANDRO VIDAL APOLINAR VELAZQUEZ | H49: 2559 | I49: 45901 | J49: APROB 4854 | K49: 2559 | L49: 45901 | M49: APROB 4854 | N49: 2559 | O49: 45901 | P49: APROB 4854 | Q49: 2559 | R49: 45901 | S49: APROB 4854 | T49: 2559 | U49: 45901 | V49: APROB 4854 | Z49: 2559 | AA49: 46058 | AB49: 50113171 | AC49: 2559 | AD49: 46058 | AE49: 50113171 | AF49: 2559 | AG49: 46058 | AH49: 50113171 | AI49: 2559 | AJ49: 46058 | AK49: 50113171 | AL49: 2559 | AM49: 46058 | AN49: 50113171 | AO49: fact ok
D50: =D16 -> AZAEL BAILON CANCINO | H50: 2686 | I50: 45904 | J50: 8.590118e+16 | K50: 2688 | L50: 45932 | M50: 8.590161e+16 | N50: 3000 | O50: 45966 | P50: 8.5901592e+16 | Q50: 2680 | R50: 45996 | S50: 8.5902057e+16 | T50: 2688 | U50: 46027 | V50: 8.5904068e+16 | Z50: 2688 | AA50: 46058 | AB50: TRANF | AC50: 3000 | AD50: 149289 | AE50: 8.5901493e+16 | AF50: 2790 | AG50: 46118 | AH50: 8.590762e+16 | AI50: 2780 | AJ50: 46134 | AK50: 311262 | AL50: 2780 | AM50: 46179 | AN50: 294315561 | AO50: fact ok
D51: =D17 -> MATEO CRUZ PORTILLA | H51: 2239 | I51: 45906 | J51: 8.5903393e+16 | K51: 2239.3 | L51: 45935 | M51: KLAR OP | N51: 2239.3 | O51: 45966 | P51: 241399 | Q51: 2239.3 | R51: 45996 | S51: 8.5909404e+16 | T51: 2239.3 | U51: 46058 | V51: 617550 | Z51: 2239.3 | AA51: 46086 | AB51: 12399279 | AC51: 2239.3 | AD51: 46087 | AE51: 54879213 | AF51: 2239.3 | AG51: 46116 | AH51: 8.5901e+16 | AI51: 2239 | AJ51: 46146 | AK51: 312461 | AL51: 2634.3 | AM51: 46182 | AN51: 15761473 | AO51: fact ok
D52: =D18 -> DEREK ABDIEL PECH SANTIAGO | H52: 2879 | I52: 45903 | J52: 303799 | K52: 2879 | L52: 45937 | M52: 60314266 | N52: 2879 | O52: 45968 | P52: 86908758 | Q52: 2879 | R52: 46000 | S52: 1110858 | T52: 2879 | U52: 46027 | V52: 79837487 | Z52: 2879 | AA52: 46063 | AB52: 53689987 | AC52: 2879 | AD52: 46090 | AE52: 30510673 | AF52: 2879 | AG52: 46116 | AH52: 59083070 | AI52: 2879 | AJ52: 46153 | AK52: 54045648 | AL52: 2879 | AM52: 46181 | AN52: 61969047 | AO52: no fact
D53: =D19 -> DIEGO LARA BARRERA | E53: 2623 | F53: 45905 | G53: HSBC332368 | H53: 2623 | I53: 45905 | J53: HSBC437843 | K53: 2623 | L53: 45926 | M53: HSBC492765 | N53: 2623 | O53: 45965 | P53: HSBC578453 | Q53: 3023 | R53: 46036 | S53: HSBC141303 | T53: 3023 | U53: 46036 | V53: HSBC141303 | W53: 2623 | X53: 46207 | Y53: 78564 | Z53: 3023 | AA53: 46036 | AB53: HSBC141303 | AC53: 2623 | AD53: 46085 | AE53: HSBC501804 | AF53: 3023 | AG53: 46143 | AH53: 5465934 ($2,623) 06216 ($400) | AI53: 2623 | AJ53: 46143 | AK53: 740 | AL53: 2623 | AM53: 46176 | AN53: 44773 | AO53: no fact
D54: =D20 -> SEBASTIAN CARRASCO RAMIREZ | H54: 2239 | I54: 45903 | J54: 250903 | K54: 2239 | L54: 45932 | M54: 251001 | N54: 2239 | O54: 45966 | P54: 4525 | Q54: 2239 | R54: 45992 | S54: 251201 | T54: 2239 | U54: 46027 | V54: 6715 | Z54: 2239 | AA54: 46058 | AB54: 260205 | AC54: 2239 | AD54: 46087 | AE54: 260306 | AF54: 2239 | AG54: 46119 | AH54: CTA6715 | AI54: 2623 | AJ54: 46148 | AK54: 119640 | AL54: 2239 | AM54: 46180 | AN54: 272659 | AO54: fact ok
D55: =D21 -> MARCELO IVAN CRUZ GARCIA | H55: 2623 | I55: 45909 | J55: 98386086 | K55: 2623 | L55: 45935 | M55: 58281065 | N55: 2623 | O55: 45966 | P55: 55095766 | Q55: 2623 | R55: 46387 | S55: 37952963 | T55: 2623 | U55: 46387 | V55: 37952963 | W55: 2623 | X55: 46387 | Y55: 37952963 | Z55: 2623 | AA55: 46085 | AB55: 32766805 | AC55: 2623 | AD55: 46085 | AE55: 29259165 | AF55: 2623 | AG55: 46138 | AH55: 1185606 | AI55: 2623 | AJ55: 46147 | AK55: 4528832 | AL55: 3023 | AM55: 46191 | AN55: 54380000
D56: =D22 -> JOSUE VALENCIA OCAMPO | H56: 2686 | I56: 45905 | J56: 4548 | K56: 2686 | L56: 45933 | M56: 3935 | N56: 2686 | O56: 45966 | P56: 2911 | Q56: 2686 | R56: 45997 | S56: 7701 | T56: 2686 | U56: 46027 | V56: 5478 | Z56: 2786 | AA56: 46058 | AB56: 9519 | AC56: 2786 | AD56: 46086 | AE56: 1169 | AF56: 2686 | AG56: 46107 | AH56: 1478 | AI56: 2786 | AJ56: 46146 | AK56: 285 (tarjeta) | AL56: 2786 | AM56: 05706/2026 | AN56: 92896 TC | AO56: fact ok
D57: =D23 -> JUAN SEBASTIAN PEREZ SANTOS | H57: 1800 | I57: 45901 | J57: 5884235 | K57: 1800 | L57: 45936 | M57: 754869 | N57: 1800 | O57: 45967 | P57: 1512114 | Q57: 1800 | R57: 45993 | S57: 9845027 | T57: 1800 | U57: 46069 | V57: PTDC | Z57: 1800 | AA57: 46058 | AB57: 54789631 | AC57: 1800 | AD57: 46086 | AE57: 43035 | AF57: 1800 | AG57: 46114 | AH57: 44056 | AI57: 1800 | AJ57: 46149 | AK57: $1500 - 291 (tarjeta) $300 transf 6431 | AL57: 1800 | AM57: 46181 | AN57: 39099 TD | AO57: no fact
D58: =D24 -> GABRIEL ARRIAGA PEREZ | E58: 2399.25 | F58: 45870 | G58: 90182870 | H58: 2399.25 | I58: 45901 | J58: 11269419 | K58: 2399.25 | L58: 45931 | M58: 67517233 | N58: 2239.25 | O58: 45966 | P58: 93903453 | Q58: 2399.25 | R58: 45992 | S58: 16865832 | T58: 2399.25 | U58: 46028 | V58: 67285183 | W58: 2399.25 | X58: 46022 | Y58: 76766709 | Z58: 2399.25 | AA58: 46144 | AB58: 11139369 | AC58: 2399.25 | AD58: 46085 | AE58: 16863636 | AF58: 2399.25 | AG58: 46117 | AH58: 35295225 | AI58: 2399 | AJ58: 46147 | AK58: 72232916 | AL58: 2399.25 | AM58: 46174 | AN58: 94515748 | AO58: fact ok
D59: =D25 -> LUIS EDUARDO GUITARTH MARTINEZ | H59: 2686 | I59: 45910 | J59: 54869750 | K59: 3086 | L59: 45971 | M59: 8.5904519e+16 | N59: 2686 | O59: 45965 | P59: 8.590483e+16 | Q59: 2686 | R59: 46010 | S59: 8.5903469e+16 | T59: 2686 | U59: 46027 | V59: 8.5906031e+16 | Z59: 2686 | AA59: 46056 | AB59: 8.5900759e+16 | AC59: 2686 | AD59: 46094 | AE59: 8.5900759e+16 | AH59: PEND ENV COMP | AI59: 2686 | AJ59: 46147 | AK59: 312563 | AL59: 2686 | AM59: 05/0672026 | AN59: 799705 TC | AO59: no fact
D60: =D26 -> CLAUDIA MARIA CASTRO CAMACHO | E60: 2879 | F60: 45895 | G60: 35154 | H60: 2879 | I60: 45895 | J60: 35154 | K60: 2879 | L60: 45937 | M60: 852805 | N60: 3279 | O60: 45974 | P60: 8.5900595e+16 | Q60: 2879 | R60: 45992 | S60: 8.5908006e+16 | T60: 2879 | U60: 46024 | V60: AUT785263 | Z60: 2879 | AA60: 46058 | AB60: 8.5906902e+16 | AC60: 2879 | AD60: 46080 | AE60: 648883 | AF60: 2879 | AG60: 46112 | AH60: 8.090084e+16 | AI60: 3279 | AJ60: 46153 | AK60: 667628 | AL60: 2879 | AM60: 46174 | AN60: 725120 | AO60: no fact
D61: =D27 -> LIAM HANIEL ROBLES LIMON | H61: 2800 | I61: 45954 | J61: 9464 | K61: 2800 | L61: 45937 | M61: 9464 | N61: 2400 | O61: 45966 | P61: CTA9464 | Q61: 2400 | R61: 45998 | S61: 4102 | T61: 2800 | U61: 46058 | V61: 9464 | W61: 2400 | X61: 45998 | Y61: 4102 | Z61: 2400 | AA61: 46058 | AB61: 9464 | AC61: 2400 | AD61: 46088 | AE61: CTA9464 | AF61: 2400 | AG61: 46117 | AH61: CTA9464 | AI61: 2400 | AJ61: 46148 | AK61: CTA 9464 | AL61: 2800 | AM61: 24706/2026 | AN61: 7576
D62: =D28 -> DIANA MARTINEZ MENDOZA | E62: 2239 | F62: 45903 | G62: debit | H62: 2239 | I62: 45934 | J62: debit | K62: 2239 | L62: 45934 | M62: 62478 | N62: 2239 | O62: 45966 | P62: 111250 | Q62: 2239 | R62: 45996 | S62: 68541263 | T62: 2239 | U62: 46058 | V62: 87964123 | W62: 2239 | X62: 46007 | Y62: 280516 | Z62: 2239 | AA62: 46059 | AB62: 60260 | AC62: 2239 | AD62: 46086 | AE62: 897451 | AF62: 2230 | AG62: 46115 | AH62: 304261 | AI62: 2239 | AJ62: 46143 | AK62: 25654750 | AL62: 2239 | AM62: 46177 | AN62: 406261 | AO62: fact ok
C63: ANUAL ??? | D63: =D29 -> CONTRERAS PALACIONS KEIDY ISABELLA | H63: 2239 | I63: 45904 | J63: 943575 | K63: 2239 | L63: 45944 | M63: 495753 | N63: 2239 | O63: 45944 | P63: 495753 | Q63: 2239 | R63: 45944 | S63: 495753 | T63: 2239 | U63: 45944 | V63: 495753 | W63: 2239 | X63: 45944 | Y63: 495753 | Z63: 2239 | AA63: 45944 | AB63: 495753 | AC63: 2239 | AD63: 45944 | AE63: 495753 | AF63: 2239 | AG63: 45944 | AH63: 495753 | AI63: 2239 | AJ63: 45944 | AK63: 495753 | AO63: no fact
D64: =D30 -> ATENEA ALESSANDRA USCANGA TOLEDO | E64: 2623 | F64: 45873 | G64: 49196170 | H64: 2623 | I64: 45903 | J64: 8810273 | K64: 2623 | L64: 45931 | M64: 19906239 | N64: 2623 | O64: 45966 | P64: 12118880 | Q64: 2623 | R64: 45992 | S64: 8814856 | T64: 2623 | U64: 46027 | V64: 72906408 | W64: 2623 | X64: 45992 | Y64: 8814856 | Z64: 2623 | AA64: 46057 | AB64: 76506622 | AC64: 2623 | AD64: 46109 | AE64: 77399211 | AF64: 2623 | AG64: 46113 | AH64: 81634893 | AI64: 2623 | AJ64: 46143 | AK64: 61428728 | AL64: 2623 | AM64: 46173 | AN64: 19809513 | AO64: no fact
D65: =D31 -> KAREN ITZEL VÉLAZQUEZ JIMENEZ | H65: 2623 | I65: 45905 | J65: 45896630 | K65: 3023 | L65: 45960 | M65: 45965421 | N65: 3086 | O65: 46022 | P65: 311225 | Q65: 3086 | R65: 45997 | S65: 311225 | T65: 3086 | U65: 46027 | V65: 110326 | W65: 3083 | X65: 46055 | Y65: 140326 | Z65: 3086 | AA65: 46088 | AB65: 260326 | AC65: 3086 | AD65: 46106 | AE65: 260326 | AF65: 3086 | AO65: POR WAT QUE EL DIA 02 LIQUIDA

Sheet 4°P
F1: Centro de Investigación Educativa Colegio San Diego | S1: ACEPTADOS POR CORPORATIVO
F2: Punta el Campanario #183 Col. Bahia de San Martín CP 96536 | S2: PAGOS DE HIJOS DE MAESTROS
F3: PREESCOLAR 30PJN1037Z PRIMARIA 30PPR3773B SECUNDARIA 30PES0033G | S3: MES PAGADO
D4: FACTURA | F4: CICLO ESCOLAR 2024-2025 | S4: ALUMNO DADO DE BAJA
B7: N° | C7: MATRICULA | D7: NOMBRE DEL ALUMNO | E7: PROMOCION | F7: INSCRIPCION | G7: FOLIO | H7: FECHA | I7: MATERIAL | J7: FECHA | K7: FOLIO | L7: ARANCEL | M7: FECHA | N7: FOLIO | O7: LIBROS | P7: FECHA | Q7: FOLIO | R7: UNIFORMES | S7: FECHA | T7: FOLIO | U7: PLAN PAGO | V7: BECA | W7: COLEG | X7: TOTAL
A8: 782 829 8093
A9: 921 261 1444 | C9: 20% DESCUENTO ARANCEL | D9: EMIR ELÍAS GUZMÁN POSADAS | E9: ENERO- FEBRERO | F9: 1550 | G9: 2402250 | H9: 45712 | I9: 2690 | J9: 45838 | K9: 8.5900054e+16 | L9: 1992 | M9: 45712 | N9: 2402250 | O9: 4000 | P9: 45901 | Q9: 8.5905693e+16 | U9: 12 MESES | V9: 0.2 | W9: 3199 | X9: 2559
A10: 921 246 4886 | C10: REINSCRIPCIÓN | D10: MARIA ESTHER HERNANDEZ VARGAS | E10: ENERO- FEBRERO | F10: 1550 | G10: HSBC344475 | H10: 45716 | I10: 2690 | J10: 45866 | K10: 9300304 | L10: 1992 | M10: 45866 | N10: 291018 | O10: 5900 | P10: 45957 | Q10: 281018
A11: Papá:916 116 2460/mamá 921 240 5771 | C11: NUEVO INGRESO | D11: EMILIANO NARVAEZ MARTINEZ | E11: ENERO- FEBRERO | F11: GRATIS | G11: GRATIS | H11: 45898 | I11: 1345 | J11: 45899 | K11: Pago con tarjeta | L11: 1245 | M11: 45899 | N11: Pago con tarjeta | O11: 5900 | P11: 45928 | Q11: 14597856 | U11: 12 MESES | V11: 0.3 | W11: 3199 | X11: 2239
A12: 921 256 2170 | C12: NUEVO INGRESO | D12: ALANA XIMENA CASTILLO ABREU | E12: ENERO- FEBRERO | F12: GRATIS | G12: GRATIS | H12: GRATIS | I12: 2690 | J12: 45824 | K12: 98851283 | L12: 2490 | M12: 45824 | N12: 988851283 | O12: 5900 | P12: 45884 | Q12: 71494998 | U12: 10 MESES | V12: 0.25 | W12: 3838.8 | X12: 2879
A13: 921 276 2448 | C13: REINSCRIPCIÓN | D13: FRANCISCO MALIK HEREDIA DOMÍNGUEZ | E13: MARZO-JUNIO | F13: 1860 | G13: 250708 | H13: 45846 | I13: 2690 | J13: 45846 | K13: 250708 | L13: 2490 | M13: 45854 | N13: 250708 | O13: 5900 | P13: 45887 | Q13: 250818 | U13: 10 MESES | V13: 0.18 | W13: 3838.8 | X13: 3147
A14: 921 134 7825 | C14: NUEVO INGRESO | D14: JOSE MARIA MARTINEZ TADEO | E14: MARZO-JUNIO | F14: GRATIS | G14: GRATIS | H14: 45898 | I14: 2690 | J14: 45900 | K14: 585317 | L14: 2490 | M14: 45900 | N14: 5851317 | O14: 5900 | P14: 45901 | Q14: 1303670
A15: 921 140 2401 | C15: REINSCRIPCIÓN | D15: MIRANDA REYES ESCOBAR | E15: MARZO-JUNIO | F15: GRATIS | G15: GRATIS | H15: 45901 | U15: 10 MESES | V15: 0.3 | W15: 3838.8 | X15: 2687
A16: 921 140 2401 | C16: REINSCRIPCIÓN | D16: CONSTANZA REYES ESCOBAR | E16: MARZO-JUNIO | F16: GRATIS | G16: GRATIS | H16: 45901 | U16: 10 MESES | V16: 0.3 | W16: 3838.8 | X16: 2687
B29: COLEGIATURA
B30: N° | C30: MATRICULA | D30: NOMBRE DEL ALUMNO | E30: AGOSTO | H30: SEPTIEMBRE | K30: OCTUBRE | N30: NOVIEMBRE | Q30: DICIEMBRE | T30: ENERO | W30: JULIO | Z30: FEBRERO | AC30: MARZO | AF30: ABRIL | AI30: MAYO | AL30: JUNIO
C32: FACT | D32: =D9 -> EMIR ELÍAS GUZMÁN POSADAS | E32: 2559 | F32: 45874 | G32: 39874855 | H32: 2559 | I32: 45910 | J32: 38736109 | K32: 2559 | L32: 45936 | M32: 8.5904479e+16 | N32: 2559 | O32: 45967 | P32: 55116694 | Q32: 2559 | R32: 45997 | S32: 58628374 | T32: 2559 | U32: 46027 | V32: 17895983 | Z32: 2559 | AA32: 46055 | AB32: 19010475 | AC32: 2559 | AD32: 46086 | AE32: 59573223 | AF32: 2559 | AG32: 46117 | AH32: 66843314 | AI32: 2559 | AJ32: 46147 | AK32: 10040008 | AL32: 2559 | AM32: 46181 | AN32: 959113 TC | AO32: fact ok
D33: =D10 -> MARIA ESTHER HERNANDEZ VARGAS | H33: 2239 | I33: 45912 | J33: 4121821 | K33: 2239.3 | L33: 45935 | M33: 281018 | N33: 2239 | O33: 45967 | P33: 40741 | Q33: 2239 | R33: 46386 | S33: 7604251 | T33: 2239 | U33: 46023 | V33: 1755783 | Z33: 2239 | AA33: 46087 | AB33: 6879938 | AC33: 2239 | AD33: 46129 | AE33: 85534 | AF33: 2239 | AG33: 46129 | AH33: 6919545 | AI33: 2239.3 | AJ33: 46156 | AK33: 9106373 | AL33: 2239.3 | AM33: 46177 | AN33: 2068462 | AO33: fact ok
D34: =D11 -> EMILIANO NARVAEZ MARTINEZ | H34: 2239 | I34: 45906 | J34: 38975648 | K34: 2239 | L34: 45936 | M34: 8.5901442e+16 | N34: 2239 | O34: 45966 | P34: 8.5900663e+16 | Q34: 2239 | R34: 45996 | S34: 8.5900999e+16 | T34: 2239 | U34: 46027 | V34: 8.5909704e+16 | Z34: 2239 | AA34: 46057 | AB34: 8.59078e+16 | AC34: 2239 | AD34: 46085 | AE34: 8.5907614e+16 | AF34: 2239 | AG34: 46117 | AH34: 8.5908582e+16 | AI34: 2240 | AJ34: 46146 | AK34: 312469
D35: =D12 -> ALANA XIMENA CASTILLO ABREU | H35: 2879 | I35: 45909 | J35: 395842 | K35: 2879 | L35: 45936 | M35: 32DNDI | N35: 2879 | O35: 45966 | P35: 493600 | Q35: 2879 | R35: 45996 | S35: 90846355 | T35: 3279 | U35: 46036 | V35: DEBITCARD | Z35: 2879 | AA35: 46056 | AB35: 477986 | AC35: 2879 | AD35: 46086 | AE35: 201243 | AF35: 2879 | AG35: 46117 | AH35: 56879412 | AI35: 2879 | AJ35: 46147 | AK35: 23254008 | AL35: 2879 | AM35: 46178 | AN35: 61453777 | AO35: fact ok
D36: =D13 -> FRANCISCO MALIK HEREDIA DOMÍNGUEZ | H36: 3147 | I36: 45905 | J36: 250905 | K36: 3147 | L36: 45935 | M36: 251005 | N36: 3147 | O36: 45966 | P36: 251105 | Q36: 3147 | R36: 45996 | S36: 251205 | T36: 3147 | U36: 46027 | V36: 260105 | Z36: 3147 | AA36: 46144 | AB36: 260205 | AC36: 3147 | AD36: 46086 | AE36: 260305 | AF36: 3147 | AG36: 46118 | AH36: 260406 | AI36: 3147 | AJ36: 46147 | AK36: 604917 | AL36: 3147 | AM36: 46178 | AN36: 326879 | AO36: no fact
D37: =D14 -> JOSE MARIA MARTINEZ TADEO | H37: 2623 | I37: 45905 | J37: 3136259 | K37: 2623 | L37: 45939 | M37: 3050285 | N37: 3023 | O37: 46032 | P37: 8.5901319e+16 | Q37: 3023 | R37: 46032 | S37: 8.5901319e+16 | T37: 3023 | U37: 46032 | V37: 8.5901319e+16 | Z37: 3023 | AA37: 46032 | AB37: 8.5901319e+16 | AC37: 3023 | AD37: 46103 | AE37: 8.5900562e+16 | AF37: 3023 | AG37: 46103 | AH37: SF
D38: =D15 -> MIRANDA REYES ESCOBAR | H38: 2680 | I38: 45906 | J38: 76206548 | K38: 2680 | L38: 45934 | M38: 58649042 | N38: 2680 | O38: 45966 | P38: SF | Q38: 2680 | R38: 45996 | S38: SF | T38: 2680 | U38: 46027 | V38: 28235253 | Z38: 2680 | AA38: 46027 | AB38: TRANSF | AC38: 2680 | AD38: 46087 | AE38: 91378914 | AF38: 2680 | AG38: 46117 | AH38: 1584619706
D39: =D16 -> CONSTANZA REYES ESCOBAR | H39: 2680 | I39: 45906 | J39: 53949849 | K39: 2680 | L39: 45934 | M39: 22966164 | N39: 2680 | O39: 45966 | P39: SF | Q39: 2680 | R39: 45996 | S39: SF | T39: 2680 | U39: 46027 | V39: 98405673 | Z39: 2680 | AA39: 46027 | AB39: TRANSF | AC39: 2680 | AD39: 46087 | AE39: 87987959 | AF39: 2680 | AG39: 46117 | AH39: 1584619706
H50: 2879

Sheet 5°P
F1: Centro de Investigación Educativa Colegio San Diego | S1: ACEPTADOS POR CORPORATIVO
F2: Punta el Campanario #183 Col. Bahia de San Martín CP 96536 | S2: PAGOS DE HIJOS DE MAESTROS
F3: PREESCOLAR 30PJN1037Z PRIMARIA 30PPR3773B SECUNDARIA 30PES0033G | S3: MES PAGADO
D4: FACTURA | F4: CICLO ESCOLAR 2024-2025 | S4: ALUMNO DADO DE BAJA
B7: N° | C7: MATRICULA | D7: NOMBRE DEL ALUMNO | E7: PROMOCION | F7: INSCRIPCION | G7: FOLIO | H7: FECHA | I7: MATERIAL | J7: FECHA | K7: FOLIO | L7: ARANCEL | M7: FECHA | N7: FOLIO | O7: LIBROS | P7: FECHA | Q7: FOLIO | R7: UNIFORMES | S7: FECHA | T7: FOLIO | U7: PLAN PAGO | V7: BECA | W7: COLEG | X7: TOTAL
A8: 921 305 2256 | B8: REINSCRITO | D8: DERECK BONILLA MARTINEZ | E8: NOVIEMBRE-DICIEMBRE | F8: 1550 | G8: SF | H8: 45630 | I8: 2690 | J8: 45749 | K8: 2579868815 | O8: 5900 | P8: 45804 | Q8: 7356956565
A9: 921 172 7241 | B9: REINSCRITO | D9: RODRIGO SORIANO LAVÍN | E9: NOVIEMBRE-DICIEMBRE | F9: 1550 | G9: 4837211 | H9: 45608 | O9: 1000 | P9: 45871 | Q9: 20825 | U9: 10 MESES | V9: 0.3 | W9: 3838 | X9: 2686
A10: 782 136 4624 | B10: REINSCRITO | D10: GUTIERREZ VEGA DAYRA VANESA | E10: NOVIEMBRE-DICIEMBRE | F10: 1550 | G10: 8.5902125e+16 | H10: 45656 | I10: 2690 | J10: 45656 | K10: 8.5902125e+16 | L10: 2490 | M10: 45656 | N10: 8.5902125e+16 | O10: 5500 | P10: 45805 | Q10: 8.5903073e+16
A11: 921 177 3402 | B11: REINSCRITO | D11: RAUL MANUEL HAMILTON ARIAS | E11: NOVIEMBRE-DICIEMBRE | F11: 1550 | G11: SF | H11: 45656 | I11: 2690 | J11: 45908 | L11: 2490 | M11: 45908 | O11: 5900 | P11: 45910 | Q11: 1096 | U11: 10 MESES | V11: 0.25 | W11: 3838 | X11: 2879
A12: 921 273 2901 | B12: REINSCRITO | D12: LUNA ALEJANDRA OSORIO CARBALLO | E12: ENERO-FEBRERO | F12: 1550 | G12: 90510FS00962067214 | H12: 45693 | O12: 5500 | P12: 45806 | Q12: 65669 | Z12: =3478.8*0.3 -> 1043.64
A13: 921 125 9896 | B13: NUEVO INGRESO | D13: TANIA ALEXA SALVADOR MARTINEZ | E13: ENERO-FEBRERO | F13: 1550 | G13: 9395584719 | H13: 45712 | I13: 1345 | J13: 45914 | K13: 10706804 | L13: 1992 | M13: 45712 | N13: 9395584719 | O13: 5900 | P13: 45884 | Q13: 46297519 | R13: 3085 | S13: 45895 | T13: 29558936 | Z13: =3478.8-Z12 -> 2435.16
A14: 921 139 3753 | B14: REINSCRITO | D14: ANGEL MATEO VELAZQUEZ GARCIA | E14: ENERO-FEBRERO | F14: 1550 | G14: 9730089422 | H14: 45716 | I14: 2690 | J14: 45733 | K14: 1187534286 | L14: 2490 | M14: 45716 | N14: 9730089422 | O14: 5900 | P14: 45875 | Q14: 56937164
A15: 921 119 3553 | B15: NUEVO INGRESO | C15: HERMANA DE RENATA SEC COMUNCIARSE CON LA MAMÁ DE RENATA | D15: GISSEL ADHARA LOPEZ CRUZ | E15: MARZO-JUNIO | F15: 1550 | G15: 50725 | H15: 45843 | I15: 2690 | J15: 45897 | K15: SF | L15: 2490 | M15: 45897 | N15: 178267 | O15: 5900 | P15: 45897 | Q15: 178267 | R15: 3085 | S15: 45897 | T15: 178267 | U15: 12 MESES | V15: 0.3 | W15: 3199 | X15: 2239
A16: 921 268 5925 | B16: REINSCRIPCIÓN | D16: MAXIMILIANO CISNEROS VILLEGAS | E16: MARZO-JUNIO | F16: 1700 | G16: 6708635 | H16: 45848 | I16: 2690 | J16: 45748 | K16: 221514 | L16: 790 | M16: 45748 | N16: 221514 | O16: 5900 | P16: 45869 | Q16: 9584764
A17: 922 127 2139 | B17: REINSCRIPCIÓN | D17: ANGEL MATHIAS CARRASCO RAMIREZ | E17: MARZO-JUNIO | F17: 1860 | G17: 250716 | H17: 45854 | I17: 2690 | J17: 45854 | K17: 250716 | L17: 2490 | M17: 45854 | N17: 250716 | O17: 5900 | P17: 45824 | Q17: 250716
A18: 921 192 2612 | B18: NUEVO INGRESO | D18: YESHUA FERNANDO VALENCIA OCAMPO | E18: JULIO | F18: 2X1 | G18: 21370334 | H18: 45856 | I18: 2690 | J18: 45856 | K18: 213703334 | O18: 5900 | P18: 45897 | Q18: 1748
B19: REINSCRIPCIÓN | D19: DANIELA MICHELLE ULIN GARCIA | E19: NOVIEMBRE-DICIEMBRE | F19: 1450 | G19: 4647997 | H19: 45677 | U19: 10 MESES
A20: 24 | B20: NUEVO INGRESO | C20: SIMON BOLIVAR | D20: VALENTINA GARCIA RUIZ | E20: MARZO-JUNIO | F20: 1860 | G20: 59269061 | H20: 45861 | I20: 1345 | L20: 1743 | M20: 45861 | N20: 59269061 | O20: 5900 | P20: 45888 | Q20: 1245877 | R20: 3085 | S20: 45888 | T20: 1245877 | U20: 10 MESES | V20: 0.3 | X20: 2687
A21: 922 140 6895 | B21: REINSCRIPCIÓN | C21: EL MARTES 26 HACE LOS PAGOS | D21: BETZABE PEREZ REYES | E21: MARZO-JUNIO | F21: GRATIS | G21: GRATIS | H21: 45898 | I21: 1345 | J21: 45898 | K21: 87801674 | L21: 1245 | M21: 45898 | N21: 87801674 | O21: 5900 | P21: 45906 | Q21: 9712449
A22: 921 285 5765 | B22: REINSCRIPCIÓN | C22: EL MARTES 26 HACE LOS PAGOS | D22: GUILLERMO MIKAEL CHAVEZ | E22: MARZO-JUNIO | F22: GRATIS | G22: GRATIS | H22: 45895 | I22: 2690 | J22: 45894 | K22: 1997964 | L22: 1245 | M22: 45894 | N22: 1997964 | O22: 5900 | P22: 45894 | Q22: 1997964
A23: 961 300 0674 | B23: REINSCRIPCIÓN | D23: ARANTXA ROSAS SANCHEZ | E23: MARZO-JUNIO | F23: GRATIS | G23: GRATIS | H23: 45900 | I23: 1345 | J23: 45900 | K23: SF | L23: 1245 | M23: 45900 | N23: SF | O23: 5900 | P23: 45912 | Q23: 2493 | U23: 10 MESES | V23: 0.3 | X23: 2687
G27: =F16+I16+L16 -> 5180
B30: COLEGIATURA
B31: N° | C31: MATRICULA | D31: NOMBRE DEL ALUMNO | E31: AGOSTO | H31: SEPTIEMBRE | K31: OCTUBRE | N31: NOVIEMBRE | Q31: DICIEMBRE | T31: ENERO | W31: JULIO | Z31: FEBRERO | AC31: MARZO | AF31: ABRIL | AI31: MAYO | AL31: JUNIO
E32: MONTO | F32: FECHA | G32: FOLIO | H32: MONTO | I32: FECHA | J32: FOLIO | K32: MONTO | L32: FECHA | M32: FOLIO | N32: MONTO | O32: FECHA | P32: FOLIO | Q32: MONTO | R32: FECHA | S32: FOLIO | T32: MONTO | U32: FECHA | V32: FOLIO | W32: MONTO | X32: FECHA | Y32: FOLIO | Z32: MONTO | AA32: FECHA | AB32: FOLIO | AC32: MONTO | AD32: FECHA | AE32: FOLIO | AF32: MONTO | AG32: FECHA | AH32: FOLIO | AI32: MONTO | AJ32: FECHA | AK32: FOLIO | AL32: MONTO | AM32: FECHA | AN32: FOLIO
C33: FACTURA | D33: =D8 -> DERECK BONILLA MARTINEZ | H33: 2879 | I33: 45901 | J33: 71535198 | K33: 2879 | L33: 45931 | M33: 57564043 | N33: 2879 | O33: 45964 | P33: 13093888 | Q33: 2879 | R33: 45993 | S33: 72290525 | T33: 2879 | U33: 46025 | V33: 53270951 | Z33: 2879 | AA33: 46056 | AB33: 88690604 | AC33: 2879 | AD33: 46084 | AE33: 58449974 | AF33: 2878 | AG33: 46113 | AH33: 55025245 | AI33: 2878 | AJ33: 46143 | AK33: 45596536 | AL33: 2879 | AM33: 46175 | AN33: 35973757
D34: =D9 -> RODRIGO SORIANO LAVÍN | H34: 2686 | I34: 45903 | J34: 3358411 | K34: 3086 | L34: 45940 | M34: 3583541 | N34: 2686 | O34: 45966 | P34: 9061654 | Q34: 2686 | R34: 45996 | S34: 55669878 | T34: 2686 | U34: 46025 | V34: 2069159 | Z34: 2686 | AA34: 46056 | AB34: 217431 | AC34: 2686 | AD34: 46085 | AE34: 40326 | AF34: 2686 | AG34: 46113 | AH34: 663958 | AI34: 2686 | AJ34: 46146 | AK34: 405226 | AL34: 2686 | AM34: 46176 | AN34: 2152112 | AO34: fact ok
D35: =D10 -> GUTIERREZ VEGA DAYRA VANESA | H35: 2687 | I35: 45903 | J35: 93843846 | K35: 2687 | L35: 45931 | M35: 9217927 | N35: 2687 | O35: 45966 | P35: 48765616 | Q35: 2687 | R35: 46000 | S35: 36193672 | T35: 2687 | U35: 46027 | V35: 78923078 | Z35: 2687 | AA35: 46056 | AB35: 8822285 | AC35: 2687 | AD35: 46086 | AE35: 99922069 | AF35: 2687 | AG35: 46115 | AH35: 79836391 | AI35: 2687 | AJ35: 46147 | AK35: 52361928 | AL35: 2687 | AM35: 46174 | AN35: 51920061
D36: =D11 -> RAUL MANUEL HAMILTON ARIAS | H36: 2879 | I36: 45905 | J36: 69790407 | K36: 2879 | L36: 45935 | M36: 6736672 | N36: 2879 | O36: 45964 | P36: 20585830 | Q36: 2879 | R36: 46048 | S36: 36793852 | T36: 2879 | U36: 46078 | V36: CTA4706 | Z36: 2879 | AA36: 46106 | AB36: 31010 TD | AC36: 2879 | AD36: 46106 | AE36: 31010 TD | AF36: 2879 | AG36: 46161 | AH36: TRANS TAR DEB | AI36: 2879 | AJ36: 46183 | AK36: 134641 | AO36: COMENTA QUE ANTES DE FINALIZAR EL MES CUBRE LO DE MAYO Y EN JUNIO PAGA LOS RECARGOS
D37: =D13 -> TANIA ALEXA SALVADOR MARTINEZ | H37: 2687 | I37: 45919 | J37: 5073899 | K37: 2687 | L37: 45936 | M37: 13183289 | N37: 2687 | O37: 45964 | P37: 14822391 | Q37: 2687 | R37: 45993 | S37: 26992059 | T37: 2687 | U37: 46037 | V37: 93127018 | Z37: 2687 | AA37: 46055 | AB37: PCT | AC37: 2687 | AD37: 46055 | AE37: PCT | AF37: 2687 | AG37: 46086 | AH37: 465671 | AI37: 2687 | AJ37: 46086 | AK37: 465671 | AL37: 2687 | AM37: 46163 | AN37: 767653 TC | AO37: fact ok
D38: =D14 -> ANGEL MATEO VELAZQUEZ GARCIA | E38: 2240 | F38: 45902 | G38: 9685 | H38: 2240 | I38: 45902 | J38: 9685 | K38: 2240 | L38: 45932 | M38: 9685 | N38: 2240 | O38: 45966 | P38: 9685 | Q38: 2240 | R38: 45999 | S38: 9865 | T38: 2240 | U38: 46022 | V38: 9865 | W38: 2240 | X38: 45999 | Y38: 9865 | Z38: 2240 | AA38: 46058 | AB38: 9865 | AC38: 2240 | AD38: 46080 | AE38: 7410 | AF38: 2240 | AG38: 46110 | AH38: 7410 | AI38: 2240 | AJ38: 46146 | AK38: SF | AL38: 2240 | AM38: 46181 | AN38: 470691 TC | AO38: fact ok
D39: =D15 -> GISSEL ADHARA LOPEZ CRUZ | E39: 2239 | F39: 45897 | G39: 178267 | H39: 2239 | I39: 45897 | J39: 8.5901783e+16 | K39: 2239 | L39: 45939 | M39: 91025 | N39: 2239 | O39: 45966 | P39: NU0544 | Q39: 2239 | R39: 45997 | S39: 8.5900646e+16 | T39: 2239 | U39: 46361 | V39: 70126 | W39: 2239 | X39: 45997 | Y39: 8.5900646e+16 | Z39: 2239 | AA39: 46086 | AB39: 8.5906145e+16 | AC39: 2239 | AD39: 46086 | AE39: 8.5906145e+16 | AF39: 2239 | AG39: 46141 | AH39: 23084311900 | AI39: 2239 | AJ39: 46156 | AK39: 414313466 | AL39: 2239 | AM39: 46183 | AN39: 14316166 | AO39: NO FACT
D40: =D16 -> MAXIMILIANO CISNEROS VILLEGAS | H40: 3071 | I40: 45904 | J40: 1129298 | K40: 3071 | L40: 45933 | M40: 6881210 | N40: 3071 | O40: 45991 | P40: 9170185 | Q40: 3071 | R40: 45991 | S40: 9170185 | T40: 3060 | U40: 46054 | V40: 5285350 | Z40: 3060 | AA40: 46054 | AB40: 5285350 | AC40: 3460 | AD40: 46112 | AE40: 8018260 | AF40: 3060 | AG40: 46112 | AH40: 8018260 | AI40: 3060 | AJ40: 46143 | AK40: 752181 | AL40: 3060 | AM40: 46174 | AN40: 9280885 | AO40: fact ok
B41: FACTURA | D41: =D17 -> ANGEL MATHIAS CARRASCO RAMIREZ | H41: 2239 | I41: 45903 | J41: 250903 | K41: 2239 | L41: 45932 | M41: 251001 | N41: 2239 | O41: 45966 | P41: 4525 | Q41: 2239 | R41: 45992 | S41: 251201 | T41: 2239 | U41: 46027 | V41: 6715 | W41: 2239 | X41: 45992 | Y41: 251201 | Z41: 2239 | AA41: 46054 | AB41: 322660 | AC41: 2239 | AD41: 46087 | AE41: 260306 | AF41: 2239 | AG41: 46119 | AH41: CTA6715 | AI41: 2239 | AJ41: 46148 | AK41: 128154 | AL41: 2239 | AM41: 46209 | AN41: 269430 | AO41: fact ok
D42: =D18 -> YESHUA FERNANDO VALENCIA OCAMPO | H42: 2686 | I42: 45905 | J42: 4548 | K42: 2686 | L42: 45933 | M42: 3935 | N42: 2686 | O42: 45966 | P42: 2911 | Q42: 2686 | R42: 45997 | S42: 7701 | T42: 2686 | U42: 46027 | V42: DEBIT | Z42: 2786 | AA42: 46058 | AB42: 9519 | AC42: 2786 | AD42: 46086 | AE42: 1169 | AF42: 2786 | AG42: 46117 | AH42: 1478 | AI42: 2786 | AJ42: 46146 | AK42: 285 (tarjeta) | AL42: 2786 | AM42: 05/060/2026 | AN42: 92896 TC | AO42: fact ok
D43: =D19 -> DANIELA MICHELLE ULIN GARCIA | H43: 3147 | I43: 46364 | J43: 8.5907216e+16 | K43: 3147 | L43: 45999 | M43: 8.5907216e+16 | N43: 2853 | O43: 45999 | P43: 8.5907216e+16 | Q43: 2853 | R43: 46093 | S43: 8.5903014e+16 | T43: 2853 | U43: 46093 | V43: 8.5903014e+16 | Z43: 2853 | AA43: 46190 | AB43: 330316861 | AC43: 2853 | AD43: 46190 | AE43: 330316861 | AF43: 2853 | AG43: 46198 | AH43: 760317665 | AI43: 2853 | AJ43: 46198 | AK43: 760317665 | AL43: 2853 | AM43: 46198 | AN43: 760317665 | AO43: fact ok
D44: =D20 -> VALENTINA GARCIA RUIZ | H44: 2687 | I44: 45905 | J44: SF | K44: 2687 | L44: 45935 | M44: SF TC | N44: 2687 | O44: 45966 | P44: 37240654 | Q44: 2687 | R44: 45993 | S44: 25782987 | T44: 2687 | U44: 46024 | V44: 36804787 | Z44: 2687 | AA44: 46058 | AB44: TRANSF | AC44: 2687 | AD44: 46083 | AE44: 3915390 | AF44: 2687 | AG44: 46108 | AH44: 88341480 | AI44: 2687 | AJ44: 46139 | AK44: 84625200 | AL44: 2687 | AM44: 46168 | AN44: 49090922 | AO44: fact ok
D45: =D21 -> BETZABE PEREZ REYES | H45: 2687 | I45: 45919 | J45: 9224609 | K45: 2687 | L45: 45951 | M45: 590065667 | N45: 2687 | O45: 45966 | P45: 4877003 | Q45: 2687 | R45: 46010 | S45: 78056577 | T45: 2687 | U45: 46023 | V45: 57896412 | Z45: 2687 | AA45: 46058 | AB45: 16066028 | AC45: 2687 | AD45: 46084 | AE45: 82784126 | AF45: 2687 | AG45: 46136 | AH45: 75067131 | AI45: 2687 | AJ45: 46146 | AK45: 751876 | AL45: 2687 | AM45: 46183 | AN45: 71456732 | AO45: fact ok
D46: =D22 -> GUILLERMO MIKAEL CHAVEZ | H46: 3347 | I46: 45916 | J46: SF | K46: 3347 | L46: 45936 | M46: SF | N46: 3347 | O46: 45967 | P46: 6353437 | Q46: 3347 | R46: 45998 | S46: 6353427 | T46: 3347 | U46: 46084 | V46: 54271 | Z46: 3347 | AA46: 46110 | AB46: 4930741 | AC46: 3347 | AD46: 46139 | AE46: 1468434 | AF46: 3347 | AG46: 46181 | AH46: 5863905 | AI46: 3347 | AJ46: 46181 | AK46: 1505897 | AL46: 3647 | AM46: 46191 | AN46: 4019405 | AO46: NOTA: PAGO RECARGOS DE ABRIL Y MAYO 18/06/2026 $800 F-4193773 | AT46: NO FACT
D47: =D23 -> ARANTXA ROSAS SANCHEZ | E47: 2687 | F47: 45900 | G47: SF | H47: 2239 | I47: 45905 | J47: 65843897 | K47: 2239 | L47: 45935 | M47: YTMBOK | N47: 2239 | O47: 45966 | P47: 974643 | Q47: 2239 | R47: 45995 | S47: VBWF3G | T47: 2239 | U47: 46058 | V47: TDC | Z47: 2239 | AA47: 46058 | AB47: TDC | AC47: 2639 | AD47: 46094 | AE47: 172267 | AF47: 2639 | AG47: 46129 | AH47: 573084 | AI47: 2239 | AJ47: 46160 | AK47: 10333 TC | AL47: 2239 | AM47: 46188 | AN47: 0349 TD | AO47: NO FACT
H48: 30880
H49: 38941

Sheet 6°P
F1: Centro de Investigación Educativa Colegio San Diego | S1: ACEPTADOS POR CORPORATIVO
F2: Punta el Campanario #183 Col. Bahia de San Martín CP 96536 | S2: PAGOS DE HIJOS DE MAESTROS
F3: PREESCOLAR 30PJN1037Z PRIMARIA 30PPR3773B SECUNDARIA 30PES0033G | S3: MES PAGADO
D4: FACTURA | F4: CICLO ESCOLAR 2024-2025 | S4: ALUMNO DADO DE BAJA
B7: N° | C7: MATRICULA | D7: NOMBRE DEL ALUMNO | E7: PROMOCION | F7: INSCRIPCION | G7: FOLIO | H7: FECHA | I7: MATERIAL | J7: FECHA | K7: FOLIO | L7: ARANCEL | M7: FECHA | N7: FOLIO | O7: LIBROS | P7: FECHA | Q7: FOLIO | R7: UNIFORMES | S7: FECHA | T7: FOLIO | U7: PLAN PAGO | V7: BECA | W7: COLEG | X7: TOTAL
A8: 921 125 9896 | C8: REINSCRIPCIÓN | D8: JOSÉ GABRIEL TRUJILLO RODRIGUEZ | E8: NOVIEMBRE-DICIEMBRE | F8: 1550 | G8: 2813595732 | H8: 45636 | I8: 2690 | J8: 45636 | K8: 2813785014 | L8: 2490 | M8: 45636 | N8: 2813719481 | O8: 5500 | P8: 45797 | Q8: 6736479464
A9: 921 202 4626 | C9: REINSCRIPCIÓN | D9: MEREDITH PAOLA LINARES LIMON | E9: ENERO-FEBRERO | F9: 1550 | G9: 8857374681 | H9: 45706 | I9: 2690 | J9: 45706 | K9: 8857374681 | L9: 2490 | M9: 45706 | N9: 8857374681 | O9: 5900 | P9: 45900 | Q9: 18378446 | U9: 10 MESES | V9: 0.25 | W9: 3838.8 | X9: 2879
A10: 921 154 4334 | C10: NUEVO INGRESO | D10: ERENDIRA DANAE SANTIAGO MARTINEZ | E10: ENERO-FEBRERO | F10: 1550 | G10: 41189 | H10: 45716 | I10: 2690 | J10: 45716 | K10: 41189 | L10: 2490 | M10: 45716 | N10: 41189 | O10: 5900
A11: 921 173 2609 | C11: NUEVO INGRESO | D11: LEOBARDO CASTELLANOS VARGAS | E11: ENERO-FEBRERO | F11: 1550 | G11: 30065 | H11: 45728 | I11: 2690 | J11: 45728 | K11: 30065 | L11: 2490 | M11: 45798 | N11: 23933 | O11: 5500 | P11: 45798 | Q11: 23933 | U11: 10 MESES | V11: 0.3 | X11: 2686
A12: 921 141 0280 | C12: NUEVO INGRESO | D12: IMELDA MARTINEZ RUIZ | E12: ENERO-FEBRERO | F12: 1550 | G12: 1640498907 | H12: 45738 | I12: 2690 | J12: 45876 | K12: 13530608 | L12: 2490 | M12: 45876 | N12: 13530608 | O12: 3000 | P12: 45890 | Q12: 8631720 | R12: 3085 | S12: 45897 | T12: 873225958
A13: 921 112 7464 | C13: REINSCRIPCIÓN | D13: VLADIMIR BAILON CANCINO | E13: MARZO-JUNIO | F13: 1860 | G13: 94628 | H13: 45839 | I13: 2690 | J13: 45871 | K13: 85902046484321400´ | L13: 2490 | M13: 45839 | N13: 94628 | O13: 5900 | P13: 45871 | Q13: 85902046484321400´
A14: 921 112 5176 | C14: SIMON BOLIVAR | D14: PEREZ CRUZ LIA KARIME | E14: MARZO-JUNIO | F14: GRATIS | G14: GRATIS | H14: 45868 | I14: 1883 | J14: 45882 | K14: 284554 | L14: 1743 | M14: 45882 | N14: 284554 | O14: 5900 | P14: 45868 | Q14: SF | R14: 3085 | S14: 45868 | T14: SF
A15: 921 250 6858 | C15: SIMON BOLIVAR | D15: CAMACHO ORDAZ JAZMIN | E15: MARZO-JUNIO | F15: GRATIS | G15: GRATIS | H15: 45868 | I15: 1883 | J15: 45960 | K15: 8.5904318e+16 | L15: 1743 | M15: 45960 | N15: 8.5904295e+16 | O15: 5900 | P15: 45868 | Q15: 6980526 | R15: 3085 | S15: 45889 | T15: 8.5903328e+16
A16: 921 113 6770 | C16: SIMON BOLIVAR | D16: CALEB SOTO ACOSTA | E16: MARZO-JUNIO | F16: GRATIS | G16: GRATIS | H16: 45868 | I16: 1883 | J16: 45957 | K16: sf | L16: 1743 | M16: 45957 | N16: sf | O16: 5900 | P16: 45868 | Q16: 10743 | U16: 10 MESES | V16: 0.25 | W16: 3199 | X16: 2879
A17: 921 240 2378 | B17: MAMÁ: DEINA GONZALEZ | C17: SIMON BOLIVAR | D17: NAOMI CARRILLO GONZALEZ | E17: MARZO-JUNIO | F17: GRATIS | G17: GRATIS | H17: 45874 | I17: 1883 | J17: 45880 | K17: 85906386994321600´ | L17: 1743 | M17: 45880 | N17: 85906386994321600´ | O17: 5900 | P17: 45874 | Q17: 8.5906387e+16 | R17: 2685 | S17: 45894 | T17: 250825 | U17: 10 MESES | V17: 0.25 | W17: 3199 | X17: 2879
A18: 921 267 4314 | B18: NUEVO INGRESO | D18: CARMEN GABRIELA DE LEÓN REYES | E18: MARZO-JUNIO | F18: 1860 | G18: 94957341 | H18: 45843 | I18: 2690 | J18: 45843 | K18: 94957341 | L18: 2490 | M18: 45843 | N18: 94957341 | O18: 5900 | P18: 45901 | Q18: SF | U18: 10 MESES
A19: 921 100 2754 | C19: REINSCRIPCIÓN | D19: ALEJANDRO DIAZ MORALES | E19: MARZO-JUNIO | F19: 1860 | G19: 990081 | H19: 45870 | L19: 2490 | M19: 46206 | N19: 252623 | O19: 5900 | P19: 45870 | Q19: 990081 | U19: 12 MESES | V19: 0.18 | W19: 3199 | X19: 2623
A20: 921 235 4100 | C20: REINSCRIPCIÓN | D20: DEREK URIEL MORALES DOMINGUEZ | E20: MARZO-JUNIO | O20: NO LLEVO | P20: NO LLEVO | Q20: NO LLEVO
A21: 921 112 9727 | C21: NUEVO INGRESO | D21: GAEL JUAREZ FUENTES | E21: MARZO-JUNIO | O21: 5900 | P21: 45901 | Q21: SF
C22: REINSCRIPCIÓN | D22: VALERIA MORENO GERMAN | E22: MARZO-JUNIO | F22: GRATIS | G22: GRATIS | H22: 45897 | I22: 1345 | J22: 45897 | K22: 791653333 | L22: 1245 | M22: 45897 | N22: 7787490 | O22: 5900 | P22: 45917 | Q22: 8.5901731e+16
C23: REINSCRIPCIÓN | D23: RODRIGO EMMANUEL SANCHEZ DOMINGUEZ | E23: MARZO-JUNIO | F23: GRATIS | G23: GRATIS | H23: 45897 | I23: 1345 | J23: 45960 | K23: 5789641231 | L23: 1245 | M23: 46262 | N23: 78986402 | O23: 5900 | P23: 45932 | Q23: ´000072 | U23: 10 MESES | V23: 0.18
A24: 921 257 2547 | C24: SIMON BOLIVAR | D24: JOSEPH DAVID CONTRERAS PALACIOS | E24: MARZO-JUNIO | F24: GRATIS | G24: GRATIS | H24: 45894 | I24: 1345 | J24: 45897 | K24: 56798416 | L24: 1245 | M24: 46262 | N24: 45213690 | O24: 5900 | P24: 46262 | Q24: 45213690 | U24: 12 MESES | V24: 0.3 | W24: 3199 | X24: 2239
A25: 921 136 7968 | B25: PAGA EL MARTES 26 AGOSTO | C25: REINSCRIPCIÓN | D25: IKER TRISTAN ROMERO AVILA | E25: MARZO-JUNIO | F25: GRATIS | G25: GRATIS | H25: 45895 | I25: 2690 | J25: 45904 | K25: 15075614 | L25: 1245 | M25: 45897 | N25: 36001691 | O25: 5900 | P25: 45902 | Q25: 57669743
A26: 921 128 9472 | C26: NUEVO INGRESO | D26: SOFIA BELEN PUCHETA RIVERA | E26: MARZO-JUNIO | F26: GRATIS | G26: GRATIS | H26: 45898 | I26: 1345 | J26: 45898 | K26: 2908250 | L26: 1245 | M26: 45898 | N26: 2908250 | O26: 5900 | P26: 45882 | Q26: SF
A27: 921 272 3613 | C27: REINSCRIPCIÓN | D27: DANIEL BURGOS MENA | E27: MARZO-JUNIO | F27: GRATIS | G27: GRATIS | H27: 45911
B36: COLEGIATURA
B37: N° | C37: MATRICULA | D37: NOMBRE DEL ALUMNO | E37: AGOSTO | H37: SEPTIEMBRE | K37: OCTUBRE | N37: NOVIEMBRE | Q37: DICIEMBRE | T37: ENERO | W37: JULIO | Z37: FEBRERO | AC37: MARZO | AF37: ABRIL | AI37: MAYO | AL37: JUNIO
E38: MONTO | F38: FECHA | G38: FOLIO | H38: MONTO | I38: FECHA | J38: FOLIO | K38: MONTO | L38: FECHA | M38: FOLIO | N38: MONTO | O38: FECHA | P38: FOLIO | Q38: MONTO | R38: FECHA | S38: FOLIO | T38: MONTO | U38: FECHA | V38: FOLIO | W38: MONTO | X38: FECHA | Y38: FOLIO | Z38: MONTO | AA38: FECHA | AB38: FOLIO | AC38: MONTO | AD38: FECHA | AE38: FOLIO | AF38: MONTO | AG38: FECHA | AH38: FOLIO | AI38: MONTO | AJ38: FECHA | AK38: FOLIO | AL38: MONTO | AM38: FECHA | AN38: FOLIO
C39: 1 | D39: =D8 -> JOSÉ GABRIEL TRUJILLO RODRIGUEZ | H39: 2686 | I39: 45782 | J39: 48922771 | K39: 2686 | L39: 45934 | M39: 62348679 | N39: 2686 | O39: 45964 | P39: 51492511 | Q39: 2686 | R39: 45992 | S39: 77361689 | T39: 2686 | U39: 45996 | V39: 89312066 | Z39: 2686 | AA39: 46058 | AB39: 71026784 | AC39: 2686 | AD39: 46086 | AE39: 8749621354 | AF39: 2686 | AG39: 46115 | AH39: 26344497 | AI39: 2686 | AJ39: 46147 | AK39: 992592 | AL39: 2686 | AM39: 06706/2026 | AN39: 46351542 | AO39: fact ok
D40: =D9 -> MEREDITH PAOLA LINARES LIMON | H40: 2879 | I40: 45901 | J40: 29230301 | K40: 2879 | L40: 45936 | M40: 43732221 | N40: 2879 | O40: 45966 | P40: 99207821 | Q40: 2879 | R40: 46011 | S40: 34343221 | T40: 2879 | U40: 46011 | V40: 34343221 | Z40: 2879 | AA40: 46059 | AB40: 72788769 | AC40: 2686 | AD40: 46081 | AE40: 604477219 | AF40: 2879 | AG40: 46116 | AH40: 79389321 | AI40: 2879 | AJ40: 46147 | AK40: 862889 | AL40: 2879 | AM40: 007/06/2026 | AN40: 62438605 | AO40: fact ok
D41: =D10 -> ERENDIRA DANAE SANTIAGO MARTINEZ | E41: 2239 | F41: 45873 | G41: 85903247514321600´ | H41: 2239 | I41: 45902 | J41: 544138 | K41: 2239 | L41: 45931 | M41: 685532 | N41: 2239 | O41: 45966 | P41: 8.5906568e+16 | Q41: 2239 | R41: 45996 | S41: 55664471 | T41: 2239 | U41: 46027 | V41: 8.5902471e+16 | W41: 2239 | X41: 45996 | Y41: 78954231 | Z41: 2239 | AA41: 46058 | AB41: 899065214537789 | AC41: 2239 | AD41: 46083 | AE41: 8.5902623e+16 | AF41: 2239 | AG41: 46118 | AH41: 8.5909749e+16 | AI41: 2239 | AJ41: 46146 | AK41: 994312642 | AL41: 2239 | AM41: 46175 | AN41: 315360 | AO41: fact ok
C42: 1 | D42: =D11 -> LEOBARDO CASTELLANOS VARGAS | H42: 2686 | I42: 45903 | J42: 892757 | K42: 2686 | L42: 45933 | M42: 787757 | N42: 2686 | O42: 45966 | P42: 680625 | Q42: 2686 | R42: 45996 | S42: PAGOTARJETASF | T42: 2686 | U42: 46027 | V42: PAGOTARJETASF | Z42: 2686 | AA42: 46057 | AB42: 829169 | AC42: 2686 | AD42: 46085 | AE42: 58791234 | AF42: 2686 | AG42: 46116 | AH42: 54896123 | AI42: 2686 | AJ42: 46140 | AK42: 427092 | AL42: 2686 | AM42: 46174 | AN42: 82731 TD | AO42: fact ok
D43: =D12 -> IMELDA MARTINEZ RUIZ | H43: 2559 | I43: 45905 | J43: 82108640 | K43: 2559 | L43: 45934 | M43: 96712653 | N43: 2559 | O43: 45965 | P43: 96712653 | Q43: 2559 | R43: 45996 | S43: 99865316 | T43: 2559 | U43: 46027 | V43: 455043358 | W43: 2559 | X43: 45996 | Y43: 99865316 | Z43: 2559 | AA43: 46058 | AB43: 47747945 | AC43: 2559 | AD43: 46085 | AE43: 23642518 | AF43: 3000 | AG43: 46140 | AH43: 78559352 | AI43: 2559 | AJ43: 46147 | AK43: 99921932 | AL43: 2559 | AM43: 46178 | AN43: 68211423 | AO43: VERIF RFC FACT
C44: 1 | D44: =D13 -> VLADIMIR BAILON CANCINO | H44: 2686 | I44: 45904 | J44: 8.5901205e+16 | K44: 2688 | L44: 45932 | M44: 8.5901581e+16 | N44: 2688 | O44: 45966 | P44: 8.5902199e+16 | Q44: 2680 | R44: 45996 | S44: 8.5902073e+16 | T44: 2680 | U44: 46027 | V44: 8.5902471e+16 | Z44: 2680 | AA44: 46058 | AB44: 54775623 | AC44: 2680 | AD44: 46087 | AE44: 54786923 | AF44: 2790 | AG44: 46118 | AH44: 8.590759e+16 | AI44: 2780 | AJ44: 46134 | AK44: 614311262 | AL44: 2780 | AM44: 02706/2026 | AN44: 944315363 | AO44: fact ok
D45: =D14 -> PEREZ CRUZ LIA KARIME | H45: 2879 | I45: 45897 | J45: 85902496594324000´ | K45: 2879 | L45: 45912 | M45: 8.5901578e+16 | N45: 2879 | O45: 45912 | P45: 8.5901578e+16 | Q45: 2879 | R45: 45912 | S45: 8.5901578e+16 | T45: 2879 | U45: 45912 | V45: 8.5901578e+16 | Z45: 2879 | AA45: 45912 | AB45: 8.5901578e+16 | AC45: 2879 | AD45: 45912 | AE45: 8.5901578e+16 | AF45: 2879 | AG45: 45912 | AH45: 8.5901578e+16 | AI45: 2879 | AJ45: 45912 | AK45: 8.5901578e+16 | AL45: 2879 | AM45: 46139 | AN45: 83240950 | AO45: fact ok
D46: =D15 -> CAMACHO ORDAZ JAZMIN | H46: 2879 | I46: 45905 | J46: 8.5906832e+16 | K46: 2879 | L46: 45931 | M46: 785010 | N46: 2879 | O46: 45991 | P46: 8.5904348e+16 | Q46: 2879 | R46: 45993 | S46: 483296 | T46: 2879 | U46: 46358 | V46: 8.5904672e+16 | Z46: 2879 | AA46: 46058 | AB46: 5489712153 | AC46: 2879 | AD46: 46086 | AE46: 78964512 | AF46: 2879 | AG46: 46116 | AH46: 8.5906142e+16 | AI46: 2879 | AJ46: 46145 | AK46: 764312365 | AL46: 2879 | AM46: 02706/2026 | AN46: 315366 | AO46: fact ok
C47: 1 | D47: =D16 -> CALEB SOTO ACOSTA | H47: 2879 | I47: 45904 | J47: 80401852 | K47: 2879 | L47: 45932 | M47: 41227896 | N47: 2879 | O47: 45966 | P47: 54512067 | Q47: 2879 | R47: 45996 | S47: 2947134 | T47: 2879 | U47: 46027 | V47: 29150743 | Z47: 2879 | AA47: 46057 | AB47: 122274 | AC47: 2879 | AD47: 46085 | AE47: 89756412 | AF47: 2879 | AG47: 46085 | AH47: 15489763 | AI47: 2879 | AJ47: 46147 | AK47: 236935 | AL47: 2879 | AM47: 05/0672026 | AN47: 402442 TC | AO47: fact ok
A48: 10 | D48: =D17 -> NAOMI CARRILLO GONZALEZ | H48: 2879 | I48: 45813 | J48: 761042 | K48: 2879 | L48: 45932 | M48: 8.5900178e+17 | N48: 2879 | O48: 45966 | P48: 8.5905398e+16 | Q48: 2879 | R48: 45993 | S48: 8.5904038e+16 | T48: 2879 | U48: 46037 | V48: 8.5901979e+16 | Z48: 2879 | AA48: 46057 | AB48: TRANF | AC48: 2879 | AD48: 46085 | AE48: TRANSF | AF48: 2879 | AG48: 46113 | AH48: 8.5905206e+16 | AI48: 2879 | AJ48: 46146 | AK48: 384312469 | AL48: 2879 | AM48: 46179 | AN48: 434315661 | AO48: fact ok
D49: =D18 -> CARMEN GABRIELA DE LEÓN REYES | H49: 3147 | I49: 45905 | J49: 78022057 | K49: 3147 | L49: 45932 | M49: 39650453 | N49: 3145 | O49: 45965 | P49: 79228037 | Q49: 3145 | R49: 46001 | S49: 59825862 | T49: 3145 | U49: 46029 | V49: 48346976 | Z49: 3145 | AA49: 46061 | AB49: 68510723 | AC49: 3145 | AD49: 46084 | AE49: 12463978 | AF49: 3145 | AG49: 46112 | AH49: 5736890 | AI49: 3145 | AJ49: 46142 | AK49: 83325607 | AL49: 3145 | AM49: 46174 | AN49: 96702243 | AO49: NF
C50: 1 | D50: =D19 -> ALEJANDRO DIAZ MORALES | H50: 2623 | I50: 45904 | J50: 141196 | K50: 2623 | L50: 45934 | M50: 725261 | N50: 3145 | O50: 45966 | P50: SF | Q50: 3145 | R50: 45995 | S50: 743304 | T50: 3145 | U50: 46026 | V50: 840025 | W50: 3145 | X50: 46026 | Y50: 840025 | Z50: 2623 | AA50: 46059 | AB50: 58796421 | AC50: 2623 | AD50: 46086 | AE50: 21563470 | AF50: 3023 | AG50: 46142 | AH50: 019874 (DEP EFEC) | AI50: 3023 | AJ50: 46163 | AK50: 189807 D EFE | AL50: 2623 | AM50: 28/0572023 | AN50: 260441 D EFE | AO50: NF
C51: 1 | D51: =D20 -> DEREK URIEL MORALES DOMINGUEZ | E51: 1750 | F51: 45877 | G51: 5612886 | H51: 1750 | I51: 45909 | J51: 4074700 | K51: 1750 | L51: 45935 | M51: 2804221 | N51: 1750 | O51: 45970 | P51: 7955124 | Q51: 1750 | R51: 45996 | S51: 3480261 | T51: 1750 | U51: 46027 | V51: 7745561 | Z51: 1750 | AA51: 46058 | AB51: 8103176 | AC51: 1750 | AD51: 46085 | AE51: 87964512 | AF51: 1750 | AG51: 46124 | AH51: 4802721 | AI51: 1750 | AJ51: 08705/2026 | AK51: 2520305 | AL51: 1750 | AM51: 46182 | AN51: 215590 | AO51: fact ok
C52: 1 | D52: =D21 -> GAEL JUAREZ FUENTES | H52: 2399.25 | I52: 45897 | J52: 280825 | K52: 2399 | L52: 45930 | M52: 8.5904538e+16 | N52: 2399 | O52: 45930 | P52: 8.5904538e+16 | Q52: 2399 | R52: 45930 | S52: 8.5904538e+16 | T52: 2399 | U52: 46027 | V52: 8.5908669e+16 | W52: 2399.25 | X52: 46176 | Y52: 315461 | Z52: 2399.25 | AA52: 46027 | AB52: 8.5908669e+16 | AC52: 2399.25 | AD52: 46027 | AE52: 8.5908669e+16 | AF52: 2399.25 | AG52: 46113 | AH52: 8.5907003e+16 | AI52: 2399.25 | AJ52: 46113 | AK52: 8.5907003e+16 | AL52: 4798.5 | AM52: 46176 | AN52: 315461 | AO52: fact ok
D53: =D22 -> VALERIA MORENO GERMAN | H53: 2200 | I53: 45922 | J53: 190925 | K53: 2200 | L53: 45935 | M53: 8.5908254e+16 | N53: 2200 | O53: 45964 | P53: 879562144367 | Q53: 2200 | R53: 45997 | S53: 8795486321 | T53: 2200 | U53: 46084 | V53: 2774102 | Z53: 2200 | AA53: 46084 | AB53: 2774102 | AC53: 2200 | AD53: 46174 | AE53: 7039631 | AN53: CONVENIO | AO53: PEND DE AVISAR
C54: 1 | D54: =D23 -> RODRIGO EMMANUEL SANCHEZ DOMINGUEZ | H54: 2395 | I54: 45910 | J54: nomban3194 | K54: 2395 | L54: 45935 | M54: nomban3194 | N54: 2795 | O54: 46056 | P54: 260204 | Q54: 2795 | R54: 46056 | S54: 260204 | Z54: 2795 | AA54: 46138 | AB54: 260426 | AC54: 2795 | AD54: 46138 | AE54: 260426 | AF54: 2795 | AG54: 46183 | AH54: 405326422 | AI54: 2795 | AJ54: 46183 | AK54: 405326422 | AO54: QUEDO DE PASAR A FIN DE MES
B55: 1 | C55: ANUAL ??? | D55: =D24 -> JOSEPH DAVID CONTRERAS PALACIOS | H55: 2230 | I55: 45914 | J55: 495753 | K55: 2230 | L55: 45944 | M55: 495753 | N55: 2230 | O55: 45944 | P55: 495753 | Q55: 2230 | R55: 45944 | S55: 495753 | T55: 2230 | U55: 45944 | V55: 495753 | W55: 2230 | X55: 45944 | Y55: 495753 | Z55: 2230 | AA55: 45944 | AB55: 495753 | AC55: 2230 | AD55: 45944 | AE55: 495753 | AF55: 2230 | AG55: 45944 | AH55: 495753
C56: 1 | D56: =D25 -> IKER TRISTAN ROMERO AVILA | H56: 2690 | I56: 45904 | J56: 15075614 | K56: 3147 | L56: 45939 | M56: 34550253 | N56: 3147 | O56: 45964 | P56: 73745420 | Q56: 3147 | R56: 45994 | S56: 23416460 | T56: 3147 | U56: 46038 | V56: 80265428 | Z56: 3147 | AA56: 46072 | AB56: 52237867 | AC56: 3147 | AD56: 46099 | AE56: 54897632 | AF56: 3147 | AG56: 46099 | AH56: 54897632 | AI56: 3147 | AJ56: 46135 | AK56: 64109215 | AL56: 3147 | AM56: 46169 | AN56: 67746777 | AO56: NO FACT
H57: 39370
H58: 47428
H61: 2686

Sheet 1°S
F1: Centro de Investigación Educativa Colegio San Diego | S1: ACEPTADOS POR CORPORATIVO
F2: Punta el Campanario #183 Col. Bahia de San Martín CP 96536 | S2: PAGOS DE HIJOS DE MAESTROS
F3: PREESCOLAR 30PJN1037Z PRIMARIA 30PPR3773B SECUNDARIA 30PES0033G | S3: MES PAGADO
D4: FACTURA | F4: CICLO ESCOLAR 2024-2025 | S4: ALUMNO DADO DE BAJA
J5: krakens academy
B7: N° | C7: MATRICULA | D7: NOMBRE DEL ALUMNO | E7: PROMOCION | F7: INSCRIPCION | G7: FOLIO | H7: FECHA | I7: MATERIAL | J7: FECHA | K7: FOLIO | L7: ARANCEL | M7: FECHA | N7: FOLIO | O7: LIBROS | P7: FECHA | Q7: FOLIO | R7: UNIFORMES | S7: FECHA | T7: FOLIO | U7: PLAN PAGO | V7: BECA | W7: COLEG | X7: TOTAL
A8: 938 113 8982 | C8: NUEVO INGRESO | D8: JOEL BARZILAI JIMENEZ AGUIRRE | E8: NOVIEMBRE-DICIEMBRE | F8: GRATIS | G8: GRATIS | H8: 45677 | I8: 909 | J8: 45677 | K8: 106672 | L8: 909 | M8: 45677 | N8: 106672 | U8: 12 meses | V8: 0.25 | W8: 3299 | X8: 2474
A9: 921 304 4382 | C9: NUEVO INGRESO | D9: BRYAN YAEL RODRÍGUEZ LOPEZ | E9: NOVIEMBRE-DICIEMBRE | F9: GRATIS | G9: GRATIS | H9: 45679 | I9: 751 | J9: 45679 | K9: 2201250 | L9: 1749 | M9: 45679 | N9: 2201250 | O9: 6700 | P9: 45799 | Q9: 1106250 | U9: 12 meses | V9: 0.25 | W9: 3299 | X9: 2474
A10: 921 274 7022 | C10: NUEVO INGRESO | D10: ZION USCANCA VAZQUEZ | E10: NOVIEMBRE-DICIEMBRE | F10: GRATIS | G10: GRATIS | H10: 45696 | I10: 2499 | J10: 45710 | K10: 9242017647 | L10: 2890 | M10: 45710 | N10: 9242017647 | O10: 6700 | P10: 45799 | Q10: 6930345587 | R10: 3835 | S10: 45833 | T10: 2064049 | U10: 10 MESES | V10: 0.2 | W10: 3958 | X10: 3167
A11: 921 125 9896 | B11: 20% DESCTO EN ARANCEL | C11: NUEVO INGRESO | D11: JORGE GABRIEL SALVADOR MARTINEZ | E11: ENERO-FEBRERO | F11: GRATIS | G11: GRATIS | H11: 45712 | I11: 1999 | J11: 45712 | K11: 9395510221 | O11: 7200 | P11: 45884 | Q11: 68015212 | R11: 3085 | S11: 45895 | T11: 24761921
A12: 921 154 4334 | C12: NUEVO INGRESO | D12: HECTOR MANUEL PONCE SANTIAGO | E12: ENERO-FEBRERO | F12: GRATIS | G12: GRATIS | H12: 45716 | I12: 2499 | J12: 45716 | K12: 41189 | L12: 2890 | M12: 45716 | N12: 41189
A13: 921 345 7203 | C13: NUEVO INGRESO | D13: EMILIANO PEREZ VELAZQUEZ | E13: ENERO-FEBRERO | F13: GRATIS | G13: GRATIS | H13: 45716 | I13: 2499 | J13: 45716 | K13: 2802257 | L13: 2890 | M13: 45716 | N13: 2802257 | O13: 7200 | P13: 45908 | Q13: 113 | R13: 3085 | S13: 45897 | T13: 2808250 | U13: 10 MESES | V13: 0.3 | W13: 3958 | X13: 2770
A14: 921 298 0490 | C14: NUEVO INGRESO | D14: ETHAN RAMIREZ ALOR | E14: ENERO-FEBRERO | F14: GRATIS | G14: GRATIS | H14: 45721 | I14: 2499 | J14: 45721 | K14: 7870915 | L14: 2890 | M14: 45721 | N14: 7870915 | O14: 7200 | P14: 45905 | Q14: 25432322 | R14: 1965 | S14: 45894 | T14: 43703096 | U14: 12 meses | V14: 0.25 | W14: 3299 | X14: 2640
A15: 921 306 9709 | C15: NUEVO INGRESO | D15: ASHLEY ALEXA TOTO MARTINEZ | E15: ENERO-FEBRERO | F15: GRATIS | G15: GRATIS | H15: 45706 | I15: 2890 | J15: 45706 | K15: 8881301154 | L15: 2890 | M15: 45706 | N15: 8881123541 | O15: 7200 | P15: 45888 | Q15: 73106416 | R15: 3085 | S15: 45866 | T15: 311400064 | U15: 10 MESES | V15: 0.25 | W15: 3958 | X15: 3167
A16: 921 184 3826 | C16: NUEVO INGRESO | D16: DAMIAN HERNANDEZ FLORES | E16: MARZO-JUNIO | F16: GRATIS | G16: GRATIS | H16: 45861 | I16: 2890 | J16: 45861 | K16: 230725 | L16: 2499 | M16: 45861 | N16: 230725 | O16: 7200 | P16: 45861 | Q16: 230725 | R16: 3335 | S16: 45861 | T16: 230725
A17: 229 465 3459 | C17: NUEVO INGRESO | D17: KENDRA ALEXANDRA PEREZ CRUZ | E17: MARZO-JUNIO | F17: GRATIS | G17: GRATIS | H17: 45894 | I17: 1445 | J17: 45895 | K17: 2508250 | L17: 1249.5 | M17: 45895 | N17: 2508250 | O17: 5200 | P17: 45917 | R17: 3085 | S17: 45895 | T17: 2508250 | U17: 10 MESES | V17: 0.3 | W17: 3958 | X17: 2309
A18: 921 311 4044 | C18: NUEVO INGRESO | D18: DARVIN GONZALEZ GOMEZ | E18: MARZO-JUNIO | F18: GRATIS | G18: GRATIS | H18: 45897 | I18: 2490 | J18: 45897 | K18: 184229 | L18: 2890 | M18: 45897 | N18: 184229 | O18: 7200 | P18: 45897 | Q18: 184229 | U18: 12 meses | V18: 0.18 | W18: 3299 | X18: 2705
B36: COLEGIATURA
B37: N° | C37: MATRICULA | D37: NOMBRE DEL ALUMNO | E37: AGOSTO | H37: SEPTIEMBRE | K37: OCTUBRE | N37: NOVIEMBRE | Q37: DICIEMBRE | T37: ENERO | W37: JULIO | Z37: FEBRERO | AC37: MARZO | AF37: ABRIL | AI37: MAYO | AL37: JUNIO
E38: MONTO | F38: FECHA | G38: FOLIO | H38: MONTO | I38: FECHA | J38: FOLIO | K38: MONTO | L38: FECHA | M38: FOLIO | N38: MONTO | O38: FECHA | P38: FOLIO | Q38: MONTO | R38: FECHA | S38: FOLIO | T38: MONTO | U38: FECHA | V38: FOLIO | W38: MONTO | X38: FECHA | Y38: FOLIO | Z38: MONTO | AA38: FECHA | AB38: FOLIO | AC38: MONTO | AD38: FECHA | AE38: FOLIO | AF38: MONTO | AG38: FECHA | AH38: FOLIO | AI38: MONTO | AJ38: FECHA | AK38: FOLIO | AL38: MONTO | AM38: FECHA | AN38: FOLIO
D39: =D8 -> JOEL BARZILAI JIMENEZ AGUIRRE | H39: 2874 | I39: 45924 | J39: SF | K39: 2874 | L39: 45936 | M39: 35874695 | N39: 2874 | O39: 45967 | P39: 7895461237 | Q39: 2874 | R39: 46065 | S39: 57813739 | T39: 2874 | U39: 46065 | V39: 57813739 | Z39: 2874 | AA39: 46065 | AB39: 57813739 | AC39: 2874 | AD39: 46189 | AE39: 98210394 | AF39: 2874 | AG39: 17/0672026 | AH39: 98210394 | AK39: CONVENIO | AN39: CONVENIO
A40: FALTA ENVIAR CSF | B40: FACTURA | D40: =D9 -> BRYAN YAEL RODRÍGUEZ LOPEZ | E40: 2470 | F40: 45897 | G40: 2808250 | H40: 2470 | I40: 45901 | J40: 109250 | K40: 2470 | L40: 45936 | M40: 50116952 | N40: 2475 | O40: 45961 | P40: 59792500 | Q40: 2475 | R40: 46001 | S40: 50116952 | T40: 2475 | U40: 46001 | V40: 50116952 | Z40: 2474 | AA40: 46057 | AB40: 402260 | AC40: 3000 | AD40: 46106 | AE40: 2503262 | AF40: 2475 | AG40: 46114 | AH40: 7882400 | AI40: 2500 | AJ40: 46146 | AK40: 594694 | AL40: 2475 | AM40: 46174 | AN40: 88650517 | AO40: FACT OK
D41: =D10 -> ZION USCANCA VAZQUEZ | H41: 3167 | I41: 45902 | J41: 7772180 | K41: 3167 | L41: 45933 | M41: 45241865 | N41: 3167 | O41: 45964 | P41: 65276465 | Q41: 3167 | R41: 45993 | S41: 23989659 | T41: 3167 | U41: 46358 | V41: 85763352 | Z41: 3167 | AA41: 46055 | AB41: 85234424 | AC41: 3167 | AD41: 46083 | AE41: 85234424 | AF41: 3167 | AG41: 46115 | AH41: 83709025 | AI41: 3167 | AJ41: 46146 | AK41: 25417070 | AL41: 3167 | AM41: 46175 | AN41: 66053735 | AO41: FACT OK
D42: =D11 -> JORGE GABRIEL SALVADOR MARTINEZ | H42: 2771 | I42: 45918 | J42: 9331418 | K42: 2771 | L42: 45936 | M42: 87895715 | N42: 2771 | O42: 45936 | P42: 87895715 | Q42: 2771 | R42: 45994 | S42: 51489777 | T42: 2771 | U42: 46037 | V42: 20820949 | Z42: 2771 | AA42: 46056 | AB42: 125169 | AC42: 2771 | AD42: 46056 | AE42: 125169 | AF42: 2771 | AG42: 46110 | AH42: 465671 | AI42: 2771 | AJ42: 46110 | AK42: 465671 | AL42: 2771 | AM42: 46163 | AN42: 767653 TC | AO42: FACT OK
D43: =D12 -> HECTOR MANUEL PONCE SANTIAGO | E43: 2309 | F43: 45873 | G43: 3130298 | H43: 2309 | I43: 45901 | J43: 258526 | K43: 2309 | L43: 45933 | M43: 389024 | N43: 2309 | O43: 45966 | P43: 4492035
D44: =D13 -> EMILIANO PEREZ VELAZQUEZ | H44: 2770 | I44: 45906 | J44: 17462271 | K44: 2770 | L44: 45936 | M44: 910250 | T44: 2770 | U44: 46027 | V44: 50117946 | Z44: 2770 | AA44: 46082 | AB44: 73962594 | AC44: 2770 | AD44: 46124 | AE44: 90570999 | AF44: 2770 | AG44: 46133 | AH44: 52112992 | AI44: 2770 | AJ44: 46148 | AK44: 11610122 | AL44: 2770 | AM44: 46177 | AN44: 45676335 | AO44: FACT OK
D45: =D14 -> ETHAN RAMIREZ ALOR | H45: 2640 | I45: 45906 | J45: SF | K45: 2640 | L45: 45935 | M45: SF | N45: 2640 | O45: 45966 | P45: 519307 | Q45: 2640 | R45: 46002 | S45: 4548491 | T45: 3000 | U45: 46023 | V45: 54789621 | Z45: 3000 | AA45: 46058 | AB45: 5316966 | AC45: 3000 | AD45: 46084 | AE45: 642776 | AF45: 3000 | AG45: 46127 | AH45: 2389663 | AI45: 3000 | AJ45: 46190 | AK45: 2357361 | AL45: 3000 | AM45: 46190 | AN45: 2357361 | AO45: no fact
C46: PAGO ANUAL | D46: =D15 -> ASHLEY ALEXA TOTO MARTINEZ | H46: 3299 | I46: 45877 | J46: DEP BANCO | K46: 3299 | L46: 45877 | M46: DEP BANCO | N46: 3299 | O46: 45877 | P46: DEP BANCO | Q46: 3299 | R46: 45877 | S46: DEP BANCO | T46: 3299 | U46: 45877 | V46: DEP BANCO | Z46: 3299 | AA46: 45877 | AB46: DEP BANCO | AC46: 3299 | AD46: 45877 | AE46: DEP BANCO | AF46: 3299 | AG46: 45877 | AH46: DEP BANCO
D47: =D16 -> DAMIAN HERNANDEZ FLORES | E47: 2705 | F47: 45932 | G47: 21025 | H47: 2705 | I47: 45932 | J47: 21025 | K47: 2705 | L47: 45932 | M47: 21025 | N47: 2705 | O47: 45964 | P47: NU 5527 | Q47: 2705 | R47: 45995 | S47: 41225 | T47: 2705 | U47: 46023 | V47: 50126 | W47: 2705 | X47: 46023 | Y47: 50126 | Z47: 2705 | AA47: 46055 | AB47: 48799 | AC47: 2705 | AD47: 46086 | AE47: 4102 | AF47: 2705 | AG47: 46118 | AH47: 60426 | AI47: 2705 | AJ47: 46300 | AK47: 50526 | AL47: 2705 | AM47: 46177 | AN47: 8200533 | AO47: no fact
D48: =D17 -> KENDRA ALEXANDRA PEREZ CRUZ | H48: 2309 | I48: 45905 | J48: 1375789930 | K48: 2309 | L48: 45935 | M48: 1487279540 | N48: 2309 | O48: 45965 | P48: 1598121268 | Q48: 2309 | R48: 45995 | S48: 61225 | T48: 2309 | U48: 46023 | V48: 1401260 | Z48: 2309 | AA48: 46085 | AB48: 2403260 | AC48: 2309 | AD48: 46085 | AE48: 2403261 | AF48: 2309 | AG48: 46124 | AH48: 55325755 | AI48: 2309 | AJ48: 46174 | AK48: 253218740
D49: =D18 -> DARVIN GONZALEZ GOMEZ | H49: 2705 | I49: 45905 | J49: 110258 | K49: 2705 | L49: 45933 | M49: 820864 | N49: 2705 | O49: 45966 | P49: 90319986 | Q49: 2705 | R49: 45996 | S49: APROB8971 | T49: 2705 | U49: 46027 | V49: 61259637 | Z49: 2705 | AA49: 46058 | AB49: 769588 | AC49: 2705 | AD49: 46084 | AE49: 68967456 | AF49: 2705 | AG49: 46117 | AH49: 13548219 | AI49: 2705 | AJ49: 46146 | AK49: 287 (tarjeta) | AL49: =2075+630 -> 2705 | AM49: 46178 | AN49: 542095 | AO49: no fact

Sheet 2°S
F1: Centro de Investigación Educativa Colegio San Diego | S1: ACEPTADOS POR CORPORATIVO
F2: Punta el Campanario #183 Col. Bahia de San Martín CP 96536 | S2: PAGOS DE HIJOS DE MAESTROS
F3: PREESCOLAR 30PJN1037Z PRIMARIA 30PPR3773B SECUNDARIA 30PES0033G | S3: MES PAGADO
D4: FACTURA | F4: CICLO ESCOLAR 2024-2025 | S4: ALUMNO DADO DE BAJA
B7: N° | C7: MATRICULA | D7: NOMBRE DEL ALUMNO | E7: PROMOCION | F7: INSCRIPCION | G7: FOLIO | H7: FECHA | I7: MATERIAL | J7: FECHA | K7: FOLIO | L7: ARANCEL | M7: FECHA | N7: FOLIO | O7: LIBROS | P7: FECHA | Q7: FOLIO | R7: UNIFORMES | S7: FECHA | T7: FOLIO | U7: PLAN PAGO | V7: BECA | W7: COLEG | X7: TOTAL
A8: 921 172 7241 | C8: REINSCRIPCIÓN | D8: ARIADNA SORIANO LAVIN | E8: NOVIEMBRE-DICIEMBRE | F8: 1700 | G8: 5464753 | H8: 45638 | O8: 1000 | P8: 45871 | Q8: 20825 | U8: 10 meses | V8: 0.3 | W8: 3958 | X8: 2770
A9: 921 137 3818 | C9: REINSCRIPCIÓN | D9: JATZIRI KRISTEL ZURIANO FELIX | E9: NOVIEMBRE-DICIEMBRE | F9: 1700 | G9: 774102 | H9: 45642 | I9: 2890 | J9: 45882 | K9: HSBC275999 | L9: 2490 | M9: 45882 | N9: HSBC272372 | U9: 10 meses | V9: 0.23 | W9: 3958 | X9: 3048
A10: 921 249 6568 | C10: REINSCRIPCIÓN | D10: EVAN MATIAS ZARAGOZA MATINEZ | E10: NOVIEMBRE-DICIEMBRE | F10: 1700 | G10: 8.5901056e+16 | H10: 45657 | I10: 2890 | J10: 45781 | K10: 8.5907362e+16 | L10: 2490 | M10: 45895 | N10: 192259 | O10: 7200 | P10: 45901 | Q10: 8.5901285e+16 | U10: 12 MESES | V10: 0.25 | W10: 3299 | X10: 2540
A11: 921 250 0484 | C11: REINSCRIPCIÓN | D11: HANNA NICOLE SALOME GOMEZ | E11: NOVIEMBRE-DICIEMBRE | F11: 1700 | G11: 6370346750 | H11: 45677 | I11: 1749.5 | J11: 45649 | K11: SF | L11: 1813 | M11: 45649 | N11: SF | O11: 7200 | P11: 45874 | Q11: 126789 | U11: 10 meses | V11: 0.23 | W11: 3958 | X11: 3048
A12: 921 280 9032 | C12: NUEVO INGRESO | D12: JIMENNA SOFIA OCHA | E12: ENERO-FEBRERO | F12: 1700 | G12: 267710 | H12: 45714 | I12: 2499 | J12: 45714 | K12: 267710 | L12: 2890 | M12: 45714 | N12: 267710 | O12: 6700 | P12: 45714 | Q12: 476381 | U12: 10 meses | V12: 0.23 | W12: 3958 | X12: 3048
A13: 921 127 8732 | C13: REINSCRIPCIÓN | D13: RENATA VALENTINA LOPEZ CRUZ | E13: ENERO-FEBRERO | F13: 1700 | G13: 8.5904474e+16 | H13: 45715 | I13: 1999.2 | J13: 45715 | K13: 8.5904517e+16 | L13: 2890 | M13: 45715 | N13: 8.5904558e+16 | O13: 6700 | P13: 45803 | Q13: HSB5306900 | U13: 12 MESES | V13: 0.3 | W13: 3299 | X13: 2309
A14: 962 214 0049 | C14: REINSCRIPCIÓN | D14: LUISA PAULETTE SANCHEZ SANTOS | E14: ENERO-FEBRERO | F14: 1700 | G14: SF | H14: 45741 | I14: 2499 | J14: REVISAR | K14: REVISAR | U14: 12 MESES | V14: 0.25 | W14: 3299 | X14: 2540
A15: 921 273 5501 | C15: REINSCRIPCIÓN | D15: VANIA ZOE FARIAS BAHENA | E15: MARZO-JUNIO | F15: 2040 | G15: 8650950 | H15: 45808 | I15: 1345 | J15: 45897 | K15: 8650950 | L15: 1245 | M15: 45897 | N15: 8650950 | O15: 5240 | P15: 45931 | Q15: 1801410
A16: 921 123 1669 | C16: REINSCRIPCIÓN | D16: LEYLA CRUZ ARIZPE | E16: MARZO-JUNIO | F16: 2040 | G16: 250623 | H16: 45831 | I16: 2499 | J16: 45831 | K16: 250623 | L16: 2890 | M16: 45831 | N16: 250623 | O16: 6700 | P16: 45831 | Q16: 250623
A17: 921 228 5003 | C17: NUEVO INGRESO | D17: ANGEL DE JESUS RABANALES ALEGRIA | E17: MARZO-JUNIO | F17: 1700 | G17: 13498576 | H17: 45838 | I17: 2499 | J17: 45838 | K17: 13498576 | L17: 2890 | M17: 45838 | N17: 13498576 | O17: 7200 | P17: 45874 | Q17: 46675885 | U17: 12 MESES | V17: 0.18 | W17: 3299 | X17: 2705
A18: 921 123 6086 | C18: REINSCRIPCIÓN | D18: KARLA DANIELA LUIS CARRERA | E18: MARZO-JUNIO | F18: 1700 | G18: 40314 | H18: 45841 | I18: 2499 | J18: 45841 | K18: 12 | L18: 2890 | M18: 45841 | N18: 40314 | O18: 7200 | P18: 45841 | Q18: 40314 | U18: 10 meses | V18: 0.18 | W18: 3958 | X18: 3246
A19: 921 305 1833 | C19: REINSCRIPCIÓN | D19: NAIM JIMENEZ DOMINGUEZ | E19: MARZO-JUNIO | F19: 2040 | G19: 277410 | H19: 45845 | I19: 2890 | J19: 45866 | K19: 2.2620258e+16 | L19: 1000 | M19: 45899 | N19: 277410 | O19: 7200 | P19: 45913 | Q19: 277410 | R19: 780 | S19: 45899 | T19: 277410 | U19: 10 meses
A20: 921 311 7475 | C20: REINSCRIPCIÓN | D20: LIAM EZEQUIEL OVILLA ESPINOZA | E20: MARZO-JUNIO | F20: 2040 | G20: 7953761387 | H20: 45817 | I20: 2890 | J20: 45817 | K20: 7953761387 | L20: 2499 | M20: 45817 | N20: 7953761387 | O20: 7200 | P20: 45817 | Q20: 7953761387 | U20: 10 MESES | V20: 0.18 | W20: 3958 | X20: 3246
A21: 921 133 6418 | C21: REINSCRIPCIÓN | D21: ELIAS EDUARDO SANCHEZ DIAZ | E21: MARZO-JUNIO | F21: GRATIS | G21: GRATIS | H21: 45866 | I21: 2890 | J21: 45866 | K21: 5375 | L21: 2490 | M21: 45866 | N21: 5375 | O21: 2000 | P21: 45866 | Q21: 5375 | U21: 10 meses | V21: 0.18 | W21: 3958 | X21: 3246
A22: 921 200 9902 | C22: REINSCRIPCIÓN | D22: NOE DAVID GARCIA NELSON | E22: MARZO-JUNIO | F22: GRATIS | G22: GRATIS | H22: 45867 | I22: 2890 | J22: 45867 | K22: 12561777 | L22: 2490 | M22: 45867 | N22: 121561777 | O22: 7200 | P22: 45902 | Q22: 5349798
A23: 921 244 5418 | C23: REINSCRIPCIÓN | D23: ANGEL JOSUE SERAPIO ZUÑIGA | E23: MARZO-JUNIO | F23: 2040 | G23: 5049409 | H23: 45869 | I23: 2890 | J23: 45890 | K23: 5049409 | L23: 2490 | M23: 45889 | N23: 5049409 | U23: 10 MESES | V23: 0.3 | W23: 3958 | X23: 2770
A24: 921 298 7455 | C24: REINSCRIPCIÓN | D24: ADA MARIA TORRES JUAREZ | E24: MARZO-JUNIO | F24: GRATIS | G24: GRATIS | H24: 45882 | I24: 2890 | J24: 45882 | K24: 1305250 | L24: 2490 | M24: 45882 | N24: 1308250 | O24: 7200 | P24: 45884 | Q24: 1508250 | U24: 12 MESES | V24: 0.2 | W24: 3958 | X24: 2640
C25: REINSCRIPCIÓN | D25: NATHAN DIDIER CARRASCO CASTAÑEDA | E25: MARZO-JUNIO | F25: 2040 | G25: 2906250 | H25: 45880 | I25: 2890 | J25: 45880 | K25: 2906250 | L25: 2490 | M25: 45880 | N25: 2906250
C26: REINSCRIPCIÓN | D26: GABRIEL ALEJANDRO SERVIN SOBERANO | E26: NOVIEMBRE-DICIEMBRE | F26: 2040 | G26: TRANF | H26: 45677 | I26: 2890 | J26: 45677 | K26: TRANSF | L26: 2490 | M26: 45677 | N26: TRANSF | O26: 7200 | P26: 45677 | Q26: TRANSF
A27: 921 302 6787 | C27: REINSCRIPCIÓN | D27: ZOE ROSADO MARTINEZ | E27: NOVIEMBRE-DICIEMBRE | F27: GRATIS | G27: GRATIS | H27: 45888 | O27: 7200 | P27: 45918 | Q27: 26757007
A28: 921 197 6868 | C28: REINSCRIPCIÓN | D28: AXEL FABÍAN BARROSO CARDENAS | E28: MARZO-JUNIO | F28: GRATIS | G28: GRATIS | H28: 45881 | I28: 1500 | J28: 45881 | K28: 263117 | L28: 300 | M28: 45881 | N28: 263117 | O28: 4200 | P28: 45881 | Q28: 263117 | U28: 12 MESES | V28: 0.23 | W28: 3958 | X28: 2540
A29: 921 276 5361 | C29: REINSCRIPCIÓN | D29: XIMENA GARDUZA LIMÓN | E29: MARZO-JUNIO | F29: GRATIS | G29: GRATIS | H29: 45897 | I29: 2890 | J29: 45897 | K29: 17957921 | O29: 3000 | P29: 45897 | Q29: 17957921 | U29: 10 MESES | W29: 3958 | X29: 2969
A30: 921 125 2551 | C30: REINSCRIPCIÓN | D30: GABRIEL ALEJANDRO FUENTES TORRES | E30: MARZO-JUNIO | F30: GRATIS | G30: GRATIS | H30: 45897 | I30: 1445 | J30: 45890 | K30: 681592 | L30: 1249 | M30: 45890 | N30: 681592 | O30: 3100 | P30: 45918 | Q30: 180925
A31: 921 297 3835 | C31: REINSCRIPCIÓN | D31: MELANY AIDEE RODRIGUEZ TOLENTINO | E31: MARZO-JUNIO | F31: GRATIS | G31: GRATIS | H31: 45899 | I31: 1445 | J31: 45905 | K31: SF | L31: GRATIS | M31: 45899 | N31: GRATIS | U31: 10 MESES | V31: 0.3 | W31: 3958 | X31: 2770
A32: 921 239 7841 | C32: REINSCRIPCIÓN | D32: VICTORIA POLA CARDENAS | E32: MARZO-JUNIO | F32: GRATIS | G32: GRATIS | H32: 45911 | I32: 1445 | J32: 45911 | K32: 1109250 | L32: 1249 | M32: 45911 | N32: 1109250
A33: 921 105 0923 | C33: REINSCRIPCIÓN | D33: ALISSA XIMENA GUTIERRES DOMINGUEZ | E33: MARZO-JUNIO | F33: GRATIS | G33: GRATIS | H33: 45899 | U33: 10 | V33: 0.18 | W33: 3958 | X33: 3246
A34: 921 280 1194 | C34: NUEVO INGRESO | D34: EDITH FERNANDA GARCIA PEÑA | E34: MARZO-JUNIO | F34: GRATIS | G34: GRATIS | H34: 45932 | I34: 1445 | J34: 45932 | K34: 89983 | L34: 1249 | M34: 45698 | N34: 89983 | U34: 10 MESES | V34: 0.3 | W34: 3958 | X34: 2771.16
B36: 0
B37: N° | C37: MATRICULA | D37: NOMBRE DEL ALUMNO | E37: AGOSTO | H37: SEPTIEMBRE | K37: OCTUBRE | N37: NOVIEMBRE | Q37: DICIEMBRE | T37: ENERO | W37: JULIO | Z37: FEBRERO | AC37: MARZO | AF37: ABRIL | AI37: MAYO | AL37: JUNIO
E38: MONTO | F38: FECHA | G38: FOLIO | H38: MONTO | I38: FECHA | J38: FOLIO | K38: MONTO | L38: FECHA | M38: FOLIO | N38: MONTO | O38: FECHA | P38: FOLIO | Q38: MONTO | R38: FECHA | S38: FOLIO | T38: MONTO | U38: FECHA | V38: FOLIO | W38: MONTO | X38: FECHA | Y38: FOLIO | Z38: MONTO | AA38: FECHA | AB38: FOLIO | AC38: MONTO | AD38: FECHA | AE38: FOLIO | AF38: MONTO | AG38: FECHA | AH38: FOLIO | AI38: MONTO | AJ38: FECHA | AK38: FOLIO | AL38: MONTO | AM38: FECHA | AN38: FOLIO
D39: =D8 -> ARIADNA SORIANO LAVIN | H39: 2770 | I39: 45905 | J39: 8302505 | K39: 3170 | L39: 45940 | M39: 9638278 | N39: 3170 | O39: 45966 | P39: 4543291 | Q39: 3170 | R39: 45996 | S39: 54895621 | T39: 2686 | U39: 46025 | V39: 2069159 | Z39: 2686 | AA39: 46055 | AB39: 58974623 | AC39: 2686 | AD39: 46085 | AE39: 7009621 | AF39: 2700 | AG39: 46113 | AH39: 663958 | AI39: 2770 | AJ39: 46146 | AK39: 40526 | AL39: 2770 | AM39: 46176 | AN39: 30626 | AO39: fact ok
D40: =D9 -> JATZIRI KRISTEL ZURIANO FELIX | H40: 3048 | I40: 45904 | J40: 98865412 | K40: 3048 | L40: 45958 | M40: 7741020 | N40: 3048 | O40: 45997 | P40: 774102 | Q40: 3048 | R40: 46014 | S40: 774102 | T40: 3048 | U40: 46080 | V40: 774102 | Z40: 3048 | AA40: 46080 | AB40: 774102 | AC40: 3023 | AD40: 46121 | AE40: 774102 | AF40: 3023 | AG40: 46121 | AH40: 774102 | AI40: 3048 | AJ40: 46188 | AK40: 455512I | AL40: 3048 | AM40: 46188 | AN40: 455512I | AO40: no fact
D41: =D10 -> EVAN MATIAS ZARAGOZA MATINEZ | E41: 2540 | F41: 45874 | G41: 8.5902335e+16 | H41: 2540 | I41: 45901 | J41: 8.5901268e+16 | K41: 2540 | L41: 45932 | M41: 8.5903553e+16 | N41: 2540 | O41: 45960 | P41: 8.5909706e+16 | Q41: 2540 | R41: 45989 | S41: 8.5905945e+16 | T41: 2540 | U41: 46020 | V41: 8.5903441e+16 | W41: 2540 | X41: 46000 | Y41: 8.5900677e+16 | Z41: 2540 | AA41: 46055 | AB41: 54897621 | AC41: 2540 | AD41: 46080 | AE41: 8.5900895e+16 | AF41: 2540 | AG41: 46119 | AH41: 8.5902254e+16 | AI41: 2540 | AJ41: 46148 | AK41: 444312668 | AL41: 2540 | AM41: 46176 | AN41: 224315464 | AO41: fact ok
D42: =D11 -> HANNA NICOLE SALOME GOMEZ | H42: 3048 | I42: 45904 | J42: SF | K42: 3050 | L42: 45934 | M42: 434038 | N42: 3050 | O42: 45972 | P42: 79311 | Q42: 3050 | R42: 46028 | S42: 918804 | T42: 3050 | U42: 46028 | V42: 89746321 | Z42: 3050 | AA42: 46059 | AB42: 48122178 | AC42: 3050 | AD42: 46089 | AE42: 54789631 | AF42: 3050 | AG42: 46116 | AH42: 58978623 | AI42: 3050 | AJ42: 46164 | AK42: 813641 TC | AL42: 3050 | AM42: 45799 | AN42: 813841 TC | AO42: no fact
D43: =D12 -> JIMENNA SOFIA OCHA | H43: 3048 | I43: 45909 | J43: 84971350 | K43: 3048 | L43: 45931 | M43: 92414255 | N43: 3048 | O43: 45964 | P43: 80467545 | Q43: 3048 | R43: 45996 | S43: 75359819 | T43: 3048 | U43: 46027 | V43: TC | Z43: 3048 | AA43: 46055 | AB43: 58994917 | AC43: 3048 | AD43: 46083 | AE43: 86719271 | AF43: 3048 | AG43: 46115 | AH43: 37342463 | AI43: 3048 | AJ43: 46143 | AK43: 319947 | AL43: 3048 | AM43: 46174 | AN43: 31468648 | AO43: FACT OK
D44: =D13 -> RENATA VALENTINA LOPEZ CRUZ | H44: 2309 | I44: 45897 | J44: 178267 | K44: 2309 | L44: 45934 | M44: 91025 | N44: 2309 | O44: 45966 | P44: SF | Q44: 2309 | R44: 45996 | S44: 54897623 | T44: 2309 | U44: 46027 | V44: 70126 | W44: 2309 | X44: 45996 | Y44: 89792134 | Z44: 2709 | AA44: 46086 | AB44: 614487 | AC44: 2709 | AD44: 46086 | AE44: 614487 | AF44: 2709 | AG44: 46141 | AH44: 909023084311960 | AI44: 2709 | AJ44: 46156 | AK44: 414313466 | AL44: 2709 | AM44: 46183 | AN44: 14316166 | AO44: NO TIENE FACT
D45: =D14 -> LUISA PAULETTE SANCHEZ SANTOS | E45: 2540 | F45: 45902 | G45: 868081 | H45: 2540 | I45: 45902 | J45: 868081 | K45: 2540 | L45: 45936 | M45: 213959 | N45: 2540 | O45: 45966 | P45: TC | Q45: 2540 | R45: 45997 | S45: 48792132 | W45: 2540 | X45: 45997 | Y45: 48792132 | Z45: 2540 | AA45: 46058 | AB45: 91576 | AC45: 2540 | AD45: 46085 | AE45: 51695 | AF45: 2540 | AG45: 46086 | AH45: 51695 | AI45: 2540 | AJ45: 46149 | AK45: 290 tarjeta | AL45: 2540 | AM45: 46179 | AN45: 951654 TC | AO45: diferencia de $60 acumular en la colegiatura de junio | AP45: FACT OK
D46: =D15 -> VANIA ZOE FARIAS BAHENA | E46: 2540 | F46: 46208 | G46: 2862924 | H46: 2540 | I46: 45905 | J46: 8650950 | K46: 2540 | L46: 45935 | M46: 4198604 | N46: 2540 | O46: 45966 | P46: 5535101 | Q46: 2540 | R46: 45996 | S46: 1495722 | T46: 2540 | U46: 46027 | V46: 9059678 | W46: 2540 | X46: 45993 | Y46: 58741236 | Z46: 2540 | AA46: 46058 | AB46: 1373476 | AC46: 2540 | AD46: 46117 | AE46: 2820694 | AF46: 2540 | AG46: 46117 | AH46: 1846459 | AI46: 2540 | AJ46: 46147 | AK46: 4416598 | AL46: 2540 | AM46: 46178 | AN46: 715659 | AO46: no fact
C47: ANUAL | D47: =D16 -> LEYLA CRUZ ARIZPE | E47: 2309 | F47: 45638 | G47: 911025 | H47: 2309 | I47: 45638 | J47: 911025 | K47: 2309 | L47: 45638 | M47: 911025 | N47: 2309 | O47: 46003 | P47: 911025 | Q47: 2309 | R47: 46003 | S47: 911025 | T47: 2309 | U47: 2309 | V47: 46003 | W47: 2309 | X47: 2309 | Y47: 46003 | Z47: 2309 | AA47: 2309 | AB47: 46003 | AC47: 2309 | AD47: 2309 | AE47: 46003 | AF47: 2309 | AG47: 2309 | AH47: 46003
D48: =D17 -> ANGEL DE JESUS RABANALES ALEGRIA | E48: 2705 | F48: 45894 | G48: 96304163 | H48: 2705 | I48: 45894 | J48: 96304163 | K48: 2705 | L48: 45934 | M48: 34586911 | N48: 2705 | O48: 45966 | P48: 81061853 | Q48: 2705 | R48: 45999 | S48: 98916367 | T48: 2705 | U48: 46027 | V48: 55497963 | Z48: 3105 | AA48: 46038 | AB48: 1601260 | AC48: 2705 | AD48: 46084 | AE48: 88703884 | AF48: 2705 | AG48: 46117 | AH48: 82248965 | AI48: 2705 | AJ48: 46147 | AK48: 620285 | AL48: 2705 | AM48: 46175 | AN48: 66334742 | AO48: fact ok | AP48: 750 | AQ48: 46199 | AR48: EXAMENES EXT
C49: pago anual | D49: =D18 -> KARLA DANIELA LUIS CARRERA | H49: 3246 | I49: 45917 | J49: 68801 | K49: 3246 | L49: 45917 | M49: 68801 | N49: 3246 | O49: 45917 | P49: 68801 | Q49: 3246 | R49: 45917 | S49: 68801 | T49: 3246 | U49: 46027 | V49: TARJETADEBIT | W49: 3246 | X49: 46027 | Y49: TARJETADEBIT | Z49: 3246 | AA49: 46027 | AB49: TARJETADEBIT | AC49: 3246 | AD49: 46027 | AE49: TARJETADEBIT | AF49: 3246 | AG49: 46027 | AH49: TARJETADEBIT | AO49: fact ok
D50: =D19 -> NAIM JIMENEZ DOMINGUEZ | H50: 3294 | I50: 45903 | J50: 277410 | K50: 2898 | L50: 45903 | M50: 277410 | N50: 3246 | O50: 45964 | P50: TRANSF5897 | Q50: 3246 | R50: 46364 | S50: 64897213 | T50: 3246 | U50: 46037 | V50: 277410 | Z50: 3246 | AA50: 46054 | AB50: 58742316 | AC50: 3246 | AD50: 46122 | AE50: 277410 | AF50: =746+2500 -> 3246 | AG50: 46173 | AH50: 44521/48221 | AO50: APENAS PAGO ABRIL
C51: pago anual | D51: =D20 -> LIAM EZEQUIEL OVILLA ESPINOZA | H51: 3048 | I51: 45905 | J51: 485213 | K51: 3048 | L51: 45905 | M51: 485213 | N51: 3048 | O51: 45905 | P51: 485213 | Q51: 3048 | R51: 45905 | S51: 485213 | T51: 3048 | U51: 45905 | V51: 485213 | Z51: 3048 | AA51: 45905 | AB51: 485213 | AC51: 3048 | AD51: 45905 | AE51: 485213 | AF51: 3048 | AG51: 45905 | AH51: 485213
D52: =D21 -> ELIAS EDUARDO SANCHEZ DIAZ | H52: 3246 | I52: 45902 | J52: 7290 | K52: 3246 | L52: 45933 | M52: 7314 | N52: 3246 | O52: 45967 | P52: 7336 | Q52: 3246 | R52: 45994 | S52: 7356 | T52: 3246 | U52: 46023 | V52: 7386 | Z52: 3246 | AA52: 46059 | AB52: dep banco | AC52: 3246 | AD52: 46086 | AE52: mbo7089 | AF52: 3246 | AG52: 46122 | AH52: no.op089 | AI52: 3245 | AJ52: 46176 | AK52: 7487 TD | AL52: 3245 | AM52: 46176 | AN52: 7471 TD | AO52: fact ok
D53: =D22 -> NOE DAVID GARCIA NELSON | H53: 3246 | I53: 45905 | J53: 60337415 | K53: 3246 | L53: 45935 | M53: 6840651 | N53: 3246 | O53: 46005 | P53: 4224894 | Q53: 3246 | R53: 46005 | S53: 4224894 | T53: 3646 | U53: 46038 | V53: 6785987 | Z53: 3646 | AA53: 46038 | AB53: 5487962310 | AC53: 3646 | AD53: 46100 | AE53: 1426508 | AF53: 3646 | AG53: 46125 | AH53: 9949622
D54: =D23 -> ANGEL JOSUE SERAPIO ZUÑIGA | H54: 2770 | I54: 45813 | J54: 60337415 | K54: 2770 | L54: 45923 | M54: 89661132 | N54: 2841 | O54: 45966 | P54: 2496991 | Q54: 2771 | R54: 46002 | S54: 6861158 | T54: 2771 | U54: 46037 | V54: 142148792154 | Z54: 2771 | AA54: 46063 | AB54: 1610335 | AC54: 2771 | AD54: 46092 | AE54: 3331528 | AF54: 2771 | AG54: 46116 | AH54: 2018820 | AI54: 2770 | AJ54: 46153 | AK54: 6069297 | AL54: 2770 | AM54: 46182 | AN54: 970125
D55: =D24 -> ADA MARIA TORRES JUAREZ | H55: 2640 | I55: 45915 | J55: 1509251 | K55: 2640 | L55: 45958 | M55: 71374561 | N55: 2640 | O55: 45974 | P55: 6573386 | Q55: 2640 | R55: 46002 | S55: 8783276 | T55: 2640 | U55: 46027 | V55: 3183656 | W55: 2640 | X55: 46002 | Y55: 57623736 | Z55: 2640 | AA55: 46078 | AB55: 9440548 | AC55: 26550 | AD55: 46161 | AE55: 828824892 | AF55: 2650 | AG55: 46161 | AH55: 828824892 | AI55: 2650 | AJ55: 46154 | AK55: 828824892 | AO55: APENAS PAGO LOS PEND
D56: =D25 -> NATHAN DIDIER CARRASCO CASTAÑEDA | H56: 2474 | I56: 45907 | J56: 50117669 | K56: 2474 | L56: 45926 | M56: 2609250 | N56: 2474 | O56: 45966 | P56: 811250 | Q56: 2474 | R56: 45966 | S56: 2311250 | T56: 2474 | U56: 46026 | V56: 50117669 | Z56: 2474 | AA56: 46058 | AB56: 98745123 | AC56: 2474 | AD56: 46095 | AE56: 1403260 | AF56: 2474 | AG56: 46127 | AH56: 1504261 | AI56: 2474 | AJ56: 46153 | AK56: 458261 | AL56: 2474 | AM56: 46167 | AN56: 685314
D57: =D26 -> GABRIEL ALEJANDRO SERVIN SOBERANO | H57: 2770 | I57: 45897 | J57: 250828 | K57: 2770 | L57: 45897 | M57: 250828 | N57: 2770 | O57: 45897 | P57: 250828 | Q57: 2770 | R57: 45897 | S57: 250828 | T57: 2770 | U57: 45897 | V57: 250828 | Z57: 2770 | AA57: 45897 | AB57: 250828 | AC57: 2770 | AD57: 45897 | AE57: 250828 | AF57: 2770 | AG57: 45897 | AH57: 250828 | AI57: 2799 | AJ57: 46175 | AK57: 2700 TD | AL57: 2799 | AM57: 46175 | AN57: 2700 TD | AO57: fact ok
D58: =D27 -> ZOE ROSADO MARTINEZ | H58: 2770 | I58: 45904 | J58: 48907887 | K58: 2770 | L58: 45936 | M58: SF | N58: 2770 | O58: 45967 | P58: 8039301 | Q58: 2770 | R58: 46015 | S58: 9949448 | T58: 2700 | U58: 46026 | V58: 69373488 | Z58: 2700 | AA58: 46054 | AB58: 173225824 | AC58: 2700 | AD58: 46122 | AE58: 67948402 | AF58: 2700 | AG58: 46122 | AH58: 67948402 | AI58: 2700 | AJ58: 46154 | AK58: 57486246 | AL58: 2700 | AM58: 46195 | AN58: 66858798
D59: =D28 -> AXEL FABÍAN BARROSO CARDENAS | H59: 2474 | I59: 46034 | J59: 52467670 | K59: 2474 | L59: 46034 | M59: 52467670 | N59: 2474 | O59: 46034 | P59: 52467670 | Q59: 2474 | R59: 46054 | S59: 52467670 | T59: 2474 | U59: 46054 | V59: 52467670 | Z59: 2474 | AA59: 46054 | AB59: 52467670 | AC59: 2474 | AD59: 46185 | AE59: 821872 | AF59: 2474 | AG59: 46185 | AH59: 821872 | AI59: 2474 | AJ59: 46185 | AK59: 821872 | AL59: 2474 | AM59: 46185 | AN59: 821872
D60: =D29 -> XIMENA GARDUZA LIMÓN | H60: 2969 | I60: 45951 | J60: 51836829 | K60: 2969 | L60: 45936 | M60: 95836432 | N60: 2969 | O60: 45936 | P60: 95867385 | Q60: 2969 | R60: 46036 | S60: 94966950 | T60: 2969 | U60: 46025 | V60: 86198917 | Z60: 2969 | AA60: 46124 | AB60: 53709293 | AC60: 2969 | AD60: 46161 | AE60: 84599846
D61: =D30 -> GABRIEL ALEJANDRO FUENTES TORRES | H61: 2770 | I61: 45902 | J61: 89877960 | K61: 3170 | L61: 45947 | M61: 251017 | N61: 2770 | O61: 45966 | P61: 251105 | Q61: 3170 | R61: 46021 | S61: 251230 | T61: 3170 | U61: 46027 | V61: 260105 | Z61: 3170 | AA61: 46058 | AB61: 260205 | AC61: 3170 | AD61: 46086 | AE61: 260305 | AF61: 3170 | AG61: 46086 | AH61: 260405 | AI61: 2770 | AJ61: 46127 | AK61: 260415
D62: =D31 -> MELANY AIDEE RODRIGUEZ TOLENTINO | H62: 2770 | I62: 45966 | J62: TC5489 | K62: 2770 | L62: 45966 | M62: TC5489 | N62: 2770 | O62: 45966 | P62: TC5489 | Q62: 2770 | R62: 46027 | S62: 98765412 | T62: 2770 | U62: 46027 | V62: 98765412 | Z62: 2770 | AA62: 46147 | AB62: 262703 | AC62: 2770 | AD62: 46147 | AE62: 262703 | AF62: 2770 | AG62: 46147 | AH62: 262703
D63: =D32 -> VICTORIA POLA CARDENAS | H63: 2770 | I63: 46358 | J63: 21225 | K63: 2770 | L63: 46358 | M63: 21225 | N63: 2770 | O63: 46358 | P63: 21225 | Q63: 2770 | R63: 46068 | S63: 98765412 | T63: 2770 | U63: 46082 | V63: 31245687 | AH63: CONVENIO | AK63: CONVENIO | AN63: CONVENIO
D64: =D33 -> ALISSA XIMENA GUTIERRES DOMINGUEZ | H64: 2969 | I64: 46035 | J64: 570688 | K64: 2969 | L64: 46037 | M64: 9792927 | N64: 2969 | O64: 46037 | P64: 4667592 | Q64: 2969 | R64: 46037 | S64: 4736564 | T64: 2969 | U64: 46150 | V64: 2310670 | Z64: 2969 | AA64: 46150 | AB64: 442224 | AC64: 2969 | AD64: 11/0672026 | AE64: 901276 | AF64: 2969 | AG64: 46196 | AH64: 4725217 | AK64: CONVENIO
D65: =D34 -> EDITH FERNANDA GARCIA PEÑA | K65: 2771 | L65: 45932 | M65: 89983 | N65: 2771 | O65: 45966 | P65: 552233 | Q65: 2771 | R65: 45997 | S65: 24151418 | T65: 2771 | U65: 46027 | V65: TARJETADEBIT | Z65: 2771 | AA65: 46058 | AB65: 953212 | AC65: 2771 | AD65: 46086 | AE65: 54897631 | AF65: 2771 | AG65: 46118 | AH65: 28873685 | AI65: 2771 | AJ65: 46148 | AK65: 289 (tarjeta cred) | AL65: 2771 | AM65: 46179 | AN65: 158878 TC | AO65: fact ok
D66: ANGEL DE JESUS RIVERA DOMINGUEZ | H66: 2705 | I66: 45902 | J66: 1510250 | K66: 2705 | L66: 45936 | M66: 1510250 | N66: 2705 | O66: 45967 | P66: 545678 | Q66: 2705 | R66: 45996 | S66: 45896472 | T66: 2705 | U66: 46026 | V66: 89765412 | Z66: 2705 | AA66: 46057 | AB66: 167380 | AC66: 2705 | AD66: 46086 | AE66: 503260 | AF66: 3247 | AG66: 46131 | AH66: 2904261 | AI66: 3105 | AJ66: 46189 | AK66: 9748869 | AO66: YA PASO PAGARA 15 Y 19

Sheet 3°S
F1: Centro de Investigación Educativa Colegio San Diego | S1: ACEPTADOS POR CORPORATIVO
F2: Punta el Campanario #183 Col. Bahia de San Martín CP 96536 | S2: PAGOS DE HIJOS DE MAESTROS
F3: PREESCOLAR 30PJN1037Z PRIMARIA 30PPR3773B SECUNDARIA 30PES0033G | S3: MES PAGADO
D4: FACTURA | F4: CICLO ESCOLAR 2024-2025 | S4: ALUMNO DADO DE BAJA
B7: N° | C7: MATRICULA | D7: NOMBRE DEL ALUMNO | E7: PROMOCION | F7: INSCRIPCION | G7: FOLIO | H7: FECHA | I7: MATERIAL | J7: FECHA | K7: FOLIO | L7: ARANCEL | M7: FECHA | N7: FOLIO | O7: LIBROS | P7: FECHA | Q7: FOLIO | R7: UNIFORMES | S7: FECHA | T7: FOLIO | U7: PLAN PAGO | V7: BECA | W7: COLEG | X7: TOTAL
A8: 921 223 9077 | B8: REINSCRIPCIÓN | D8: ALEJANDRO DOMINGUEZ LAUREANO | E8: NOVIEMBRE-DICIEMBRE | F8: 1700 | G8: 277410 | H8: 45628 | I8: 2890 | J8: 45882 | K8: 277410 | L8: 2499 | M8: 45868 | N8: 277410 | O8: 3600 | P8: 45901 | Q8: 277410
A9: 921 133 0288 | B9: REINSCRIPCIÓN | D9: ARYED ALEJANDRA MONTESINOS GARCIA | E9: NOVIEMBRE-DICIEMBRE | F9: 1700 | G9: 1455301 | H9: 45761 | O9: 7200 | P9: 45859 | Q9: 1455301
A10: 921 109 9026 | B10: REINSCRIPCIÓN | D10: DAMARA GENOVEVA PRIMO MORALES | E10: MARZO-JUNIO | F10: 1700 | G10: 45838 | H10: 45838 | I10: 2890 | J10: 45838 | K10: 94628 | L10: 2499 | M10: 45838 | N10: 3006250 | O10: 7200 | P10: 45917 | Q10: 1709250
A11: 229 551 1831 | B11: REINSCRIPCIÓN | D11: SAMUEL VALLEROJO SANCHEZ | E11: MARZO-JUNIO | F11: 1700 | G11: 45842 | H11: 45842 | I11: 2890 | J11: 45842 | K11: 8.5903085e+16 | L11: 2499 | M11: 45876 | N11: 90501257 | O11: 7200 | P11: 45918 | Q11: 65471502
A12: 921 142 2363 | B12: REINSCRIPCIÓN | D12: CARLOS MIGUEL MATEO ORTEGA | E12: MARZO-JUNIO | F12: 2040 | G12: 85904603774319000´ | H12: 45847 | I12: 2890 | J12: 45847 | K12: 85904633504319053´ | L12: 2499 | M12: 45847 | N12: 8.5904624e+17 | O12: 7200 | P12: 45847 | Q12: 085904806074319059´
A13: 921 297 3074 | B13: NUEVO INGRESO | D13: LUIS ALEJANDRO RODRIGUEZ BOFFIL | E13: ENERO-FEBRERO | F13: GRATIS | G13: GRATIS | H13: 45863 | I13: 2690 | J13: 45863 | K13: 4373274 | L13: 2499 | M13: 45863 | N13: 4373274 | O13: 7200 | P13: 45894 | Q13: 58193010 | U13: 12 MESES | V13: 0.23 | W13: 3299 | X13: 2540
A14: 921 307 0216 | B14: REINSCRIPCIÓN | D14: IKER SANTIAGO SAAVEDRA GRAJEDA | E14: MARZO-JUNIO | F14: 2040 | G14: 3170750108 | H14: 45872 | L14: 2499 | M14: 45885 | N14: 4358531070 | O14: 7200 | P14: 45885 | Q14: 4358961369
A15: 921 235 4100 | B15: REINSCRIPCIÓN | D15: ADRIEL MORALES DOMINGUEZ | E15: MARZO-JUNIO | F15: GRATIS | G15: GRATIS | H15: 45901 | O15: 7200 | P15: 45914 | Q15: TC
B16: REINSCRIPCIÓN | D16: HELLEN MONTSERRAT HERNANDEZ GARCIA | E16: MARZO-JUNIO | F16: GRATIS | G16: GRATIS | H16: 45903 | L16: 1250 | M16: 45903 | N16: 309250 | U16: 12 MESES | V16: 0.23 | W16: 3299 | X16: 2540
B17: REINSCRIPCIÓN | D17: ROMINA GONZALEZ HERNANDEZ | E17: MARZO-JUNIO | F17: GRATIS | G17: GRATIS | H17: 45894 | I17: 1345 | J17: 45894 | K17: 185330 | L17: 1249.5 | M17: 45894 | N17: 185330 | U17: 10 MESES | V17: 0.23 | W17: 3958.8 | X17: 3246
B18: REINSCRIPCIÓN | D18: KARLA VALENTINA ROSALES SAN JUAN | E18: MARZO-JUNIO | F18: GRATIS | G18: GRATIS | H18: 45898 | I18: 1345 | J18: 45897 | K18: 27698147 | L18: 1249.5 | M18: 45897 | N18: 27698147 | O18: 7200 | P18: 45914 | Q18: TC
B19: REINSCRIPCIÓN | D19: EMILIO ESTRADA CABRERA | E19: MARZO-JUNIO | F19: GRATIS | G19: GRATIS | H19: 45911 | O19: 7200 | P19: 45922 | Q19: TC
A20: 921 239 7841 | B20: REINSCRIPCIÓN | D20: PAOLA AYALETH POLA CARDENAS | E20: MARZO-JUNIO | F20: GRATIS | G20: GRATIS | H20: 45911 | I20: 1345 | J20: 45911 | K20: 1109250 | L20: 1249.5 | M20: 45911 | N20: 1109250
B29: COLEGIATURA
B30: N° | C30: MATRICULA | D30: NOMBRE DEL ALUMNO | E30: AGOSTO | H30: SEPTIEMBRE | K30: OCTUBRE | N30: NOVIEMBRE | Q30: DICIEMBRE | T30: ENERO | W30: JULIO | Z30: FEBRERO | AC30: MARZO | AF30: ABRIL | AI30: MAYO | AL30: JUNIO
E31: MONTO | F31: FECHA | G31: FOLIO | H31: MONTO | I31: FECHA | J31: FOLIO | K31: MONTO | L31: FECHA | M31: FOLIO | N31: MONTO | O31: FECHA | P31: FOLIO | Q31: MONTO | R31: FECHA | S31: FOLIO | T31: MONTO | U31: FECHA | V31: FOLIO | W31: MONTO | X31: FECHA | Y31: FOLIO | Z31: MONTO | AA31: FECHA | AB31: FOLIO | AC31: MONTO | AD31: FECHA | AE31: FOLIO | AF31: MONTO | AG31: FECHA | AH31: FOLIO | AI31: MONTO | AJ31: FECHA | AK31: FOLIO | AL31: MONTO | AM31: FECHA | AN31: FOLIO
D32: =D8 -> ALEJANDRO DOMINGUEZ LAUREANO | H32: 1200 | I32: 45905 | J32: SF | K32: 1200 | L32: 45936 | M32: SF | N32: 1200 | O32: 45967 | P32: SF | Q32: 1200 | R32: 45996 | S32: SF | T32: 1200 | U32: 45992 | V32: 277410 | Z32: 1200 | AA32: 46055 | AB32: 277410 | AC32: 1200 | AD32: 46086 | AE32: 277410 | AF32: 1200 | AG32: 46107 | AH32: 277410 | AI32: 1200 | AJ32: 46148 | AK32: 277410 | AL32: 1200 | AM32: 46155 | AN32: 277410
D33: =D9 -> ARYED ALEJANDRA MONTESINOS GARCIA | H33: 2640 | I33: 45901 | J33: 10925 | K33: 2640 | L33: 45933 | M33: 127941871861 | N33: 2640 | O33: 45966 | P33: 501181180 | Q33: 2640 | R33: 45994 | S33: 50118180 | T33: 2640 | U33: 46026 | V33: 7366787 | W33: 2640 | X33: 46026 | Y33: 7366787 | Z33: 2640 | AA33: 46083 | AB33: 203260 | AC33: 2640 | AD33: 46085 | AE33: 54897621 | AF33: 2640 | AG33: 46115 | AH33: 304260 | AI33: 2640 | AJ33: 46146 | AK33: 60294474 | AL33: 2640 | AM33: 46174 | AN33: 2688668 | AO33: FACT OK
D34: =D10 -> DAMARA GENOVEVA PRIMO MORALES | H34: 3247 | I34: 45905 | J34: 509250 | K34: 3247 | L34: 45936 | M34: 610251 | N34: 3247 | O34: 45967 | P34: 611250 | Q34: 3247 | R34: 46022 | S34: 3112251 | T34: 3247 | U34: 46044 | V34: 221260 | Z34: 3247 | AA34: 46065 | AB34: 1202262 | AC34: 3247 | AD34: 46123 | AE34: 1104260 | AF34: 3247 | AG34: 46175 | AH34: 753426 | AI34: 3247 | AJ34: 46175 | AK34: 753426
D35: =D11 -> SAMUEL VALLEROJO SANCHEZ | H35: 2350 | I35: 45905 | J35: 8.590596e+16 | K35: 2350 | L35: 45935 | M35: 8.5904047e+16 | N35: 2350 | O35: 45967 | P35: 8.5900412e+16 | Q35: 2350 | R35: 45995 | S35: 8.5901203e+16 | T35: 2350 | U35: 46026 | V35: 8.5900765e+16 | W35: 2350 | X35: 45995 | Y35: 8.5901203e+16 | Z35: 2350 | AA35: 46065 | AB35: 232571686440694 | AC35: 2350 | AD35: 46085 | AE35: 21564987 | AF35: 2350 | AG35: 46116 | AH35: 8.5907478e+16 | AI35: 2350 | AJ35: 46146 | AK35: 390312469 | AL35: 2350 | AM35: 46178 | AN35: 60315660
B36: SE ENVIO INF DE INSCRIPCIN | D36: =D12 -> CARLOS MIGUEL MATEO ORTEGA | H36: 3246 | I36: 45847 | J36: 85904647184319056´ | K36: 3246 | L36: 45940 | M36: 85904647184319056´ | N36: 3246 | O36: 45964 | P36: 5487963521 | Q36: 3246 | R36: 45996 | S36: 8.5904027e+16 | T36: 3246 | U36: 46037 | V36: 8.5900449e+16 | Z36: 3246 | AA36: 46060 | AB36: 8.5904383e+15 | AC36: 3246 | AD36: 46086 | AE36: 784569 | AF36: 3246 | AG36: 46114 | AH36: 8.5901721e+16 | AI36: 3246 | AJ36: 46143 | AK36: 179060 | AL36: 3246 | AM36: 46171 | AN36: 314962 | AO36: FACT OK
D37: =D13 -> LUIS ALEJANDRO RODRIGUEZ BOFFIL | H37: 2540 | I37: 45905 | J37: 95032967 | K37: 2540 | L37: 45935 | M37: 43919755 | N37: 2540 | O37: 45964 | P37: 1197346 | Q37: 2540 | R37: 45996 | S37: 94338967 | T37: 2540 | U37: 46027 | V37: 89823987 | Z37: 2540 | AA37: 46058 | AB37: 3638040406 | AC37: 2540 | AD37: 46086 | AE37: 4521879863 | AF37: 2540 | AG37: 46117 | AH37: 1747899 | AI37: 2540 | AJ37: 46147 | AK37: 22663069 | AL37: 2540 | AM37: 46178 | AN37: 51147971 | AO37: FACT OK
D38: =D14 -> IKER SANTIAGO SAAVEDRA GRAJEDA | H38: 2770 | I38: 45908 | J38: 7326614361 | K38: 2770 | L38: 45936 | M38: 30753647 | N38: 2770 | O38: 2770 | P38: 87979245 | Q38: 2770 | R38: 45996 | S38: 3834974946 | T38: 2770 | U38: 46027 | V38: 6518917920 | Z38: 2770 | AA38: 46063 | AB38: 30753647 | AC38: 2770 | AD38: 46088 | AE38: 71166682 | AF38: 2770 | AG38: 46156 | AH38: 27485894 | AI38: 2770 | AJ38: 46147 | AK38: 94974910 | AL38: 2770 | AM38: 46176 | AN38: 31302167 | AO38: FACT OK
D39: =D15 -> ADRIEL MORALES DOMINGUEZ | E39: 2540 | F39: 45877 | G39: 30777402 | H39: 2540 | I39: 45909 | J39: 7801886 | K39: 1820 | L39: 45935 | M39: 6288443 | N39: 1820 | O39: 45935 | P39: 8151048 | Q39: 1820 | R39: 45935 | S39: 69512345 | T39: 1820 | U39: 46026 | V39: 7745561 | Z39: 1820 | AA39: 46062 | AB39: 6718806 | AC39: 1820 | AD39: 46087 | AE39: 240003 | AF39: 1820 | AG39: 46114 | AH39: 7438562 | AI39: 1820 | AJ39: 46150 | AK39: 7713655 | AL39: 1850 | AM39: 46182 | AN39: SF TRNS | AO39: FACT OK
D40: =D16 -> HELLEN MONTSERRAT HERNANDEZ GARCIA | H40: 2540 | I40: 45935 | J40: …..... | K40: 2540 | L40: 45935 | M40: 558963 | N40: 2540 | O40: 45964 | P40: 448521 | Q40: 2540 | R40: 45997 | S40: 331879 | T40: 2540 | U40: 45664 | V40: 542139 | Z40: CONVENIO | AC40: CONVENIO | AF40: CONVENIO | AI40: CONVENIO
D41: =D17 -> ROMINA GONZALEZ HERNANDEZ | H41: 3246 | I41: 45903 | J41: 89006 | K41: 3246 | L41: 46300 | M41: 548972 | N41: 3246 | O41: 45962 | P41: 379546 | Q41: 3246 | R41: 46133 | S41: 93721298 | T41: 3246 | U41: 46133 | V41: 93721298 | Z41: =1508+1738 -> 3246 | AA41: 21/04/2026 Y 17/05/2026 | AB41: 93721298 Y 64467721 | AC41: =762+2484 -> 3246 | AD41: 46178 | AF41: CONVENIO | AI41: CONVENIO
D42: =D18 -> KARLA VALENTINA ROSALES SAN JUAN | H42: 3249 | I42: 45918 | J42: 58168986 | K42: 3249 | L42: 45938 | M42: 55168601 | N42: 3249 | O42: 45966 | P42: 72108656 | Q42: 3249 | R42: 45997 | S42: 89237488 | T42: 3249 | U42: 46027 | V42: 59592380 | Z42: 3249 | AA42: 46059 | AB42: 4751520 | AC42: 3249 | AD42: 46086 | AE42: 5489746521 | AF42: 3300 | AG42: 46131 | AH42: 38396580 | AI42: 3249 | AJ42: 46147 | AK42: 18388546 | AL42: 3249 | AM42: 46174 | AN42: 63165277
D43: =D19 -> EMILIO ESTRADA CABRERA | H43: 3048 | I43: 45902 | J43: TD28066 | K43: 3048 | L43: 45935 | M43: TD28066 | N43: 3048 | O43: 46332 | P43: TD28066 | Q43: 3048 | R43: 46361 | S43: TD28066 | T43: 3048 | U43: 46361 | V43: TD28066 | Z43: 3048 | AA43: 46361 | AB43: TD28066 | AC43: 3448 | AD43: 46190 | AE43: 445359 TD | AF43: 1552 | AG43: 46190 | AH43: 445359 TD | AI43: CONVENIO | AO43: no fact
D44: =D20 -> PAOLA AYALETH POLA CARDENAS | H44: 2386 | I44: 45993 | J44: 21225 | K44: 2686 | L44: 45993 | M44: 21225 | N44: 2686 | O44: 45993 | P44: 21225 | Q44: 2686 | R44: 45993 | S44: 21225 | T44: 2686 | U44: 46358 | V44: 21225 | Z44: CONVENIO | AC44: CONVENIO | AF44: CONVENNIO | AI44: CONVENIO
H45: 23062
H46: 34142
H50: 2309 | I50: 9236

Sheet 1-2°B
F1: Centro de Investigación Educativa Colegio San Diego | S1: ACEPTADOS POR CORPORATIVO
F2: Punta el Campanario #183 Col. Bahia de San Martín CP 96536 | S2: PAGOS DE HIJOS DE MAESTROS
F3: antonio100 | S3: MES PAGADO
D4: FACTURA | F4: CICLO ESCOLAR 2024-2025 | S4: ALUMNO DADO DE BAJA
B7: N° | C7: MATRICULA | D7: NOMBRE DEL ALUMNO | E7: PROMOCION | F7: INSCRIPCION | G7: FOLIO | H7: FECHA | I7: MATERIAL | J7: FECHA | K7: FOLIO | L7: ARANCEL | M7: FECHA | N7: FOLIO | O7: LIBROS | P7: FECHA | Q7: FOLIO | R7: UNIFORMES | S7: FECHA | T7: FOLIO | U7: PLAN PAGO | V7: BECA | W7: COLEG | X7: TOTAL
B29: COLEGIATURA
B30: N° | C30: MATRICULA | D30: NOMBRE DEL ALUMNO | E30: AGOSTO | H30: SEPTIEMBRE | K30: OCTUBRE | N30: NOVIEMBRE | Q30: DICIEMBRE | T30: ENERO | W30: JULIO | Z30: FEBRERO | AC30: MARZO | AF30: ABRIL | AI30: MAYO | AL30: JUNIO
E31: MONTO | F31: FECHA | G31: FOLIO | H31: MONTO | I31: FECHA | J31: FOLIO | K31: MONTO | L31: FECHA | M31: FOLIO | N31: MONTO | O31: FECHA | P31: FOLIO | Q31: MONTO | R31: FECHA | S31: FOLIO | T31: MONTO | U31: FECHA | V31: FOLIO | W31: MONTO | X31: FECHA | Y31: FOLIO | Z31: MONTO | AA31: FECHA | AB31: FOLIO | AC31: MONTO | AD31: FECHA | AE31: FOLIO | AF31: MONTO | AG31: FECHA | AH31: FOLIO | AI31: MONTO | AJ31: FECHA | AK31: FOLIO | AL31: MONTO | AM31: FECHA | AN31: FOLIO

Sheet 3-4°B
F1: Centro de Investigación Educativa Colegio San Diego | S1: ACEPTADOS POR CORPORATIVO
F2: Punta el Campanario #183 Col. Bahia de San Martín CP 96536 | S2: PAGOS DE HIJOS DE MAESTROS
F3: PREESCOLAR 30PJN1037Z PRIMARIA 30PPR3773B SECUNDARIA 30PES0033G | S3: MES PAGADO
D4: FACTURA | F4: CICLO ESCOLAR 2024-2025 | S4: ALUMNO DADO DE BAJA
B7: N° | C7: MATRICULA | D7: NOMBRE DEL ALUMNO | E7: PROMOCION | F7: INSCRIPCION | G7: FOLIO | H7: FECHA | I7: MATERIAL | J7: FECHA | K7: FOLIO | L7: ARANCEL | M7: FECHA | N7: FOLIO | O7: LIBROS | P7: FECHA | Q7: FOLIO | R7: UNIFORMES | S7: FECHA | T7: FOLIO | U7: PLAN PAGO | V7: BECA | W7: COLEG | X7: TOTAL
B21: 14
B22: 15
B23: 16
B24: 17
B29: COLEGIATURA
B30: N° | C30: MATRICULA | D30: NOMBRE DEL ALUMNO | E30: AGOSTO | H30: SEPTIEMBRE | K30: OCTUBRE | N30: NOVIEMBRE | Q30: DICIEMBRE | T30: ENERO | W30: JULIO | Z30: FEBRERO | AC30: MARZO | AF30: ABRIL | AI30: MAYO | AL30: JUNIO
E31: MONTO | F31: FECHA | G31: FOLIO | H31: MONTO | I31: FECHA | J31: FOLIO | K31: MONTO | L31: FECHA | M31: FOLIO | N31: MONTO | O31: FECHA | P31: FOLIO | Q31: MONTO | R31: FECHA | S31: FOLIO | T31: MONTO | U31: FECHA | V31: FOLIO | W31: MONTO | X31: FECHA | Y31: FOLIO | Z31: MONTO | AA31: FECHA | AB31: FOLIO | AC31: MONTO | AD31: FECHA | AE31: FOLIO | AF31: MONTO | AG31: FECHA | AH31: FOLIO | AI31: MONTO | AJ31: FECHA | AK31: FOLIO | AL31: MONTO | AM31: FECHA | AN31: FOLIO

Sheet 5-6°B
F1: Centro de Investigación Educativa Colegio San Diego | S1: ACEPTADOS POR CORPORATIVO
F2: Punta el Campanario #183 Col. Bahia de San Martín CP 96536 | S2: PAGOS DE HIJOS DE MAESTROS
F3: PREESCOLAR 30PJN1037Z PRIMARIA 30PPR3773B SECUNDARIA 30PES0033G | S3: MES PAGADO
D4: FACTURA | F4: CICLO ESCOLAR 2024-2025 | S4: ALUMNO DADO DE BAJA
B7: N° | C7: MATRICULA | D7: NOMBRE DEL ALUMNO | E7: PROMOCION | F7: INSCRIPCION | G7: FOLIO | H7: FECHA | I7: MATERIAL | J7: FECHA | K7: FOLIO | L7: ARANCEL | M7: FECHA | N7: FOLIO | O7: LIBROS | P7: FECHA | Q7: FOLIO | R7: UNIFORMES | S7: FECHA | T7: FOLIO | U7: PLAN PAGO | V7: BECA | W7: COLEG | X7: TOTAL
A8: 33 1252 9236 | D8: ANA ISABEL RODRIGUEZ CASTILLO | E8: NOVIEMBRE-DICIEMBRE | F8: 1800 | G8: 2813960418 | H8: 45636 | I8: 2590 | J8: 45636 | K8: 2814043004 | L8: 2990 | M8: 45636 | N8: 2814114112 | O8: 6200 | P8: 45797 | Q8: 6736479464
A9: 921 123 1669 | D9: ABRIL YATZIL CRUZ ARIZPE | E9: MARZO-JUNIO | F9: 1800 | G9: 250623 | H9: 45831 | I9: 2590 | J9: 45831 | K9: 250623 | L9: 2990 | M9: 45831 | N9: 250623 | O9: 6200 | P9: 45831 | Q9: 250623
A10: 229 127 2310 | D10: NAHOMI CRUZ GOMEZ | E10: MARZO-JUNIO | F10: 1800 | G10: 33028 | H10: 45835 | I10: 2590 | J10: 45835 | K10: 33028 | L10: 2990 | M10: 45835 | N10: 33028 | O10: 6200 | P10: 45874 | Q10: TC | U10: 12 MESES | V10: 0.2 | W10: 3685 | X10: 3058
A11: 921 178 8837 | D11: IVANNA PAULINA ALCEDA GUILLEN | E11: MARZO-JUNIO | F11: GRATIS | G11: GRATIS | H11: 45866 | I11: 2590 | J11: 45866 | K11: 76790595 | L11: 2990 | M11: 45866 | N11: 76790595 | O11: 2000 | P11: 45920 | Q11: 35001304
B29: COLEGIATURA
B30: N° | C30: MATRICULA | D30: NOMBRE DEL ALUMNO | E30: AGOSTO | H30: SEPTIEMBRE | K30: OCTUBRE | N30: NOVIEMBRE | Q30: DICIEMBRE | T30: ENERO | W30: JULIO | Z30: FEBRERO | AC30: MARZO | AF30: ABRIL | AI30: MAYO | AL30: JUNIO
E31: MONTO | F31: FECHA | G31: FOLIO | H31: MONTO | I31: FECHA | J31: FOLIO | K31: MONTO | L31: FECHA | M31: FOLIO | N31: MONTO | O31: FECHA | P31: FOLIO | Q31: MONTO | R31: FECHA | S31: FOLIO | T31: MONTO | U31: FECHA | V31: FOLIO | W31: MONTO | X31: FECHA | Y31: FOLIO | Z31: MONTO | AA31: FECHA | AB31: FOLIO | AC31: MONTO | AD31: FECHA | AE31: FOLIO | AF31: MONTO | AG31: FECHA | AH31: FOLIO | AI31: MONTO | AJ31: FECHA | AK31: FOLIO | AL31: MONTO | AM31: FECHA | AN31: FOLIO
D32: =D8 -> ANA ISABEL RODRIGUEZ CASTILLO | H32: 3245 | I32: 45782 | J32: 48922771 | K32: 3245 | L32: 45935 | M32: 54896213 | N32: 3245 | O32: 45966 | P32: 89785461 | Q32: 3245 | R32: 45992 | S32: 89312066 | T32: 3245 | U32: 46023 | V32: 77361689 | Z32: 3245 | AA32: 46054 | AB32: 54789621 | AC32: 3245 | AD32: 46085 | AE32: 325489760 | AF32: 3245 | AG32: 46113 | AH32: 4578962314 | AI32: 3245 | AJ32: 46147 | AK32: 25992592 | AL32: 3245 | AM32: 46179 | AN32: 46351542
C33: PAGO AÑO COMPLETO | D33: =D9 -> ABRIL YATZIL CRUZ ARIZPE | H33: 3245 | I33: 45638 | J33: TRANSF | K33: 3245 | L33: 45638 | M33: TRANS | N33: 3245 | O33: 45638 | P33: TRANSF | Q33: 3245 | R33: 45638 | S33: TRANSF | T33: 3245 | U33: 45638 | V33: TRANSF | Z33: 3245 | AA33: 45638 | AB33: TRANSF | AC33: 3245 | AD33: 45638 | AE33: TRANSF | AF33: 3245 | AG33: 45638 | AH33: TRANSF | AI33: 3245 | AJ33: 45638 | AK33: TRANSF
D34: =D10 -> NAHOMI CRUZ GOMEZ | H34: 3510 | I34: 45882 | J34: 5425312 | K34: 2606 | L34: 45905 | M34: 4925 | N34: 2606 | O34: 45931 | P34: 60969 | Q34: 2606 | R34: 45992 | S34: 4925 | T34: 2606 | U34: 46024 | V34: 4925 | Z34: 2606 | AA34: 46057 | AB34: cta4925 | AC34: 2606 | AD34: 46086 | AE34: cta4925 | AF34: 2606 | AG34: 46086 | AH34: cta4925 | AI34: 2606 | AJ34: 46146 | AK34: 284 (tarjeta) | AL34: 2606 | AM34: 46174 | AN34: 21421 TC
D35: =D11 -> IVANNA PAULINA ALCEDA GUILLEN | H35: 3640 | I35: 45905 | J35: 4364809 | K35: 3640 | L35: 45933 | M35: 57449043 | N35: 3640 | O35: 45962 | P35: 89674123 | Q35: 3640 | R35: 45996 | S35: 437909900 | T35: 3640 | U35: 46024 | V35: 11491603 | Z35: 3640 | AA35: 46058 | AB35: 75890577 | AC35: 3640 | AD35: 46087 | AE35: 56938363 | AF35: 4046 | AG35: 46118 | AH35: 87546213 | AI35: 3640 | AJ35: 46146 | AK35: 64175336 | AL35: =2000+1640 -> 3640 | AM35: 46178 | AN35: 22620137
H49: 13640
H50: 13640

Sheet MATRICULA
A1: =+'[1]2ºK'!B4 -> 0
B3: PREESCOLAR | E3: PRIMARIA | H3: SECUNDARIA | K3: BACHILLERATO
A5: 1ro | B5: =COUNTIF('1°K'!D8:D14,"*") -> 3 | E5: =COUNTIF('1°P'!D8:D23,"*") -> 15 | H5: =COUNTIF('1°S'!D8:D29,"*") -> 11 | K5: =COUNTIF('1-2°B'!D8:D24,"*") -> 0
A6: 2do | B6: =COUNTIF('2°K'!D8:D14,"*") -> 5 | E6: =COUNTIF('2°P'!D8:D28,"*") -> 20 | H6: =COUNTIF('2°S'!D8:D34,"*") -> 27 | O6: MATRICULA TOTAL
A7: 3ro | B7: =COUNTIF('3°K'!D8:D14,"*") -> 4 | E7: =COUNTIF('3° P'!D8:D34,"*") -> 24 | H7: =COUNTIF('3°S'!D8:D24,"*") -> 13 | K7: =COUNTIF('3-4°B'!D8:D25,"*") -> 0 | O7: =SUM(B11:M11) -> 170
A8: 4to | E8: =COUNTIF('4°P'!D8:D24,"*") -> 8
A9: 5to | E9: =COUNTIF('5°P'!D8:D25,"*") -> 16 | K9: 4
A10: 6to | E10: =COUNTIF('6°P'!D8:D31,"*") -> 20
A11: TOTAL | B11: =B5+B6+B7 -> 12 | E11: =SUM(E5:G10) -> 103 | H11: =SUM(H5:J7) -> 51 | K11: =SUM(K5:M10) -> 4

Sheet CONTROL FACTURACION
A2: FACTURAS
A3: FACTURA SI/NO | B3: NOMBRE DEL ALUMNO | C3: ULT FACT | D3: MONTO | E3: AGO | F3: SEPT | G3: OCT | H3: NOV | I3: DIC | J3: ENE | K3: FEB | L3: MAR | M3: ABR | N3: MAY | O3: JUN | P3: JUL | Q3: PADRE - FACTURA | S3: COMPL. FACT
A5: 1° PREESCOLAR
A6: SI | B6: ADRIAN GABRIEL CASTELLANOS VARGAS | C6: NUEVO INGRESO | D6: 2394 | F6: 3727 | G6: 3782 | H6: 3855 | I6: 3876 | J6: 4024 | K6: 4056 | L6: 4106 | M6: 4228 | N6: 4353 | O6: 4399 | Q6: CELSO ERIK LEOBARDO CASTELLANOS BANDALA | R6: COLEGIATURA (MES) CICLO 2025-2026 | S6: Complemento Inst. Educativas: Alumno - ADRIAN GABRIEL CASTELLANOS VARGAS CURP - CAVA221221HVZSRDA3 RFC - CABC760812PU7 Nivel Educativo - Preescolar autRVOE - PR
A7: SI | B7: ELIAS DANIEL CRUZ LOPEZ | C7: NUEVO INGRESO | D7: 2394 | F7: 3715 | G7: 3845 | H7: 3846 | I7: 3877 | J7: 4025 | K7: 4057 | L7: 4107 | M7: 4229 | N7: 4229 | O7: 4406 | Q7: GERMAIN CRUZ CLARA | R7: COLEGIATURA (MES) CICLO 2025-2026 | S7: Complemento Inst. Educativas: Alumno - ELIAS DANIEL CRUZ LOPEZ CURP - CULE220205HVZRPLA7 RFC - CUCG950530AB7 Nivel Educativo - Preescolar autRVOE - PRE/004/2015
A8: SI | B8: HELENA POBLETE PEÑA | C8: NUEVO INGRESO | D8: 1852 | F8: 3783 | G8: 3784 | H8: 3857 | I8: 3878 | J8: 4026 | K8: 4072 | L8: 4073 | M8: 4230 | N8: 4355 | O8: 4424 | Q8: EDITH GUADALUPE PEÑA SANCHEZ | R8: COLEGIATURA (MES) CICLO 2025-2026 | S8: Complemento Inst. Educativas: Alumno - HELENA POBLETE PEÑA CURP - POPH230212MVZBXLA9 RFC - PESE8812203R4 Nivel Educativo - Preescolar autRVOE - P
A10: 2° PREESCOLAR
A11: SI | B11: DANAE GARCÍA JIMÉNEZ | C11: NUEVO INGRESO | D11: 1995 | F11: 3792 | G11: 3793 | H11: 3829 | I11: 3880 | J11: 4027 | K11: 4058 | L11: 4082 | M11: 4231 | N11: 4303 | O11: 4400 | P11: 3881 | Q11: MARIELA JIMENEZ SANCHEZ | R11: COLEGIATURA (MES) CICLO 2025-2026 | S11: Complemento Inst. Educativas: Alumno - DANAE GARCIA JIMENEZ CURP - GAJD210201MVZRMNA8 RFC - JISM930304MK7 Nivel Educativo - Preescolar autRVOE - PRE/004/2015
B12: JOHANA CRUZ MURGIA | C12: NUEVO INGRESO | D12: 2223 | F12: 3743 | G12: 3780 | H12: 3859 | I12: 3879
A13: NO | B13: ='2°K'!D23 -> SARA ANALI CRUZ PORTILLA | O13: 4426 | Q13: ANA LUZ PORTILLA RODRIGUEZ | R13: COLEGIATURA (MES) CICLO 2025-2026 | S13: Complemento Inst. Educativas: Alumno - SARA ALANI CRUZ PORTILLA CURP - CUPS210115MVZRRRA7 RFC - Nivel Educativo - Preescolar autRVOE - PRE/004/2015
B14: ='2°K'!D25 -> AITANA REBECA FERNÁNDEZ CRUZ
A16: 3° PREESCOLAR
B17: CARLA SOFÍA JIMÉNEZ CRUZ | C17: 3447
A18: SI | B18: ELISA ABIGAIL ALONSO ZAMORA | C18: NUEVO INGRESO | D18: 2394 | F18: 3730 | G18: 3773 | H18: 3826 | I18: 3889 | J18: 4035 | K18: 4059 | L18: 4083 | M18: 4236 | N18: 4304 | O18: 4428 | P18: 3890 | Q18: JESSICA ZAMORA MENENDEZ | R18: COLEGIATURA (MES) CICLO 2025-2026 | S18: Complemento Inst. Educativas: Alumno - ELISA ABIGAIL ALONSO ZAMORA CURP - AOZE200822MVZLMLA3 RFC - ZAMJ840424KT4 Nivel Educativo - Preescolar autRVOE - PR
A19: SI | B19: NAYAN MARIN MARTINEZ | C19: 3427 | D19: 2565 | F19: 3896 | G19: 3897 | H19: 3898 | I19: 3899 | J19: 4028 | K19: 4060 | L19: 4108 | M19: 4237 | N19: 4305 | O19: 4429 | Q19: ADRIAN MARIN CASTILLO | R19: COLEGIATURA (MES) CICLO 2025-2026 | S19: Complemento Inst. Educativas: Alumno - NAYAN MARIN MARTINEZ CURP - MAMN200306MVZRRYA9 RFC - MACA910609454 Nivel Educativo - Preescolar autRVOE - PRE/004/2015
B20: KAI DE MARIA HERNADEZ ROMÁN | C20: 3603 | D20: 2794
A22: 1° PRIMARIA
A23: SI | B23: LIAM SAEL RAMIREZ PEREA | C23: 3270 | D23: 2623 | E23: 3759 | F23: 3760 | G23: 3797 CANCELADA / 3821 VIGENTE | H23: 3822 | I23: 3882 | J23: 4029 | K23: 4061 | L23: 4109 | M23: 4238 | N23: 4306 | O23: 4388 | P23: 3883 | Q23: KARLA MARGARITA PEREA GUZMAN | R23: COLEGIATURA (MES) CICLO 2025-2026 | S23: Complemento Inst. Educativas: Alumno - LIAM SAEL RAMIREZ PEREA CURP - RAPL190830HVZMRMA2 RFC - PEGK931224MB2 Nivel Educativo - Primaria autRVOE - PRI/004/2015
A24: SI | B24: ISABELLA GALVEZ DÍAZ | C24: NUEVO INGRESO | D24: 2879 | F24: 3884 | G24: 3885 | H24: 3886 | I24: 3887 | J24: 4036 | K24: 4062 | L24: 4110 | M24: 4239 | N24: 4307 | O24: 4389 | Q24: KAREN JACKELINE DIAZ RODRIGUEZ | R24: COLEGIATURA (MES) CICLO 2025-2026 | S24: Complemento Inst. Educativas: Alumno - ISABELLA GALVEZ DIAZ CURP - GADI190618MVZLZSA3 RFC - DIRK9505175H7 Nivel Educativo - Primaria autRVOE - PRI/004/2015
B25: GEORGINA FERNÁNDEZ THEUREL | C25: NUEVO INGRESO
B26: LILIAN RENATA CORTEZ FUENTES | C26: NUEVO INGRESO
B27: ANGEL SANTIAGO MENDOZA ORTEGA | C27: NUEVO INGRESO
B28: LIAM ZAMORANO HERNANDEZ | C28: NUEVO INGRESO
A29: SI FACTURA | B29: REGINA PEREYRA TOLEDO | C29: NUEVO INGRESO | D29: 2623 | E29: 3704 | F29: 3719 | G29: 3767 | H29: 3860 | I29: 3900 | J29: 4037 | K29: 4111 | L29: 4240 | M29: 4241 | N29: 4357 | O29: 4377 | P29: 3900 | Q29: CLAUDIA KARINA TOLEDO GUILLEN | R29: COLEGIATURA (MES) CICLO 2025-2026 | S29: Complemento Inst. Educativas: Alumno - REGINA PEREYRA TOLEDO CURP - PETR190917MVZRLGA3 RFC - TOGC9207286C1 Nivel Educativo - Primaria autRVOE - PRI/004/2015
A30: SI FACTURA | B30: ABRAHAM DE JESUS MONTERO GARCIA | C30: NUEVO INGRESO | D30: 1500 | J30: 4086 | K30: 4087 | L30: 4088 | M30: 4089 | N30: 4339 | O30: 4379 | Q30: CAROLINA DEL CARMEN GARCIA ORDOÑEZ | R30: COLEGIATURA (MES) CICLO 2025-2026 | S30: Complemento Inst. Educativas: Alumno - ABRAHAM DE JESUS MONTERO GARCIA CURP - MOGA190104HVZNRBA9 RFC - GAOC911029FW3 Nivel Educativo - Primaria autRVOE - PRI/004/2015
A31: SI | B31: IVANNA GARCIA RUIZ | C31: NUEVO INGRESO | D31: 2687 | F31: 3755 | G31: 3757 | H31: 3861 | I31: 3901 | J31: 4038 | K31: 4112 | L31: 4113 | M31: 4242 | N31: 4308 | O31: 4430 | Q31: JOSE IGNACIO GARCIA TORRES | R31: COLEGIATURA (MES) CICLO 2025-2026 | S31: Complemento Inst. Educativas: Alumno - IVANNA GARCIA RUÍZ CURP - GARI191129MVZRZVA3 RFC - GATI800420AM5 Nivel Educativo Primaria autRVOE - PRI/004/2015
A32: SI | B32: MATIAS SAUL RIVAS GRAJEDA | C32: 3615 | D32: 2686 | F32: 3741 | G32: 3998 | H32: 3999 | I32: 4114 | J32: 4115 | K32: 4116 | L32: 4117 | M32: 4243 | N32: 4309 | O32: 4431 | Q32: ADRIANA GRAJEDA AGUIRRE | R32: COLEGIATURA (MES) CICLO 2025-2026 | S32: Complemento Inst. Educativas: Alumno - MATIAS SAUL RIVAS GRAJEDA CURP - RIGM190113HCSVRTA9 RFC - GAAA910506L20 Nivel Educativo - Primaria autRVOE - PRI/004/2015
B33: AKANE MORALES ROMAN | C33: NUEVO INGRESO
A36: 2° PRIMARIA
B37: OSWALDO LOPEZ FONSECA | C37: 3195 | D37: 2600 | E37: 3711 | F37: 3711 | G37: 3891 | H37: NO FACTURÓ | I37: 3892 | J37: 3892 | K37: 3970 | L37: 4361 | M37: 4361 | N37: 4361
A38: SI FACTURA | B38: CESAR BENHUR CASTAN OVANDO | C38: 3634 | D38: 2879 | F38: 3712 | G38: 3800 | H38: 3904 | I38: 3905 | J38: 3906 | K38: 4118 | L38: 4119 | M38: 4120 | N38: 4310 | O38: 4376 | Q38: MONTSERRAT CASTAN OVANDO | R38: COLEGIATURA (MES) CICLO 2025-2026 | S38: Complemento Inst. Educativas: Alumno - CESAR BENHUR CASTAN OVANDO CURP - CAOC181107HVZSVSA4 RFC - CAOM880602P13 Nivel Educativo - Primaria autRVOE - PRI/004/2015
B39: NATHALIA ITZAÉ JIMÉNEZ CRUZ | C39: 3449
A40: SI FACTURA | B40: DOMINIC GUSTAVO NIVON OROZCO | C40: 3639 | D40: 2559 | F40: 3734 | G40: 3801 | H40: 3830/3907 SE DUPLICÓ | I40: 3908 | J40: 3908 | K40: 4121 | L40: 4122 | M40: 4244 | N40: 4311 | O40: 4380 | P40: 3908 | Q40: CARLA KATANIA OROZCO TORRES | R40: COLEGIATURA (MES) CICLO 2025-2026 | S40: Complemento Inst. Educativas: Alumno - DOMINIC GUSTAVO NIVON OROZCO CURP - NIOD180813HVZVRMA8 RFC - OOTC910112M48 Nivel Educativo - Primaria autRVOE - PRI/004/2015
A41: SI FACTURA | B41: LUIS MARIO HERNANDEZ VARGAS | C41: 3271 | D41: 2239 | F41: 3750 | G41: 3909 | H41: 3910 | I41: 4016 | J41: 4017 | N41: 4360 | Q41: EDGAR MARIO HERNANDEZ MORENO | R41: COLEGIATURA (MES) CICLO 2025-2026 | S41: Complemento Inst. Educativas: Alumno - LUIS MARIO HERNÁNDEZ VARGAS CURP - HEVL181028HVZRRSA2 RFC - HEME8708202F8 Nivel Educativo - Primaria autRVOE - PRI/004/2015
A42: SI FACTURA | B42: ROMINA RODRIGUEZ PEREZ | C42: 3227 | D42: 2879 | F42: 3802 | G42: 3803 | H42: 3865 | I42: 3911 | J42: 4039 | K42: 4123 | L42: 4124 | M42: 4245 | N42: 4362 | O42: 4433 | Q42: ESTEFANIA PEREZ VALLES | R42: COLEGIATURA MES ABRIL DEL CICLO ESCOLAR 2025-2026 | S42: Complemento Inst. Educativas: Alumno - ROMINA RODRIGUEZ PEREZ CURP - ROPR180105MVZDRMA2 RFC - ROPV890812HS0 Nivel Educativo - Primaria autRVOE - PRI/004
A43: SI FACTURA | B43: JOSE MIGUEL CRUZ LOPEZ | C43: 3654 | D43: 2687.6 | F43: 3714 | G43: 3843 | H43: 3844 | I43: 3912 | J43: 4040 | K43: 4125 | L43: 4126 | M43: 4246 | N43: 4312 | O43: 4407 | Q43: GERMAIN CRUZ CLARA | R43: COLEGIATURA (MES) CICLO 2025-2026 | S43: Complemento Inst. Educativas: Alumno - JOSÉ MIGUEL CRUZ LÓPEZ CURP - CULM180517HVZRPGA7 RFC - CUCG950530AB7 Nivel Educativo - Primaria autRVOE - PRI/004/2015
A44: SI FACTURA | B44: INGRID PATRICIA GUZMAN SANTIAGO | C44: NUEVO INGRESO | D44: 2559 | F44: 3913 | G44: 4005 | H44: 4006 | I44: 4007 | J44: 4022 | K44: 4127 | L44: 4128 | M44: 4247 | N44: 4313 | O44: 4410 | P44: 4008 | Q44: INGRID SANTIAGO OJEDA | R44: COLEGIATURA (MES) CICLO 2025-2026 | S44: Complemento Inst. Educativas: Alumno - INGRID PATRICIA GUZMAN SANTIAGO CURP - GUSI180914MVZZNNA1 RFC - SAOI8507298P4 Nivel Educativo - Primaria autRVOE - PRI/004/2015
B45: ABIGAIL GARCIA MARTINEZ | C45: 3585
A46: ABRIL ESMERALDA NIETO VASCONCELOS | B46: EMMA SOFIA DOMINGUEZ NIETO | C46: NUEVO INGRESO | D46: 2878 | F46: 3729 | G46: 3804 | H46: 3820 | I46: 3914 | J46: 4041 | K46: 4129 | L46: 4130 | M46: 4248 | N46: 4314 | O46: 4434 | Q46: ABRIL ESMERALDA NIETO VASCONCELOS | R46: COLEGIATURA (MES) CICLO 2025-2026 | S46: Complemento Inst. Educativas: Alumno - EMMA SOFIA DOMINGUEZ NIETO CURP - DONE180320MVZMTMA0 RFC - NIVA840415QL0 Nivel Educativo - Primaria autRVOE - PRI/004/2015
A47: SI FACTURA | B47: MATIAS ALEJANDRO PEREZ REYES | C47: 3687 | D47: 2687 | E47: 3807 | F47: 3763 | G47: 3805 | H47: 3828 | I47: 3915 | J47: 4033 | K47: 4067 | L47: 4084 | M47: 4249 | N47: 4315 | O47: 4435 | Q47: CORPORATIVO CONTABLE Y FISCAL BRP | R47: COLEGIATURA (MES) CICLO 2025-2026 | S47: Complemento Inst. Educativas: Alumno - PEREZ REYES MATIAS ALEJANDRO CURP - PERM180827HVZRYTA1 RFC - CCF210318PP4 Nivel Educativo - Primaria autRVOE - PRI/004/2015
B48: JARED ALEXANDER FUENTES GARCIA | C48: 3659
A49: SI FACTURA | B49: VALENTINA MARTINEZ | C49: 3628 | D49: 2399 | H49: 3916 | I49: 3917 | J49: 4042 | K49: 4131 | L49: 4132 | M49: 4250 | N49: 4332 | Q49: REBECA RODRIGUEZ GARCIA | R49: COLEGIATURA (MES) CICLO 2025-2026 | S49: Complemento Inst. Educativas: Alumno - VALENTINA MARTINEZ RODRIGUEZ CURP - MARV181219MVZRDLA2 RFC - ROGR810920664 Nivel Educativo - Primaria autRVOE - PRI/004/2015
B50: CARLOS DANIEL TRUJILLO RODRIGUEZ | L50: 4343 | O50: 4415 | Q50: MARIA GUADALUPE DEL PILAR RODRIGUEZ CASTILLO | R50: COLEGIATURA (MES) CICLO 2025-2026 | S50: Complemento Inst. Educativas: Alumno - CARLOS DANIEL TRUJILLO RODRIGUEZ CURP - TURC180305HSRRDRA6 RFC - ROCG8504197Y8 Nivel Educativo - Primaria autRVOE - PRI/004/2015
B51: JHONATAN DE JESUS SALINAS TOLEDO
B52: JEAN CARLO RICARDEZ VEGA
A54: 3° PRIMARIA
A55: SI FACTURA | B55: KAORU HIGASHI ALCANTARA | F55: 3918 | G55: 3918 | H55: 3918 | I55: 3918 | J55: 3918 | K55: 3918 | L55: 3918 | M55: 3918 | N55: 3918 | O55: 3918 | P55: 3918
B56: AGNES DANIELLE JIMENEZ CALDERON | C56: NUEVO INGRESO
A57: SI FACTURA | B57: CESAR MATEO CRUZ LANDA | C57: 3283 | D57: 2559 | E57: 3722 | F57: 3723 | G57: 3809 | H57: 3866 | I57: 3919 | J57: 4049 | K57: 4069 | L57: 4133 | M57: 4251 | N57: 4316 | O57: 4404 | P57: 3920 | Q57: CESAR ARTURO CRUZ GUZMAN | R57: COLEGIATURA (MES) CICLO 2025-2026 | S57: Complemento Inst. Educativas: Alumno - CRUZ LANDA CESAR MATEO CURP - CULC170201HVZRNSA0 RFC - CUGC840908UR3 Nivel Educativo - Primaria Primaria autRVOE - PRI/004/2015
B58: THIAGO ALFONSO FUENTES | C58: NUEVO INGRESO | D58: 2239 | F58: 3922 | G58: 3923 | H58: 3924 | I58: 3925 | J58: 4134 | K58: 4135 | L58: 4136 | M58: 4252 | N58: 4317 | O58: 4437 | Q58: EDUARDO ALFONSO MARTINEZ | R58: COLEGIATURA (MES) CICLO 2025-2026 | S58: Complemento Inst. Educativas: Alumno - THIAGO ALFONSO FUENTES CURP - AOFT170512HVZLNHA3 RFC - AOME941002AD5 Nivel Educativo - Primaria autRVOE - PRI/004/2015
B59: ISABELLA FERNANDA PÉREZ | C59: NUEVO INGRESO | L59: 4416 | M59: 4417 | N59: 4418 | O59: 4419 | Q59: RIGOBERTO GARDUZA DE LA CRUZ | R59: COLEGIATURA (MES) CICLO 2025-2026 | S59: Complemento Inst. Educativas: Alumna - ISABELLA FERNANDA PEREZ VELAZQUEZ CURP - PEVI170125MVZRLSA4 RFC - GACR771202773 Nivel Educativo - Primaria autRVOE - PRI/004/2015
A60: SI FACTURA | B60: ASIEL ROQUE FUENTES | C60: 3595 | D60: 3071 | F60: 3716 | G60: 3810 | H60: 3867 | I60: 3926 | J60: 4050 | K60: 4070 | L60: 4137 | M60: 4253 | N60: 4318 | O60: 4409 | Q60: AARON ASIEL ROQUE URBANO | R60: COLEGIATURA (MES) CICLO 2025-2026 | S60: Complemento Inst. Educativas: Alumno - ASIEL ROQUE FUENTES CURP - ROFA170116HVZQNSA1 RFC - FUOA8704234S2 Nivel Educativo - Primaria autRVOE - PRI/004/2015
A61: SI FACTURA | B61: ALEXANDRO VIDAL APOLINAR VELAZQUEZ | C61: 3409 | E61: 3702 | F61: 3702 | G61: 3702 | H61: 3702 | I61: 3702 | J61: 3702 | K61: 4064 | L61: 4064 | M61: 4064 | N61: 4064 | O61: 4064 | P61: 4064
A62: SI FACTURA | B62: AZAEL BAILON CANCINO | C62: 3691 | D62: 2686 | F62: 3753 | G62: 3768 | H62: 3853 | I62: 3927 | J62: 4055 | K62: 4138 | L62: 4139 | M62: 4254 | N62: 4319 | O62: 4405 | Q62: LORENA CANCINO CRUZ | R62: COLEGIATURA (MES) CICLO 2025-2026 | S62: Complemento Inst. Educativas: Alumno - AZAEL BAYLON CANCINO CURP - BXCA170923HVZYNZA0 RFC - CACL780721FCA Nivel Educativo - Primaria autRVOE - PRI/004/2015
B63: MATEO CRUZ PORTILLA | C63: NUEVO INGRESO | O63: 4427 | Q63: ANA LUZ PORTILLA RODRIGUEZ | R63: COLEGIATURA (MES) CICLO 2025-2026 | S63: Complemento Inst. Educativas: Alumno - MATEO CRUZ PORTILLA CURP - CUPM170126HVZRRTA3 RFC - Nivel Educativo - Primaria autRVOE - PRI/004/2015
B64: DEREK ABDIEL PECH SANTIAGO | C64: NUEVO INGRESO
B65: DIEGO LARA BARRERA | M65: pag | N65: pag
A66: SI FACTURA | B66: SEBASTIAN CARRASCO RAMIREZ | C66: 3689 | D66: 2239 | F66: 3725 | G66: 3770 | H66: 3837 | I66: 3928 | J66: 4047 | K66: 4074 | L66: 4075 | M66: 4255 | N66: 4321 | O66: 4438 | Q66: MIGUEL ANGEL CARRASCO PEREZ | R66: COLEGIATURA (MES) CICLO 2025-2026 | S66: Complemento Inst. Educativas: Alumno - CARRASCO RAMIREZ SEBASTIAN CURP - CARS171130HVZRMBA6 RFC - CAPM790321FI4 Nivel Educativo - Primaria autRVOE - PRI/004/2015
A67: SI FACTURA | B67: JOSUE VALENCIA OCAMPO | C67: NUEVO INGRESO | D67: 2686 | F67: 4090 | G67: 4091 | H67: 4092 | I67: 4093 | J67: 4094 | K67: 4095 | L67: 4096 | M67: 4097 | N67: 4324 | O67: 4440 | Q67: TANIA OCAMPO LOPEZ | R67: COLEGIATURA (MES) CICLO 2025-2026 | S67: Complemento Inst. Educativas: Alumno - JOSUE VALENCIA OCAMPO CURP - VAOJ170107HVZLCSA4 RFC - OALT920215RW5 Nivel Educativo - Primaria autRVOE - PRI/004/2015
A68: SI FACTURA | B68: JUAN SEBASTIAN PEREZ SANTOS | C68: 3697
A69: SI FACTURA | B69: GABRIEL ARRIAGA PEREZ | C69: NUEVO INGRESO | D69: 2399.25 | E69: 3706 | F69: 3707 | G69: 3765 | H69: 3839 | I69: 3929 | J69: 4048 | K69: 4140 | L69: 4141 | M69: 4256 | N69: 4326 | O69: 4378 | P69: 4011 | Q69: LUIS ALBERTO ARRIAGA OLALDE | R69: COLEGIATURA (MES) CICLO 2025-2026 | S69: Complemento Inst. Educativas: Alumno - Gabriel Arriaga Perez CURP - AIPG170921HVZRRBA4 RFC - AIOL8801243P7 Nivel Educativo - Primaria autRVOE - PRI/004/2015
B70: CLAUDIA MARIA CASTRO CAMACHO | C70: NUEVO INGRESO | N70: pag | O70: PAG
A71: SI FACTURA | B71: LIAM HANIEL ROBLES LIMON | C71: 3231 | D71: 2400 | E71: 3849 | F71: 3850 | G71: 3851 | H71: 3852 | I71: 3930 | J71: 4142 | K71: 4143 | L71: 4144 | M71: 4257 | N71: 4327 | Q71: KARINA GUADALUPE LIMON DIAZ | R71: COLEGIATURA (MES) CICLO 2025-2026 | S71: Complemento Inst. Educativas: Alumno - LIAM HANIEL ROBLES LIMON CURP - ROLL170726HVZBMMA9 RFC - LIDK8801286S8 Nivel Educativo - Primaria autRVOE - PRI/004/2015
B72: DIANA MARTINEZ MENDOZA | C72: NUEVO INGRESO | D72: 2239 | F72: 3778 | G72: 3779 | H72: 3931 | I72: 3932 | J72: 4145 | K72: 4146 | L72: 4147 | M72: 4258 | N72: 4296 | O72: 4411 | P72: 3933 | Q72: GENARO MARTINEZ TOLEDO | R72: COLEGIATURA (MES) CICLO 2025-2026 | S72: Complemento Inst. Educativas: Alumno - DIANA MARTINEZ MENDOZA CURP - MAMD170819MVZRNNA6 RFC - MATG8305184H6 Nivel Educativo - Primaria autRVOE - PRI/004/2015
A73: SI FACTURA | B73: ATENEA ALESSANDRA USCANGA TOLEDO | C73: NUEVO INGRESO | N73: pag | O73: PAG
B74: KAREN ITZEL VÉLAZQUEZ JIMENEZ | C74: NUEVO INGRESO
A75: SI FACTURA | B75: MARCELO IVAN CRUZ GARCIA | C75: 3276 | D75: 2623 | F75: 3790 | G75: 3791 | H75: 4014 | I75: 4015 | J75: 4015 | K75: 4148 | L75: 4149 | M75: 4259 | N75: 4323 | P75: 4015 | Q75: PAMELA COSTALES TIBURCIO | R75: COLEGIATURA (MES) CICLO 2025-2026 | S75: Complemento Inst. Educativas: Alumno - MARCELO IVAN GARCIA CRUZ CURP - GACM170209HVZRRRA0 RFC - COTP851202G93 Nivel Educativo - Primaria autRVOE - PRI/004/2015
A77: 4° PRIMARIA
A78: SI FACTURA | B78: EMIR ELÍAS GUZMÁN POSADAS | C78: 3450 | D78: 2559 | E78: 3710 | F78: 3746 | G78: 3789 | H78: 3934 | I78: 3935 | J78: 4043 | K78: 4063 | L78: 4076 | M78: 4260 | N78: 4333 | O78: 4442 | Q78: TOMASA POSADAS VILLANUEVA | R78: COLEGIATURA (MES) CICLO 2025-2026 | S78: Complemento Inst. Educativas: Alumno - EMIR ELÍAS GUZMÁN POSADAS CURP - GUPE161126HVZZSMA2 RFC - POVT770721GG6 Nivel Educativo - Primaria autRVOE - PRI/004/2015
A79: SI FACTURA | B79: MARIA ESTHER HERNANDEZ VARGAS | C79: 3272 | D79: 2239 | F79: 3751 | G79: 4018 | H79: 4019 | I79: 4020 | J79: 4021 | K79: 4261 | L79: 4262 | M79: 4263 | N79: 4334 | O79: 4408 | Q79: EDGAR MARIO HERNANDEZ MORENO | R79: COLEGIATURA (MES) CICLO 2025-2026 | S79: Complemento Inst. Educativas: Alumno - MARÍA ESTHER HERNÁNEZ VARGAS CURP - HEVE160818MVZRRSA7 RFC - HEME8708202F8 Nivel Educativo - Primaria autRVOE - PRI/004/2015
A80: SI FACTURA | B80: ALANA XIMENA CASTILLO ABREU | C80: NUEVO INGRESO | D80: 2879 | F80: 3834 | G80: 3835 | H80: 3836 | I80: 3940 | J80: 4150 | K80: 4151 | L80: 4152 | M80: 4264 | N80: 4363 | O80: 4443 | Q80: JUANA YOLANDA ABREU PEREZ | R80: COLEGIATURA (MES) CICLO 2025-2026 | S80: Complemento Inst. Educativas: Alumno - ALANA XIMENA CASTILLO ABREU CURP - CAAA160311MVZSBLA2 RFC - AEPJ951103QHA Nivel Educativo - Primaria autRVOE - PRI/004/2015
B81: FRANCISCO MALIK HEREDIA DOMÍNGUEZ | C81: 3663
B82: JOSE MARIA MARTINEZ TADEO | C82: NUEVO INGRESO | F82: 4232 | G82: 4233 | H82: 4234 | I82: 4071 | J82: 4071 | K82: 4071 | L82: 4235
B83: MIRANDA REYES ESCOBAR | C83: 3681 | D83: 2680 | F83: 3936 | G83: 3937
B84: CONSTANZA REYES ESCOBAR | C84: 3679 | D84: 2680 | F84: 3938 | G84: 3939
A86: 5° PRIMARIA
A87: SI FACTURA | B87: DERECK BONILLA MARTINEZ | C87: 3641 | D87: 2879 | F87: 3709 | G87: 3813 | H87: 3868 | I87: 3941 | N87: 4297 | O87: 4385 | P87: Ya no factura | Q87: PABLO BONILLA DELGADO | R87: COLEGIATURA (MES) CICLO 2025-2026 | S87: COLEGIATURA DEL MES DE MAYO CICLO ESCOLAR 2025-2026. Complemento Inst. Educativas: Alumno - DEREK YAHIR BONILLA MARTINEZ CURP - OMD151107HVZNRRA8 RFC - MAOP8902255G3 Nivel Educativo - Primaria aut RVOE - PRI/004/2015
A88: SI FACTURA | B88: RODRIGO SORIANO LAVÍN | C88: 3673 | D88: 2686 | F88: 3736 | G88: 3814 | H88: 3869 | I88: 3942 | J88: 4044 | K88: 4155 | L88: 4156 | M88: 4157 | N88: 4364 | O88: 4401 | Q88: JAVIER SORIANO KURI | R88: COLEGIATURA MES ABRIL CICLO 2025-2026 | S88: Complemento Inst. Educativas: Alumno - RODRIGO SORIANO LAVÍN CURP - SOLR150617HVZRVDA6 RFC - SOKJ7410219Z7 Nivel Educativo - Primaria autRVOE - PRI/004/2015
A89: SI FACTURA | B89: RAUL MANUEL HAMILTON ARIAS | C89: 3666 | D89: 2879 | F89: 3943 | G89: 3944 | H89: 3945
A90: SI FACTURA | B90: TANIA ALEXA SALVADOR MARTINEZ | C90: NUEVO INGRESO | D90: 2687 | E90: 3498 | F90: 3776 | G90: 3796 | H90: 3870 | I90: 3946 | J90: 4051 | K90: 4158 | L90: 4265 | M90: 4266 | N90: 4367 | O90: 4368 | Q90: JORGE ALBERTO SALVADOR MARQUEZ
A91: SI FACTURA | B91: ANGEL MATEO VELAZQUEZ GARCIA | C91: 3287 | D91: 2240 | E91: 3717 | F91: 3718 | G91: 3847 | H91: 3848 | I91: 3947 | J91: 4159 | K91: 4160 | L91: 4161 | M91: 4267 | N91: 4369 | O91: 4446 | P91: 3948 | Q91: MARTHA ELBA GARCIA MUMENTHEY | R91: GAMM7507299A6 | S91: Complemento Inst. Educativas: Alumno - VELAZQUEZ GARCIA ANGEL MATEO CURP - VEGA150317HVZLRNA3 RFC - GAMM7507299A6 Nivel Educativo - Primaria autRVOE - PRI/004/2015
A92: SI FACTURA | B92: MAXIMILIANO CISNEROS VILLEGAS | C92: 3651 | D92: 3071 | F92: 3949 | G92: 3950 | H92: 3951 | I92: 3952 | J92: 4162 /4328 | K92: 4163/4329 | L92: 4164/4330 | M92: 4164/4330 | N92: 4300/4331 | O92: 4381 | Q92: KARLA NAYELI VILLEGAS MARTINEZ | R92: COLEGIATURA MES ABRIL CICLO 2025-2026 | S92: Complemento Inst. Educativas: Alumno - MAXIMILIANO CISNEROS VILLEGAS CURP - CIVM150724HVZSLXA7 RFC - CIGM850910BR6 Nivel Educativo - Primaria autRVOE - PRI/004/2015
B93: GISSEL ADHARA LOPEZ CRUZ | C93: NUEVO INGRESO
A94: SI FACTURA | B94: ANGEL MATHIAS CARRASCO RAMIREZ | C94: 3690 | D94: 2239 | F94: 3726 | G94: 3771 | H94: 3838 | I94: 3953 | J94: 4046 | K94: 4077 | L94: 4078 | M94: 4268 | N94: 4322 | O94: 4439 | Q94: MIGUEL ANGEL CARRASCO PEREZ | R94: COLEGIATURA (MES) CICLO 2025-2026 | S94: Complemento Inst. Educativas: Alumno - CARRASCO RAMIREZ ANGEL MATHIAS CURP - CARA150831HVZRMNA7 RFC - CAPM790321FI4 Nivel Educativo - Primaria autRVOE - PRI/004/2015
A95: SI FACTURA | B95: YESHUA FERNANDO VALENCIA OCAMPO | C95: NUEVO INGRESO | D95: 2686 | F95: 4098 | G95: 4099 | H95: 4100 | I95: 4101 | J95: 4102 | K95: 4103 | L95: 4104 | M95: 4105 | N95: 4325 | O95: 4441 | Q95: TANIA OCAMPO LOPEZ | R95: COLEGIATURA (MES) CICLO 2025-2026 | S95: Complemento Inst. Educativas: Alumno - YESHUA FERNANDO VALENCIA OCAMPO CURP - VAOY150108HVZLCSA1 RFC - OALT920215RW5 Nivel Educativo - Primaria autRVOE - PRI/004/2015
A96: SI FACTURA | B96: DANIELA MICHELLE ULIN GARCIA | C96: 3506 | D96: 3147 | F96: 4009 | G96: 4009 | Q96: DANIELA EUGENIA MARTINEZ BRAVO | R96: COLEGIATURA SEPTIEMBRE DEL CICLO ESCOLAR 2025-2026 | S96: Complemento Inst. Educativas: Alumno - DANIELA MICHELLE ULIN MARTINEZ CURP - UIMD151104MVZLRNA9 RFC - MABD810411U81 Nivel Educativo - Primaria autRVOE - PRI/004/2015
A97: SI FACTURA | B97: VALENTINA GARCIA RUIZ | C97: NUEVO INGRESO | D97: 2687 | F97: 3756 | G97: 3758 | H97: 3862 | I97: 3954 | J97: 4045 | K97: 4165 | L97: 4166 | M97: 4269 | N97: 4447 | Q97: JOSE IGNACIO GARCIA TORRES | R97: COLEGIATURA SEPTIEMBRE DEL CICLO ESCOLAR 2025-2026 | S97: Complemento Inst. Educativas: Alumno - GARCIA RUIZ VALENTINA CURP - GARV150316MVZRZLA5 RFC - GATI800420AM5 Nivel Educativo - Primaria autRVOE - PRI/004/2015
A98: sin factura | B98: CARMEN GABRIELA DE LEÓN REYES | C98: NUEVO INGRESO | N98: pag
A99: SI FACTURA | B99: BETZABE PEREZ REYES | C99: 3688 | D99: 2687 | E99: 3808 | F99: 3764 | G99: 3806 | H99: 3827 | I99: 3921 | J99: 4034 | K99: 4068 | L99: 4085 | M99: 4270 | N99: 4270 | O99: 4436 | Q99: CORPORATIVO CONTABLE Y FISCAL BRP | R99: COLEGIATURA (MES) CICLO 2025-2026 | S99: Complemento Inst. Educativas: Alumno - PEREZ REYES BETZABE DEL ROSARIO CURP - PERB150905MVZRYTA2 RFC - BCA170725A94 Nivel Educativo - Primaria autRVO
B100: GUILLERMO MIKAEL CHAVEZ | C100: 3686
A104: 6° PRIMARIA
A105: SI FACTURA | B105: JOSÉ GABRIEL TRUJILLO RAMÍREZ | C105: 3667 | D105: 2686 | F105: 3738 | G105: 3798 | H105: 3863 | I105: 3902 | J105: 4167 | K105: 4168 | L105: 4169 | M105: 4271 | N105: 4345 | O105: 4414 | Q105: MARIA GUADALUPE DEL PILAR RODRIGUEZ CASTILLO | R105: COLEGIATURA (MES) CICLO 2025-2026 | S105: Complemento Inst. Educativas: Alumno - TRUJILLO RODRIGUEZ JOSE GABRIEL CURP - TURG140528HJCRDBA6 RFC - ROCG8504197Y8 Nivel Educativo - Primaria autRVOE - PRI/004/2015
B106: MEREDITH PAOLA LINARES LIMON | C106: 3575 | D106: 2879 | F106: 3713 | G106: 3816 | H106: 3871 | I106: 3955 | J106: 4170 | K106: 4171 | L106: 4172 | M106: 4272 | N106: 4336 | O106: 4449 | Q106: TANIA FABIOLA LIMON DIAZ | R106: COLEGIATURA (MES) CICLO 2025-2026 | S106: Complemento Inst. Educativas: Alumno - MEREDITH PAOLA LINARES LIMON CURP - LILM140112MVZNMRA2 RFC - LIDT860218CR6 Nivel Educativo - Primaria autRVOE - PRI/004/2015
B107: ERENDIRA DANAE SANTIAGO MARTINEZ | C107: NUEVO INGRESO | D107: 2239 | E107: 3698 | F107: 3732 | G107: 3786 | H107: 3825 | I107: 3893 | J107: 4031 | K107: 4173 | L107: 4174 | M107: 4273 | N107: 4370 | O107: 4397 | P107: 3894 | Q107: HECTOR SANTIAGO HERNANDEZ | R107: COLEGIATURA (MES) CICLO 2025-2026 | S107: Complemento Inst. Educativas: Alumno - ERENDIRA DANAE SANTIAGO MARTINEZ CURP - SAME141207MVZNRRA6 RFC - SAHH660727BK2 Nivel Educativo - Primaria autRVOE - PRI/004/2015
B108: LEOBARDO CASTELLANOS VARGAS | C108: NUEVO INGRESO | D108: 2686 | F108: 3728 | G108: 3781 | H108: 3856 | I108: 3956 | J108: 4053 | K108: 4175 | L108: 4176 | M108: 4274 | N108: 4354 | O108: OK | Q108: CELSO ERIK LEOBARDO CASTELLANOS BANDALA | R108: COLEGIATURA ABRIL CICLO 2025-2026 | S108: Complemento Inst. Educativas: Alumno - ERIK LEOBARDO CASTELLANOS VARGAS CURP - CAVE140330HVZSRRA6 RFC - CABC760812PU7 Nivel Educativo - Primaria autRVOE
A109: SI FACTURA | B109: IMELDA MARTINEZ RUIZ | C109: NUEVO INGRESO | D109: 2559 | F109: 3735 | G109: 3840 | H109: 3841 | I109: 3957 | J109: 4030 | K109: 4177 | L109: 4178 | M109: PEND VERIF REG | P109: 3957 | Q109: LUZ DEL CARMEN RUIZ HERNANDEZ | R109: COLEGIATURA ABRIL CICLO 2025-2026 | S109: Complemento Inst. Educativas: Alumno - IMELDA MARTINEZ RUIZ CURP - MARI140509MVZRZMA8 RFC - RUHL781013HPA Nivel Educativo - Primaria autRVOE - PRI/004/2015
A110: SI FACTURA | B110: VLADIMIR BAILON CANCINO | C110: 3692 | D110: 2686 | F110: 3754 | G110: 3769 | H110: 3854 | I110: 3958 | J110: 4054 | K110: 4179 | L110: 4180 | M110: 4275 | N110: 4320 | O110: 4386 | Q110: LORENA CANCINO CRUZ | R110: COLEGIATURA (MES) CICLO 2025-2026 | S110: Complemento Inst. Educativas: Alumno - VLADIMIR BAYLON CANCINO CURP - BACV140206HVZYNLA2 RFC - CACL780721FCA Nivel Educativo - Primaria autRVOE - PRI/004/2015
B111: PEREZ CRUZ LIA KARIME | C111: NUEVO INGRESO | D111: 2879 | F111: 3748 | G111: 3752 | H111: 3819 | I111: 3819 | J111: 3819 | K111: 3819 | L111: 3819 | M111: 3819 | N111: 3819 | O111: 4371 | Q111: JUANA CRUZ VILLALOBOS | R111: COLEGIATURA (MES) CICLO 2025-2026 | S111: Complemento Inst. Educativas: Alumno - LIA KARIME PEREZ CRUZ CURP - PECL141019MVZRRXA8 RFC - CUVJ850512D1A Nivel Educativo - Primaria autRVOE - PRI/004/2015
A112: SI FACTURA | B112: CAMACHO ORDAZ JAZMIN | C112: NUEVO INGRESO | D112: 2879 | F112: 3747 | G112: 3817 | H112: 3872 | I112: 3959 | J112: 4013 | K112: 4181 | L112: 4182 | M112: 4183 | N112: 4348 | O112: 4390 | Q112: MONICA BERENICE ORDAZ HERNANDEZ | R112: COLEGIATURA ABRIL DEL CICLO ESCOLAR 2025-2026 | S112: Complemento Inst. Educativas: Alumno - JAZMIN CAMACHO ORDAZ CURP - CAOJ140406MVZMRZA9 RFC - OAHM800721C23 Nivel Educativo - Primaria autRVOE - PRI/004/2015
A113: SI FACTURA | B113: CALEB SOTO ACOSTA | C113: NUEVO INGRESO | D113: 2879 | F113: 3731 | G113: 3818 | H113: 3873 | I113: 3960 | J113: 4184 | K113: 4185 | L113: 4186 | M113: 4276 | N113: 4349 | O113: 4450 | Q113: JORGE ALBERTO SOTO TRINIDAD | R113: COLEGIATURA ABRIL DEL CICLO ESCOLAR 2025-2026 | S113: Complemento Inst. Educativas: Alumno - CALEB SOTO ACOSTA CURP - SOAC141018HVZTCLA6 RFC - SOTJ840416DW4 Nivel Educativo - Primaria autRVOE - PRI
...

Sheet ADEUDOS
B2: ADEUDOS PENDIENTES
C3: FEBRERO | D3: MARZO | E3: ABRIL | F3: MAYO | G3: JUNIO | H3: OBSERVACIÓN
B4: 3RO PRESCOLAR
B5: CARLA SOFÍA JIMÉNEZ CRUZ | E5: 2052 | G5: 2052
B6: KAI DE MARIA HERNANDEZ ROMAN | F6: 2790 | G6: 2790
B8: 1ER PRIMARIA
B9: GEORGINA FERNÁNDEZ THEUREL | G9: 2399
B10: KHATERIN AMAIA MORALES DOMINGUEZ | G10: 2686
B12: 2DO PRIMARIA
B13: OSWALDO LOPEZ FONSECA | E13: 800 | F13: 2600 | G13: 2600
B14: NATHALIA ITZAÉ JIMÉNEZ CRUZ | E14: 2302 | G14: 2302
B15: ANGEL DE JESUS ARRONIZ CALZADA | G15: 2798
B16: ANDRES VEGA CAPORAL | G16: 2287
B18: 3RO PRIMARIA
B19: ='3° P'!D44 -> AGNES DANIELLE JIMENEZ CALDERON | E19: 2686 | G19: 2686
B20: LUIS EDUARDO GUITARTH MARTINEZ | E20: 2686
B21: ='3° P'!D65 -> KAREN ITZEL VÉLAZQUEZ JIMENEZ | E21: 2686 | F21: 2686 | G21: 2686
B23: 4TO PRIMARIA
B24: ='4°P'!D34 -> EMILIANO NARVAEZ MARTINEZ | G24: 2239
B25: ='4°P'!D37 -> JOSE MARIA MARTINEZ TADEO | F25: 2683 | G25: 2623
B26: MIRANDA REYES ESCOBAR | F26: 2680 | G26: 2680
B27: CONSTANZA REYES ESCOBAR | F27: 2680 | G27: 2680
B29: 5TO PRIMARIA
B30: RAUL MANUEL HAMILTON ARIAS | G30: 2879
B32: 6TO PRIMARIA
B33: VALERIA MORENO GERMAN | E33: 2200 | F33: 2200 | G33: 2200
B34: RODRIGO EMMANUEL SANCHEZ DOMINGUEZ | G34: 2395
B36: 1RO SECUNDARIA
B37: JOEL BARZILAI JIMENEZ AGUIRRE | F37: 2874 | G37: 2874 | H37: CONVENIO
B38: ='1°S'!D48 -> KENDRA ALEXANDRA PEREZ CRUZ | G38: 2309
B40: 2DO SECUNDARIA
B41: NAIM JIMENEZ DOMINGUEZ | F41: 2890 | G41: 2890
B42: NOE DAVID GARCIA NELSON | F42: 2846 | G42: 2846
B43: ='2°S'!D55 -> ADA MARIA TORRES JUAREZ | G43: 2240
B44: XIMENA GARDUZA LIMÓN | E44: 2569 | F44: 2569 | G44: 2569
B45: MELANY AIDEE RODRIGUEZ TOLENTINO | F45: 2370 | G45: 2370
B46: VICTORIA POLA CARDENAS | C46: 2770 | D46: 2770 | E46: 2770 | F46: 2770 | G46: 2770 | H46: CONVENIO
B47: ALISSA XIMENA GUTIERRES DOMINGUEZ | F47: 2569 | G47: 2569
B48: ANGEL DE JESUS RIVERA DOMINGUEZ | G48: 2705
B50: 3RO SECUNDARIA
B51: ='3°S'!D34 -> DAMARA GENOVEVA PRIMO MORALES | G51: 2847
B52: HELLEN MONTSERRAT HERNANDEZ GARCIA | C52: 2540 | D52: 2540 | E52: 2540 | F52: 2540 | G52: 2540 | H52: CONVENIO
B53: ROMINA GONZALEZ HERNANDEZ | E53: 3246 | F53: 3246 | G53: 3246 | H53: CONVENIO
B54: EMILIO ESTRADA CABRERA | E54: 3048 | F54: 3048 | G54: 3048 | H54: CONVENIO
B55: PAOLA AYALETH POLA CARDENAS | C55: 2386 | D55: 2386 | E55: 2386 | F55: 2386 | G55: 2386 | H55: CONVENIO
B57: SUMA MENSUAL | C57: =SUM(C5:C56) -> 7696 | D57: =SUM(D5:D56) -> 7696 | E57: =SUM(E5:E56) -> 31971 | F57: =SUM(F5:F56) -> 48427 | G57: =SUM(G5:G56) -> 83191
B59: TOTAL | G59: =C57+D57+E57+F57+G57 -> 178981
